Workbook
Name _ZA10115: #REF!
Name _ZA10121: #REF!
Name _ZA10122: #REF!
Name _ZA10123: #REF!
Name _ZA10124: #REF!
Name _ZA10125: #REF!
Name _ZA10132: #REF!
Name _ZA10133: #REF!
Name _ZA10137: #REF!
Name _ZA10139: #REF!
Name _ZA10143: #REF!
Name _ZA10153: #REF!
Name _ZA10154: #REF!
Name _ZA10155: #REF!
Name _ZA10157: #REF!
Name _ZA10208: #REF!
Name _ZA10209: #REF!
Name _ZA10213: #REF!
Name _ZA10217: #REF!
Name _ZA10223: #REF!
Name _za10230: #REF!
Name _za10231: #REF!
Name _ZA10306: #REF!
Name _ZA10315: #REF!
Name _ZA10317: #REF!
Name _za10318: #REF!
Name _ZA10320: #REF!
Name _ZA10324: #REF!
Name _ZA10326: #REF!
Name _ZA10334: #REF!
Name _ZA10337: #REF!
Name _ZA10339: #REF!
Name _ZA10340: #REF!
Name _ZA10341: #REF!
Name _ZA10345: #REF!
Name _ZA10346: #REF!
Name _ZA10351: #REF!
Name _ZA10353: #REF!
Name _ZA10354: #REF!
Name _ZA10355: #REF!
Name _ZA10375: #REF!
Name _ZA10381: #REF!
Name _ZA10382: #REF!
Name _ZA10384: #REF!
Name _ZA10387: #REF!
Name _ZA10395: #REF!
Name _ZA10398: #REF!
Name _ZA10399: #REF!
Name _ZA10408: #REF!
Name _za10409: #REF!
Name _ZA10413: #REF!
Name _ZA10414: #REF!
Name _ZA10416: #REF!
Name _ZA10417: #REF!
Name _ZA10418: #REF!
Name _ZA10419: #REF!
Name _ZA10421: #REF!
Name _ZA10429: #REF!
Name _za10439: #REF!
Name _ZA10445: #REF!

Sheet Master
A2: 1.Location Name: Akua Madrasa Quarter, Mymensingh. | B2: Enter Location Area | C2: Khilkhet Amtola, Hazibari, House - Kha-53, Khilkhet, Dhaka -1229
A3: Address: Akua Madrasa Quarter, Hajibari Fulbaria Road, Mymensingh. | B3: P&P (Y OR N) | C3: N
A4: 2.Location District - Mymensingh | B4: FR/OWN | C4: FR
A5: 3.P&P (Y OR N) - N | B5: Location Size Range -SFT | C5: 1550
A6: 4.Location Size Range (1100 SFT) | B6: Population Density (H/M/L) | C6: H | G6: Mr. Kaushik | H6: Regional Head
A7: 5.Population Density - H | B7: Income Level (A/B/C) | C7: A | E7: Opened by | G7: Mr. Shadhin | H7: Regional Head
A8: 6.Income Level - A | B8: Commercial Hub | E8: Md. Hasanuzzaman | F8: Head Of Business Expansion | G8: Mr. Azim | H8: Regional Head
A9: 7.Location Type - Residential Hub | B9: Dhaka | E9: Mr. Shamsuzzaman | F9: Assistant Director, Business Expansion | G9: Mr. Emran | H9: Regional Head
A10: 8.Front Fasia Long - 24 feet | B10: Long-feet | C10: 25 | E10: Mr. Mohammad Zaherul Islam | F10: Assistant Director, Business Expansion | G10: Mr. Mahbub | H10: Regional Head
A11: 9.MONTHLY RENT - 45 K | B11: Projected Per Day Sales for this new location | C11: 60000 | E11: Mr. Abdullah Al Masum | F11: Head Of Business Expansion | G11: Mr. Kabir | H11: Regional Head
A12: 10.ADVANCE - 6 Lac | B12: MONTHLY RENT | C12: 61000 | E12: Mr. Lutful Kabir Munna | F12: Head Of Business Expansion | G12: Mr. Riaz | H12: Regional Head
A13: 11.Sales Given By - Mr. Mamun (Sales Daily: 45,000 TK ) | B13: ADVANCE | C13: 1200000 | E13: Mr. Fakhrul Alamgir | F13: Head Of Business Expansion | G13: Mr. Sunny | H13: Regional Head
A14: 12.Opened by (Mr. Abu Sayem) | B14: Outbound Transport | C14: 10000 | E14: Mr. Abu Sayem Mohammad Al Azad | F14: Head Of Business Expansion | G14: Mr. Yusuf | H14: Regional Head
A15: 13.Google Location: https://maps.app.goo.gl/7f4Sa7PpExz26h596?g_st=ac | B15: Sales Given By | C15: Mr. Ersadul Haque | E15: Mr. Mahbub | F15: Regional Head | G15: Ms. Qarin | H15: Regional Head
B16: Opened by | C16: Mr. Fakhrul Alamgir | G16: Mr.Ranjan | H16: Regional Head
B17: Opened by Designation | C17: =VLOOKUP(C16,E8:F15,2,) -> Head Of Business Expansion
B18: Existing No. of outlets around 1 KM radius | C18: 0
A20: (1)Location Name:
A21: (2)Location District-
A22: (3)FR/OWN-
A23: (4)P&P (Y OR N):-
A24: (5)Location Size Range:-….......SFT
A25: (6)Population Density (H/M/L):-
A26: (7)Income Level (A/B/C):-
A27: (8)Location Type:
A28: (9)Front Fasia Long-
A29: (10)MONTHLY RENT:-
A30: (11)ADVANCE:-
A31: (12)Sales Given By:-Mr. …... -- (Sales Daily : …...../- )
... A33: Existing No. of outlets around 1 KM radius

Sheet Stock WRT.O_Final
B4: Status | C4: Sales Revenue | D4: Stock write off (Prov.) | E4: Stock write off (Prov.)%
B5: Barishal FR Non-PNP | C5: 908674821 | D5: 3747205.1 | E5: =D5/C5 -> 0.004123813
B6: Barishal OWN PNP | C6: 108325208 | D6: 670902.24 | E6: =D6/C6 -> 0.0061934082
B7: Chattogram FR Non-PNP | C7: 1549026526 | D7: 7275302.2 | E7: =D7/C7 -> 0.0046966931
B8: Chattogram FR PNP | C8: 92204996 | D8: 313385.28 | E8: =D8/C8 -> 0.0033987885
B9: Chattogram OWN Non-PNP | C9: 132376746 | D9: 614629.69 | E9: =D9/C9 -> 0.0046430337
B10: Chattogram OWN PNP | C10: 1339491716 | D10: 5939811.2 | E10: =D10/C10 -> 0.004434377
B11: Dhaka FR Non-PNP | C11: 6708526730 | D11: 32474401 | E11: =D11/C11 -> 0.0048407649
B12: Dhaka FR PNP | C12: 1223538654 | D12: 9114594.8 | E12: =D12/C12 -> 0.0074493722
B13: Dhaka OWN Non-PNP | C13: 243678729 | D13: 932225.52 | E13: =D13/C13 -> 0.0038256335
B14: Dhaka OWN PNP | C14: 4971522470 | D14: 23651948 | E14: =D14/C14 -> 0.004757486
B15: DhakaGBUD OWN PNP | C15: 5291302809 | D15: 25693923 | E15: =D15/C15 -> 0.0048558784
B16: Khulna FR Non-PNP | C16: 681218749 | D16: 3447527.8 | E16: =D16/C16 -> 0.0050608234
... B28: Sylhet OWN PNP | C28: 827375791 | D28: 4192059.5 | E28: =D28/C28 -> 0.0050666935

Sheet Stock WRT.O
F1: inventory gap | G1: =SUBTOTAL(9,G3:G7966) -> 27604407075 | H1: =SUBTOTAL(9,H3:H7966) -> 4.5675019e+09 | I1: =SUBTOTAL(9,I3:I7966) -> 1.3536976e+08 | J1: =H1/G1 -> 0.16546278 | K1: =I1/G1 -> 0.0049039185
A2: CODE | B2: District | C2: Division | D2: PNP Non PNP status | E2: Status | F2: Feasibility Calc | G2: Sales Revenue | H2: GP | I2: Stock write off (Prov.) | J2: GP% | K2: Stock write off (Prov.)% | L2: GP% | M2: Stock write off (Prov.)%
A3: C001 | B3: Chattogram | C3: Chattogram | D3: PNP | E3: OWN | F3: =CONCATENATE(C3," ",E3," ",D3) -> Chattogram OWN PNP | G3: 11539330 | H3: 1969677.4 | I3: 120945.08 | L3: =(H3/G3)*100 -> 17.069253 | M3: =(I3/G3)*100 -> 1.0481118
A4: C009 | B4: Chattogram | C4: Chattogram | D4: PNP | E4: OWN | F4: =CONCATENATE(C4," ",E4," ",D4) -> Chattogram OWN PNP | G4: 16656264 | H4: 3033316.3 | I4: 64543.47 | L4: =(H4/G4)*100 -> 18.211265 | M4: =(I4/G4)*100 -> 0.38750268
A5: C011 | B5: Cumilla | C5: Chattogram | D5: PNP | E5: OWN | F5: =CONCATENATE(C5," ",E5," ",D5) -> Chattogram OWN PNP | G5: 11423303 | H5: 1972918.2 | I5: 0 | L5: =(H5/G5)*100 -> 17.270996 | M5: =(I5/G5)*100 -> 0
A6: C013 | B6: Cumilla | C6: Chattogram | D6: PNP | E6: OWN | F6: =CONCATENATE(C6," ",E6," ",D6) -> Chattogram OWN PNP | G6: 27426999 | H6: 5257223.1 | I6: 97281.735 | L6: =(H6/G6)*100 -> 19.168058 | M6: =(I6/G6)*100 -> 0.35469333
A7: C015 | B7: Chattogram | C7: Chattogram | D7: PNP | E7: OWN | F7: =CONCATENATE(C7," ",E7," ",D7) -> Chattogram OWN PNP | G7: 11154136 | H7: 1908185.1 | I7: 330768.94 | L7: =(H7/G7)*100 -> 17.107422 | M7: =(I7/G7)*100 -> 2.9654375
A8: C016 | B8: Cumilla | C8: Chattogram | D8: Non-PNP | E8: OWN | F8: =CONCATENATE(C8," ",E8," ",D8) -> Chattogram OWN Non-PNP | G8: 2857188 | H8: 508590.43 | I8: 11428.752 | L8: =(H8/G8)*100 -> 17.800384 | M8: =(I8/G8)*100 -> 0.4
A9: C017 | B9: Feni | C9: Chattogram | D9: PNP | E9: OWN | F9: =CONCATENATE(C9," ",E9," ",D9) -> Chattogram OWN PNP | G9: 9024395 | H9: 1670629.2 | I9: 34423.28 | L9: =(H9/G9)*100 -> 18.512367 | M9: =(I9/G9)*100 -> 0.38144696
A10: C018 | B10: Chattogram | C10: Chattogram | D10: PNP | E10: OWN | F10: =CONCATENATE(C10," ",E10," ",D10) -> Chattogram OWN PNP | G10: 6808373 | H10: 1189576.6 | I10: 0 | L10: =(H10/G10)*100 -> 17.47226 | M10: =(I10/G10)*100 -> 0
A11: C019 | B11: Cox's Bazar | C11: Chattogram | D11: Non-PNP | E11: OWN | F11: =CONCATENATE(C11," ",E11," ",D11) -> Chattogram OWN Non-PNP | G11: 3193573 | H11: 651214.53 | I11: 12774.292 | L11: =(H11/G11)*100 -> 20.391409 | M11: =(I11/G11)*100 -> 0.4
A12: C020 | B12: Brahmanbaria | C12: Chattogram | D12: Non-PNP | E12: OWN | F12: =CONCATENATE(C12," ",E12," ",D12) -> Chattogram OWN Non-PNP | G12: 3971632 | H12: 747317.23 | I12: 15886.528 | L12: =(H12/G12)*100 -> 18.816377 | M12: =(I12/G12)*100 -> 0.4
A13: C021 | B13: Cox's Bazar | C13: Chattogram | D13: PNP | E13: OWN | F13: =CONCATENATE(C13," ",E13," ",D13) -> Chattogram OWN PNP | G13: 9728809 | H13: 1714786.5 | I13: 38392.395 | L13: =(H13/G13)*100 -> 17.625863 | M13: =(I13/G13)*100 -> 0.39462585
A14: D002 | B14: Dhaka | C14: Dhaka | D14: PNP | E14: OWN | F14: =CONCATENATE(C14," ",E14," ",D14) -> Dhaka OWN PNP | G14: 3715386 | H14: 672033.71 | I14: 15502.49 | L14: =(H14/G14)*100 -> 18.087857 | M14: =(I14/G14)*100 -> 0.41725113
... A70: B004 | B70: Barishal | C70: Barishal | D70: PNP | E70: OWN | F70: =CONCATENATE(C70," ",E70," ",D70) -> Barishal OWN PNP | G70: 8600171 | H70: 1433123.2 | I70: 33614.165 | L70: =(H70/G70)*100 -> 16.663892 | M70: =(I70/G70)*100 -> 0.39085461
A71: K006 | B71: Khulna | C71: Khulna | D71: Non-PNP | E71: OWN | F71: =CONCATENATE(C71," ",E71," ",D71) -> Khulna OWN Non-PNP | G71: 5909133 | H71: 974360.45 | L71: =(H71/G71)*100 -> 16.489059 | M71: =(I71/G71)*100 -> 0
A72: K007 | B72: Khulna | C72: Khulna | D72: PNP | E72: OWN | F72: =CONCATENATE(C72," ",E72," ",D72) -> Khulna OWN PNP | G72: 5439059 | H72: 868608.52 | I72: 23937.065 | L72: =(H72/G72)*100 -> 15.969831 | M72: =(I72/G72)*100 -> 0.4400957
A73: K008 | B73: Khulna | C73: Khulna | D73: PNP | E73: OWN | F73: =CONCATENATE(C73," ",E73," ",D73) -> Khulna OWN PNP | G73: 4895825 | H73: 785540.47 | I73: 21707.905 | L73: =(H73/G73)*100 -> 16.045109 | M73: =(I73/G73)*100 -> 0.44339626
A74: R008 | B74: Bogura | C74: Rajshahi | D74: PNP | E74: OWN | F74: =CONCATENATE(C74," ",E74," ",D74) -> Rajshahi OWN PNP | G74: 10935478 | H74: 1792668.2 | I74: 39900.37 | L74: =(H74/G74)*100 -> 16.39314 | M74: =(I74/G74)*100 -> 0.36487084
A75: R009 | B75: Joypurhat | C75: Rajshahi | D75: Non-PNP | E75: OWN | F75: =CONCATENATE(C75," ",E75," ",D75) -> Rajshahi OWN Non-PNP | G75: 2862881 | H75: 540561.7 | I75: 2.1827873e-11 | L75: =(H75/G75)*100 -> 18.881738 | M75: =(I75/G75)*100 -> 7.6244429e-16
A76: R010 | B76: Naogaon | C76: Rajshahi | D76: Non-PNP | E76: OWN | F76: =CONCATENATE(C76," ",E76," ",D76) -> Rajshahi OWN Non-PNP | G76: 3850115 | H76: 696489.97 | L76: =(H76/G76)*100 -> 18.090108 | M76: =(I76/G76)*100 -> 0
A77: R011 | B77: Rajshahi | C77: Rajshahi | D77: PNP | E77: OWN | F77: =CONCATENATE(C77," ",E77," ",D77) -> Rajshahi OWN PNP | G77: 7692364 | H77: 1221016.9 | I77: 30926.27 | L77: =(H77/G77)*100 -> 15.873104 | M77: =(I77/G77)*100 -> 0.40203857
A78: S001 | B78: Sylhet | C78: Sylhet | D78: PNP | E78: OWN | F78: =CONCATENATE(C78," ",E78," ",D78) -> Sylhet OWN PNP | G78: 14173786 | H78: 2384696.4 | I78: 162133.89 | L78: =(H78/G78)*100 -> 16.824696 | M78: =(I78/G78)*100 -> 1.1438997
A79: S002 | B79: Sylhet | C79: Sylhet | D79: PNP | E79: OWN | F79: =CONCATENATE(C79," ",E79," ",D79) -> Sylhet OWN PNP | G79: 7236201 | H79: 1279415.4 | I79: 22396.948 | L79: =(H79/G79)*100 -> 17.680762 | M79: =(I79/G79)*100 -> 0.30951253
A80: S003 | B80: Sylhet | C80: Sylhet | D80: PNP | E80: OWN | F80: =CONCATENATE(C80," ",E80," ",D80) -> Sylhet OWN PNP | G80: 6067286 | H80: 982450.21 | I80: 0 | L80: =(H80/G80)*100 -> 16.192581 | M80: =(I80/G80)*100 -> 0
A81: S006 | B81: Sylhet | C81: Sylhet | D81: PNP | E81: OWN | F81: =CONCATENATE(C81," ",E81," ",D81) -> Sylhet OWN PNP | G81: 14497811 | H81: 2576229 | I81: 53552.59 | L81: =(H81/G81)*100 -> 17.769779 | M81: =(I81/G81)*100 -> 0.36938397
A82: S007 | B82: Sylhet | C82: Sylhet | D82: PNP | E82: OWN | F82: =CONCATENATE(C82," ",E82," ",D82) -> Sylhet OWN PNP | G82: 6051094 | H82: 984409.35 | I82: 80987.116 | L82: =(H82/G82)*100 -> 16.268287 | M82: =(I82/G82)*100 -> 1.338388
A83: S008 | B83: Sylhet | C83: Sylhet | D83: PNP | E83: OWN | F83: =CONCATENATE(C83," ",E83," ",D83) -> Sylhet OWN PNP | G83: 11174878 | H83: 1941708.6 | I83: 35961.95 | L83: =(H83/G83)*100 -> 17.375658 | M83: =(I83/G83)*100 -> 0.32181067
A84: S009 | B84: Moulvibazar | C84: Sylhet | D84: PNP | E84: OWN | F84: =CONCATENATE(C84," ",E84," ",D84) -> Sylhet OWN PNP | G84: 5851452 | H84: 1038132.6 | I84: 63597.779 | L84: =(H84/G84)*100 -> 17.741452 | M84: =(I84/G84)*100 -> 1.0868718
A85: C012 | B85: Brahmanbaria | C85: Chattogram | D85: Non-PNP | E85: FR | F85: =CONCATENATE(C85," ",E85," ",D85) -> Chattogram FR Non-PNP | G85: 2212323 | H85: 388037.73 | I85: 8849.292 | L85: =(H85/G85)*100 -> 17.539831 | M85: =(I85/G85)*100 -> 0.4
A86: D079 | B86: Dhaka | C86: Dhaka | D86: Non-PNP | E86: FR | F86: =CONCATENATE(C86," ",E86," ",D86) -> Dhaka FR Non-PNP | G86: 3610102 | H86: 603507.49 | I86: 14440.408 | L86: =(H86/G86)*100 -> 16.717187 | M86: =(I86/G86)*100 -> 0.4
A87: D080 | B87: Dhaka | C87: Dhaka | D87: Non-PNP | E87: FR | F87: =CONCATENATE(C87," ",E87," ",D87) -> Dhaka FR Non-PNP | G87: 2000247 | H87: 333069.81 | I87: 8000.988 | L87: =(H87/G87)*100 -> 16.651434 | M87: =(I87/G87)*100 -> 0.4
A88: D081 | B88: Dhaka | C88: Dhaka | D88: Non-PNP | E88: FR | F88: =CONCATENATE(C88," ",E88," ",D88) -> Dhaka FR Non-PNP | G88: 4511067 | H88: 746105.66 | I88: 18044.268 | L88: =(H88/G88)*100 -> 16.53945 | M88: =(I88/G88)*100 -> 0.4
... A657: F705 | B657: Dhaka | C657: Dhaka | D657: Non-PNP | E657: FR | F657: =CONCATENATE(C657," ",E657," ",D657) -> Dhaka FR Non-PNP | G657: 1608083 | H657: 277469.05 | I657: 6432.332 | L657: =(H657/G657)*100 -> 17.254647 | M657: =(I657/G657)*100 -> 0.4
A658: F706 | B658: Cumilla | C658: Chattogram | D658: Non-PNP | E658: FR | F658: =CONCATENATE(C658," ",E658," ",D658) -> Chattogram FR Non-PNP | G658: 528001 | H658: 104574.33 | L658: =(H658/G658)*100 -> 19.805707 | M658: =(I658/G658)*100 -> 0
A659: F709 | B659: Gaibandha | C659: Rangpur | D659: Non-PNP | E659: FR | F659: =CONCATENATE(C659," ",E659," ",D659) -> Rangpur FR Non-PNP | G659: 625133 | H659: 118519.52 | L659: =(H659/G659)*100 -> 18.959088 | M659: =(I659/G659)*100 -> 0
A660: F710 | B660: Dhaka | C660: Dhaka | D660: Non-PNP | E660: FR | F660: =CONCATENATE(C660," ",E660," ",D660) -> Dhaka FR Non-PNP | G660: 811384 | H660: 142434.3 | L660: =(H660/G660)*100 -> 17.554487 | M660: =(I660/G660)*100 -> 0
A661: F711 | B661: Sylhet | C661: Sylhet | D661: Non-PNP | E661: FR | F661: =CONCATENATE(C661," ",E661," ",D661) -> Sylhet FR Non-PNP | G661: 4543 | H661: 992.39811 | L661: =(H661/G661)*100 -> 21.844554 | M661: =(I661/G661)*100 -> 0
A662: F712 | B662: Tangail | C662: Dhaka | D662: Non-PNP | E662: FR | F662: =CONCATENATE(C662," ",E662," ",D662) -> Dhaka FR Non-PNP | G662: 2241 | H662: 84.684535 | L662: =(H662/G662)*100 -> 3.7788726 | M662: =(I662/G662)*100 -> 0
A663: F715 | B663: Sylhet | C663: Sylhet | D663: Non-PNP | E663: FR | F663: =CONCATENATE(C663," ",E663," ",D663) -> Sylhet FR Non-PNP | G663: 18919 | H663: 3143.8083 | L663: =(H663/G663)*100 -> 16.617201 | M663: =(I663/G663)*100 -> 0
A664: F716 | B664: Dhaka | C664: Dhaka | D664: Non-PNP | E664: FR | F664: =CONCATENATE(C664," ",E664," ",D664) -> Dhaka FR Non-PNP | G664: 113 | H664: 28.769816 | L664: =(H664/G664)*100 -> 25.460014 | M664: =(I664/G664)*100 -> 0
A665: F718 | B665: Dhaka | C665: Dhaka | D665: Non-PNP | E665: FR | F665: =CONCATENATE(C665," ",E665," ",D665) -> Dhaka FR Non-PNP | G665: 28455 | H665: 5442.2855 | L665: =(H665/G665)*100 -> 19.125937 | M665: =(I665/G665)*100 -> 0
A666: F719 | B666: Dhaka | C666: Dhaka | D666: Non-PNP | E666: FR | F666: =CONCATENATE(C666," ",E666," ",D666) -> Dhaka FR Non-PNP | G666: 9208 | H666: 1807.0384 | L666: =(H666/G666)*100 -> 19.624657 | M666: =(I666/G666)*100 -> 0
A667: F721 | B667: Barishal | C667: Barishal | D667: Non-PNP | E667: FR | F667: =CONCATENATE(C667," ",E667," ",D667) -> Barishal FR Non-PNP | G667: 1560 | H667: 54.88 | L667: =(H667/G667)*100 -> 3.5179487 | M667: =(I667/G667)*100 -> 0
A668: F722 | B668: Khulna | C668: Khulna | D668: Non-PNP | E668: FR | F668: =CONCATENATE(C668," ",E668," ",D668) -> Khulna FR Non-PNP | G668: 8440 | H668: 1412.0271 | L668: =(H668/G668)*100 -> 16.730179 | M668: =(I668/G668)*100 -> 0
A669: F723 | B669: Noakhali | C669: Chattogram | D669: Non-PNP | E669: FR | F669: =CONCATENATE(C669," ",E669," ",D669) -> Chattogram FR Non-PNP | G669: 9104 | H669: 2079.9609 | L669: =(H669/G669)*100 -> 22.84667 | M669: =(I669/G669)*100 -> 0
... A676: F732 | B676: Panchagarh | C676: Rangpur | D676: Non-PNP | E676: FR | F676: =CONCATENATE(C676," ",E676," ",D676) -> Rangpur FR Non-PNP | G676: 49118 | H676: 9500.1572 | L676: =(H676/G676)*100 -> 19.341498 | M676: =(I676/G676)*100 -> 0
A677: C001 | B677: Chattogram | C677: Chattogram | D677: PNP | E677: OWN | F677: =CONCATENATE(C677," ",E677," ",D677) -> Chattogram OWN PNP | G677: 10774164 | H677: 1775016.2 | I677: 37052.665 | L677: =(H677/G677)*100 -> 16.474746 | M677: =(I677/G677)*100 -> 0.34390292
A678: C009 | B678: Chattogram | C678: Chattogram | D678: PNP | E678: OWN | F678: =CONCATENATE(C678," ",E678," ",D678) -> Chattogram OWN PNP | G678: 14586702 | H678: 2516628.4 | I678: -4.3655746e-11 | L678: =(H678/G678)*100 -> 17.252895 | M678: =(I678/G678)*100 -> -2.9928455e-16
A679: C011 | B679: Cumilla | C679: Chattogram | D679: PNP | E679: OWN | F679: =CONCATENATE(C679," ",E679," ",D679) -> Chattogram OWN PNP | G679: 11187352 | H679: 1796071.6 | I679: 34886.84 | L679: =(H679/G679)*100 -> 16.054483 | M679: =(I679/G679)*100 -> 0.3118418
A680: C013 | B680: Cumilla | C680: Chattogram | D680: PNP | E680: OWN | F680: =CONCATENATE(C680," ",E680," ",D680) -> Chattogram OWN PNP | G680: 24878212 | H680: 4546793 | I680: 88976.435 | L680: =(H680/G680)*100 -> 18.276205 | M680: =(I680/G680)*100 -> 0.35764803
A681: C015 | B681: Chattogram | C681: Chattogram | D681: PNP | E681: OWN | F681: =CONCATENATE(C681," ",E681," ",D681) -> Chattogram OWN PNP | G681: 9874780 | H681: 1635913.3 | I681: 11646.426 | L681: =(H681/G681)*100 -> 16.56658 | M681: =(I681/G681)*100 -> 0.11794111
A682: C016 | B682: Cumilla | C682: Chattogram | D682: Non-PNP | E682: OWN | F682: =CONCATENATE(C682," ",E682," ",D682) -> Chattogram OWN Non-PNP | G682: 2964470 | H682: 491743.64 | I682: 11857.88 | L682: =(H682/G682)*100 -> 16.587911 | M682: =(I682/G682)*100 -> 0.4
A683: C017 | B683: Feni | C683: Chattogram | D683: PNP | E683: OWN | F683: =CONCATENATE(C683," ",E683," ",D683) -> Chattogram OWN PNP | G683: 9604979 | H683: 1697107 | I683: 32068.645 | L683: =(H683/G683)*100 -> 17.669033 | M683: =(I683/G683)*100 -> 0.33387522
A684: C018 | B684: Chattogram | C684: Chattogram | D684: PNP | E684: OWN | F684: =CONCATENATE(C684," ",E684," ",D684) -> Chattogram OWN PNP | G684: 6304029 | H684: 1099212 | I684: -5.0931703e-11 | L684: =(H684/G684)*100 -> 17.436659 | M684: =(I684/G684)*100 -> -8.0792305e-16
A685: C019 | B685: Cox's Bazar | C685: Chattogram | D685: Non-PNP | E685: OWN | F685: =CONCATENATE(C685," ",E685," ",D685) -> Chattogram OWN Non-PNP | G685: 2762454 | H685: 557108.9 | I685: 0 | L685: =(H685/G685)*100 -> 20.167174 | M685: =(I685/G685)*100 -> 0
A686: C020 | B686: Brahmanbaria | C686: Chattogram | D686: Non-PNP | E686: OWN | F686: =CONCATENATE(C686," ",E686," ",D686) -> Chattogram OWN Non-PNP | G686: 3467881 | H686: 666883.18 | I686: 178060.98 | L686: =(H686/G686)*100 -> 19.230279 | M686: =(I686/G686)*100 -> 5.1345758
A687: C021 | B687: Cox's Bazar | C687: Chattogram | D687: PNP | E687: OWN | F687: =CONCATENATE(C687," ",E687," ",D687) -> Chattogram OWN PNP | G687: 8265719 | H687: 1507120.4 | I687: 32286.285 | L687: =(H687/G687)*100 -> 18.233385 | M687: =(I687/G687)*100 -> 0.39060468
A688: D002 | B688: Dhaka | C688: Dhaka | D688: PNP | E688: OWN | F688: =CONCATENATE(C688," ",E688," ",D688) -> Dhaka OWN PNP | G688: 3479344 | H688: 633725.34 | I688: 14414.02 | L688: =(H688/G688)*100 -> 18.213932 | M688: =(I688/G688)*100 -> 0.41427407
... A2255: F460 | B2255: Dhaka | C2255: Dhaka | D2255: Non-PNP | E2255: FR | F2255: =CONCATENATE(C2255," ",E2255," ",D2255) -> Dhaka FR Non-PNP | G2255: 2614945 | H2255: 451462.88 | I2255: 10459.78 | L2255: =(H2255/G2255)*100 -> 17.264718 | M2255: =(I2255/G2255)*100 -> 0.4
A2256: F461 | B2256: Dinajpur | C2256: Rangpur | D2256: Non-PNP | E2256: FR | F2256: =CONCATENATE(C2256," ",E2256," ",D2256) -> Rangpur FR Non-PNP | G2256: 1974607 | H2256: 285625.47 | L2256: =(H2256/G2256)*100 -> 14.464927 | M2256: =(I2256/G2256)*100 -> 0
A2257: F462 | B2257: Dhaka | C2257: Dhaka | D2257: Non-PNP | E2257: FR | F2257: =CONCATENATE(C2257," ",E2257," ",D2257) -> Dhaka FR Non-PNP | G2257: 2836422 | H2257: 518423.21 | I2257: 11345.688 | L2257: =(H2257/G2257)*100 -> 18.277365 | M2257: =(I2257/G2257)*100 -> 0.4
A2258: F463 | B2258: Madaripur | C2258: Dhaka | D2258: Non-PNP | E2258: FR | F2258: =CONCATENATE(C2258," ",E2258," ",D2258) -> Dhaka FR Non-PNP | G2258: 1501318 | H2258: 206212.9 | I2258: 6005.272 | L2258: =(H2258/G2258)*100 -> 13.735457 | M2258: =(I2258/G2258)*100 -> 0.4
A2259: F464 | B2259: Gazipur | C2259: Dhaka | D2259: Non-PNP | E2259: FR | F2259: =CONCATENATE(C2259," ",E2259," ",D2259) -> Dhaka FR Non-PNP | G2259: 1734878 | H2259: 356636.32 | I2259: 6939.512 | L2259: =(H2259/G2259)*100 -> 20.556853 | M2259: =(I2259/G2259)*100 -> 0.4
A2260: F465 | B2260: Dhaka | C2260: Dhaka | D2260: Non-PNP | E2260: FR | F2260: =CONCATENATE(C2260," ",E2260," ",D2260) -> Dhaka FR Non-PNP | G2260: 1973560 | H2260: 393134.59 | I2260: 7894.24 | L2260: =(H2260/G2260)*100 -> 19.920073 | M2260: =(I2260/G2260)*100 -> 0.4
A2261: F466 | B2261: Bhola | C2261: Barishal | D2261: Non-PNP | E2261: FR | F2261: =CONCATENATE(C2261," ",E2261," ",D2261) -> Barishal FR Non-PNP | G2261: 1107584 | H2261: 227080.37 | I2261: 4430.336 | L2261: =(H2261/G2261)*100 -> 20.502316 | M2261: =(I2261/G2261)*100 -> 0.4
A2262: F467 | B2262: Patuakhali | C2262: Barishal | D2262: Non-PNP | E2262: FR | F2262: =CONCATENATE(C2262," ",E2262," ",D2262) -> Barishal FR Non-PNP | G2262: 1235992 | H2262: 229791.64 | I2262: 4943.968 | L2262: =(H2262/G2262)*100 -> 18.591677 | M2262: =(I2262/G2262)*100 -> 0.4
A2263: F468 | B2263: Lalmonirhat | C2263: Rangpur | D2263: Non-PNP | E2263: FR | F2263: =CONCATENATE(C2263," ",E2263," ",D2263) -> Rangpur FR Non-PNP | G2263: 885547 | H2263: 185280.51 | I2263: 3542.188 | L2263: =(H2263/G2263)*100 -> 20.922719 | M2263: =(I2263/G2263)*100 -> 0.4
A2264: F469 | B2264: Dhaka | C2264: Dhaka | D2264: Non-PNP | E2264: FR | F2264: =CONCATENATE(C2264," ",E2264," ",D2264) -> Dhaka FR Non-PNP | G2264: 957980 | H2264: 171518.07 | I2264: 3831.92 | L2264: =(H2264/G2264)*100 -> 17.904139 | M2264: =(I2264/G2264)*100 -> 0.4
A2265: F471 | B2265: Cumilla | C2265: Chattogram | D2265: Non-PNP | E2265: FR | F2265: =CONCATENATE(C2265," ",E2265," ",D2265) -> Chattogram FR Non-PNP | G2265: 1181682 | H2265: 173272.35 | I2265: 4726.728 | L2265: =(H2265/G2265)*100 -> 14.663196 | M2265: =(I2265/G2265)*100 -> 0.4
A2266: F472 | B2266: Dhaka | C2266: Dhaka | D2266: Non-PNP | E2266: FR | F2266: =CONCATENATE(C2266," ",E2266," ",D2266) -> Dhaka FR Non-PNP | G2266: 1501793 | H2266: 238441.13 | I2266: 6007.172 | L2266: =(H2266/G2266)*100 -> 15.877097 | M2266: =(I2266/G2266)*100 -> 0.4
A2267: F473 | B2267: Natore | C2267: Rajshahi | D2267: Non-PNP | E2267: FR | F2267: =CONCATENATE(C2267," ",E2267," ",D2267) -> Rajshahi FR Non-PNP | G2267: 1030726 | H2267: 161427.02 | I2267: 4122.904 | L2267: =(H2267/G2267)*100 -> 15.661487 | M2267: =(I2267/G2267)*100 -> 0.4
A2268: F474 | B2268: Meherpur | C2268: Khulna | D2268: Non-PNP | E2268: FR | F2268: =CONCATENATE(C2268," ",E2268," ",D2268) -> Khulna FR Non-PNP | G2268: 1385555 | H2268: 196622.43 | I2268: 5542.22 | L2268: =(H2268/G2268)*100 -> 14.190879 | M2268: =(I2268/G2268)*100 -> 0.4
... A5504: F332 | B5504: Naogaon | C5504: Rajshahi | D5504: Non-PNP | E5504: FR | F5504: =CONCATENATE(C5504," ",E5504," ",D5504) -> Rajshahi FR Non-PNP | G5504: 745550 | H5504: 117374.76 | I5504: 2982.2 | L5504: =(H5504/G5504)*100 -> 15.743379 | M5504: =(I5504/G5504)*100 -> 0.4
A5505: F333 | B5505: Chapainawabganj | C5505: Rajshahi | D5505: Non-PNP | E5505: FR | F5505: =CONCATENATE(C5505," ",E5505," ",D5505) -> Rajshahi FR Non-PNP | G5505: 15 | H5505: 3.48 | L5505: =(H5505/G5505)*100 -> 23.2 | M5505: =(I5505/G5505)*100 -> 0
A5506: F334 | B5506: Dinajpur | C5506: Rangpur | D5506: Non-PNP | E5506: FR | F5506: =CONCATENATE(C5506," ",E5506," ",D5506) -> Rangpur FR Non-PNP | G5506: 1665168 | H5506: 259862.93 | I5506: 6660.672 | L5506: =(H5506/G5506)*100 -> 15.605808 | M5506: =(I5506/G5506)*100 -> 0.4
A5507: F335 | B5507: Barishal | C5507: Barishal | D5507: Non-PNP | E5507: FR | F5507: =CONCATENATE(C5507," ",E5507," ",D5507) -> Barishal FR Non-PNP | G5507: 3621767 | H5507: 554971.57 | I5507: 14487.068 | L5507: =(H5507/G5507)*100 -> 15.323227 | M5507: =(I5507/G5507)*100 -> 0.4
A5508: F336 | B5508: Madaripur | C5508: Dhaka | D5508: Non-PNP | E5508: FR | F5508: =CONCATENATE(C5508," ",E5508," ",D5508) -> Dhaka FR Non-PNP | G5508: 3334266 | H5508: 449314.96 | I5508: 0 | L5508: =(H5508/G5508)*100 -> 13.475678 | M5508: =(I5508/G5508)*100 -> 0
A5509: F337 | B5509: Khulna | C5509: Khulna | D5509: Non-PNP | E5509: FR | F5509: =CONCATENATE(C5509," ",E5509," ",D5509) -> Khulna FR Non-PNP | G5509: 1825400 | H5509: 269248.34 | I5509: 7301.6 | L5509: =(H5509/G5509)*100 -> 14.750101 | M5509: =(I5509/G5509)*100 -> 0.4
A5510: F338 | B5510: Gaibandha | C5510: Rangpur | D5510: Non-PNP | E5510: FR | F5510: =CONCATENATE(C5510," ",E5510," ",D5510) -> Rangpur FR Non-PNP | G5510: 3268830 | H5510: 598300.91 | I5510: 13075.32 | L5510: =(H5510/G5510)*100 -> 18.303213 | M5510: =(I5510/G5510)*100 -> 0.4
A5511: F339 | B5511: Dinajpur | C5511: Rangpur | D5511: Non-PNP | E5511: FR | F5511: =CONCATENATE(C5511," ",E5511," ",D5511) -> Rangpur FR Non-PNP | G5511: 675429 | H5511: 93675.978 | I5511: 2701.716 | L5511: =(H5511/G5511)*100 -> 13.869108 | M5511: =(I5511/G5511)*100 -> 0.4
A5512: F340 | B5512: Barishal | C5512: Barishal | D5512: Non-PNP | E5512: FR | F5512: =CONCATENATE(C5512," ",E5512," ",D5512) -> Barishal FR Non-PNP | G5512: 2038030 | H5512: 325604.16 | I5512: 8152.12 | L5512: =(H5512/G5512)*100 -> 15.976416 | M5512: =(I5512/G5512)*100 -> 0.4
A5513: F342 | B5513: Mymensingh | C5513: Mymensingh | D5513: Non-PNP | E5513: FR | F5513: =CONCATENATE(C5513," ",E5513," ",D5513) -> Mymensingh FR Non-PNP | G5513: 1414698 | H5513: 216176.75 | I5513: 36734.875 | L5513: =(H5513/G5513)*100 -> 15.28077 | M5513: =(I5513/G5513)*100 -> 2.5966585
A5514: F343 | B5514: Brahmanbaria | C5514: Chattogram | D5514: Non-PNP | E5514: FR | F5514: =CONCATENATE(C5514," ",E5514," ",D5514) -> Chattogram FR Non-PNP | G5514: 1493234 | H5514: 225057.11 | I5514: 5972.936 | L5514: =(H5514/G5514)*100 -> 15.071791 | M5514: =(I5514/G5514)*100 -> 0.4
A5515: F344 | B5515: Kishoreganj | C5515: Mymensingh | D5515: Non-PNP | E5515: FR | F5515: =CONCATENATE(C5515," ",E5515," ",D5515) -> Mymensingh FR Non-PNP | G5515: 925505 | H5515: 136089.97 | I5515: 3702.02 | L5515: =(H5515/G5515)*100 -> 14.704401 | M5515: =(I5515/G5515)*100 -> 0.4
A5516: F346 | B5516: Jashore | C5516: Khulna | D5516: Non-PNP | E5516: FR | F5516: =CONCATENATE(C5516," ",E5516," ",D5516) -> Khulna FR Non-PNP | G5516: 1789284 | H5516: 294201.99 | I5516: 7157.136 | L5516: =(H5516/G5516)*100 -> 16.442443 | M5516: =(I5516/G5516)*100 -> 0.4
A5517: F347 | B5517: Narsingdi | C5517: Dhaka | D5517: Non-PNP | E5517: FR | F5517: =CONCATENATE(C5517," ",E5517," ",D5517) -> Dhaka FR Non-PNP | G5517: 1666443 | H5517: 280336.57 | I5517: 6665.772 | L5517: =(H5517/G5517)*100 -> 16.822452 | M5517: =(I5517/G5517)*100 -> 0.4
... A7966: F614 | B7966: Lakshmipur | C7966: Chattogram | D7966: Non-PNP | E7966: FR | F7966: =CONCATENATE(C7966," ",E7966," ",D7966) -> Chattogram FR Non-PNP | G7966: 15745 | H7966: 2168.5146 | I7966: 62.98 | L7966: =(H7966/G7966)*100 -> 13.772719 | M7966: =(I7966/G7966)*100 -> 0.4

Sheet Sales forecasting tools
A1: Sales Forecasting Format
A2: SL | B2: Description | C2: Weightage | D2: Target | E2: Measuring Tools | F2: Answers | G2: Marking Criteria | H2: Mark | I2: Achievement | AC2: GP% | AD2: Basket | AE2: Stock write off (Prov.)%
A3: =ROW()-2 -> 1 | B3: Location Size Range | E3: SFT | F3: =Master!C5 -> 1550 | N3: =VLOOKUP(F3,$X$3:$Y$20597,2,0) -> 1501 TO 1800 | X3: 300 | Y3: 0 TO 800 | AB3: Chattogram FR Non-PNP | AC3: 0.16528831 | AD3: 485.08971 | AE3: 0.0046966931
A4: =ROW()-2 -> 2 | B4: Population Density/Residential Area | C4: 0.18 | D4: 100 | E4: High/Medium/Low | F4: =Master!C6 -> H | H4: =IF(F4="H",100,IF(F4="M",70,IF(F4="L",50,0))) -> 100 | I4: =(H4/D4)*C4 -> 0.18 | K4: =F8 -> M | N4: =F4 -> H | X4: 301 | Y4: 0 TO 800 | AB4: Dhaka FR Non-PNP | AC4: 0.15969476 | AD4: 426.75837 | AE4: 0.0048407649
A5: =ROW()-2 -> 3 | B5: House Rent/Income Level | C5: 0.15 | D5: 100 | E5: A/B/C | F5: =Master!C7 -> A | H5: =IF(F5="A",100,IF(F5="B",70,IF(F5="C",50,0))) -> 100 | I5: =(H5/D5)*C5 -> 0.15 | J5: Location Type | N5: =F5 -> A | X5: 302 | Y5: 0 TO 800
A6: =ROW()-2 -> 4 | B6: Location Type | C6: 0.18 | D6: 100 | E6: =Master!B8 -> Commercial Hub | H6: =_xlfn.XLOOKUP(E6,$T$6:$T$13,$U$6:$U$13,0) -> 85 | I6: =(H6/D6)*C6 -> 0.153 | N6: =E6 -> Commercial Hub | T6: Commercial Hub | U6: 85 | X6: 303 | Y6: 0 TO 800 | AB6: Barishal FR Non-PNP | AC6: 0.15601993 | AD6: 416.77936 | AE6: 0.004123813
A7: =ROW()-2 -> 5 | B7: Avg. Sales of Departmental Stores/Competitor Store | C7: 0.08 | D7: 100 | E7: Avg per Day Sales | F7: 25000 | H7: =IF(F7=0,0,IF(F7>=45000,100,IF(F7>=35000,80,IF(F7>=25000,60,IF(F7>=15000,40,20))))) -> 60 | I7: =(H7/D7)*C7 -> 0.048 | N7: =C19 -> Dhaka | T7: High Street W Residential Block | U7: 90 | X7: 304 | Y7: 0 TO 800 | AB7: Mymensingh FR Non-PNP | AC7: 0.15572779 | AD7: 418.87151 | AE7: 0.0041957585
A8: =ROW()-2 -> 6 | B8: Road Status | C8: 0.08 | D8: 100 | E8: Main Road/Support Road | F8: M | H8: =IF(F8="M",100,IF(F8="S",80,0)) -> 100 | I8: =(H8/D8)*C8 -> 0.08 | N8: =C20 -> N | T8: Within the Mahalla | U8: 65 | X8: 305 | Y8: 0 TO 800 | AB8: Sylhet FR PNP | AC8: 0.14642073 | AD8: 451.98979 | AE8: 0.0044435185
A9: =ROW()-2 -> 7 | B9: Mosque/Mandir/Girza | C9: 0.08 | D9: 100 | E9: How Many | F9: 2 | H9: =IF(F9>=2,100,IF(F9=1,80,0)) -> 100 | I9: =(H9/D9)*C9 -> 0.08 | N9: =IF(C19="Dhaka","Inside Dhaka","Outside Dhaka") -> Inside Dhaka | T9: Industrial | U9: 60 | X9: 306 | Y9: 0 TO 800 | AB9: Chattogram FR PNP | AC9: 0.1748718 | AD9: 573.29022 | AE9: 0.0033987885
A10: =ROW()-2 -> 8 | B10: School/College/University | C10: 0.07 | D10: 100 | E10: How Many | F10: 2 | H10: =IF(F10>=2,100,IF(F10=1,80,0)) -> 100 | I10: =(H10/D10)*C10 -> 0.07 | T10: High Street | U10: 70 | X10: 307 | Y10: 0 TO 800 | AB10: Rajshahi FR Non-PNP | AC10: 0.15744786 | AD10: 440.13984 | AE10: 0.0065464264
A11: =ROW()-2 -> 9 | B11: Bank/Office/ATM BOOTH | C11: 0.06 | D11: 100 | E11: How Many | F11: 2 | H11: =IF(F11>=2,100,IF(F11=1,80,0)) -> 100 | I11: =(H11/D11)*C11 -> 0.06 | T11: Gated Community | U11: 100 | X11: 308 | Y11: 0 TO 800 | AB11: Khulna FR Non-PNP | AC11: 0.16189873 | AD11: 410.65205 | AE11: 0.0050608234
A12: =ROW()-2 -> 10 | B12: CNG, Bus, Train Station/ Pick & Drop | C12: 0.04 | D12: 100 | E12: Y/N | F12: Y | H12: =IF(F12="Y",100,0) -> 100 | I12: =(H12/D12)*C12 -> 0.04 | N12: =CONCATENATE(N3,N4,N8) -> 1501 TO 1800HN | T12: Inside the Mall | U12: 55 | X12: 309 | Y12: 0 TO 800 | AB12: Rangpur FR PNP | AC12: 0.15913809 | AD12: 820.18193 | AE12: 0.0039854998
A13: =ROW()-2 -> 11 | B13: Front Fasia | C13: 0.02 | D13: 100 | E13: Long-feet | F13: =Master!C10 -> 25 | H13: =IF(F13=0,0,IF(F13>=20,100,80)) -> 100 | I13: =(H13/D13)*C13 -> 0.02 | T13: High Street W Institutions | U13: 75 | X13: 310 | Y13: 0 TO 800 | AB13: Rangpur FR Non-PNP | AC13: 0.15282818 | AD13: 427.30991 | AE13: 0.0049513318
A14: =ROW()-2 -> 12 | B14: Signboard Visibility | C14: 0.04 | D14: 100 | E14: High/Medium | F14: H | H14: =IF(F14="H",100,IF(F14="M",80)) -> 100 | I14: =(H14/D14)*C14 -> 0.04 | N14: =CONCATENATE(N3,N4,N8) -> 1501 TO 1800HN | X14: 311 | Y14: 0 TO 800 | AB14: Khulna FR PNP | AC14: 0.14902038 | AD14: 726.30333 | AE14: 0.004041028
A15: =ROW()-2 -> 13 | B15: Hotel & Restaurant & Hospital/ Club | C15: 0.02 | D15: 100 | E15: How Many | F15: 3 | H15: =IF(F15>=3,100,IF(F15=2,80,0)) -> 100 | I15: =(H15/D15)*C15 -> 0.02 | X15: 312 | Y15: 0 TO 800 | AB15: Rajshahi OWN Non-PNP | AC15: 0.17797353 | AD15: 531.42859
B16: Total | C16: =SUM(C4:C15) -> 1 | E16: Total | I16: =SUM(I4:I15) -> 0.941 | X16: 313 | Y16: 0 TO 800 | AB16: Dhaka FR PNP | AC16: 0.15766804 | AD16: 414.02385 | AE16: 0.0074493722
E17: Category wise Sales Mix | X17: 314 | Y17: 0 TO 800 | AB17: Rajshahi FR PNP | AC17: 0.16 | AD17: 368.04767 | AE17: 0.0055
B18: Enter Location Area | C18: =Master!C2 -> Khilkhet Amtola, Hazibari, House - Kha-53, Khilkhet, Dhaka -1229 | E18: Category | H18: Per Day Sales | I18: Monthly Sales | X18: 315 | Y18: 0 TO 800 | AB18: Sylhet FR Non-PNP | AC18: 0.15249915 | AD18: 277.68537 | AE18: 0.0049894139
B19: Enter Division Name | C19: =Master!B9 -> Dhaka | D19: 4 | E19: Baby Care | H19: =(IF($C$20="Y",U21,V21))*$H$37 -> 808.35627 | I19: =H19*30 -> 24250.688 | N19: =Master!C4 -> FR | X19: 316 | Y19: 0 TO 800
B20: P&P (Y OR N) | C20: =Master!C3 -> N | D20: 6 | E20: Baby Food | H20: =(IF($C$20="Y",U22,V22))*$H$37 -> 702.91272 | I20: =H20*30 -> 21087.382 | N20: =IF(C20="Y","PNP","Non-PNP") -> Non-PNP | S20: FR PNP | T20: FR NON-PNP | U20: FR PNP Con% | V20: FR NON-PNP Con% | X20: 317 | Y20: 0 TO 800 | AB20: Barishal OWN PNP | AC20: 0.15686241 | AD20: 565.56883 | AE20: 0.0061934082
B21: GP% | C21: =VLOOKUP($N$21,$AB$3:$AC$30,2,0) -> 0.15969476 | D21: 8 | E21: Beverage & Tobacco | H21: =(IF($C$20="Y",U23,V23))*$H$37 -> 3167.9267 | I21: =H21*30 -> 95037.8 | N21: =CONCATENATE(C19," ",N19," ",N20) -> Dhaka FR Non-PNP | R21: Baby Care | S21: 67721.612 | T21: 21262.176 | U21: =IFERROR(S21/$S$39,0) -> 0.01001768 | V21: =IFERROR(T21/$T$39,0) -> 0.013472604 | X21: 318 | Y21: 0 TO 800 | AB21: Chattogram OWN PNP | AC21: 0.1638435 | AD21: 865.0753 | AE21: 0.004434377
B22: Dhaka/out of Dhaka | C22: =IF(C19="Dhaka","Dhaka","Out Of Dhaka") -> Dhaka | D22: 12 | E22: Dairy | H22: =(IF($C$20="Y",U24,V24))*$H$37 -> 4270.3409 | I22: =H22*30 -> 128110.23 | R22: Baby Food | S22: 45340.417 | T22: 18488.697 | U22: =IFERROR(S22/$S$39,0) -> 0.0067069548 | V22: =IFERROR(T22/$T$39,0) -> 0.011715212 | X22: 319 | Y22: 0 TO 800 | AB22: Chattogram OWN Non-PNP | AC22: 0.18723579 | AD22: 492.64322 | AE22: 0.0046430337
B23: Sales (Reference) | C23: =VLOOKUP($B$43,'Reference (LocationType & Dens '!$E:$H,2,0)/30 -> 119126.78 | D23: 24 | E23: Home Care | H23: =(IF($C$20="Y",U25,V25))*$H$37 -> 4814.3045 | I23: =H23*30 -> 144429.14 | R23: Beverage & Tobacco | S23: 293387.48 | T23: 83325.902 | U23: =IFERROR(S23/$S$39,0) -> 0.043399172 | V23: =IFERROR(T23/$T$39,0) -> 0.052798778 | X23: 320 | Y23: 0 TO 800 | AB23: Dhaka OWN PNP | AC23: 0.16750762 | AD23: 722.70586 | AE23: 0.004757486
B24: FF (Reference)/Day | C24: =VLOOKUP($B$43,'Reference (LocationType & Dens '!$E:$H,3,0)/30 -> 217.24375 | D24: 30 | E24: Kitchen Additives | H24: =(IF($C$20="Y",U26,V26))*$H$37 -> 3156.0873 | I24: =H24*30 -> 94682.62 | R24: Dairy | S24: 455189.69 | T24: 112322.68 | U24: =IFERROR(S24/$S$39,0) -> 0.067333669 | V24: =IFERROR(T24/$T$39,0) -> 0.071172348 | X24: 321 | Y24: 0 TO 800 | AB24: Dhaka GBUD OWN PNP | AC24: 0.17314745 | AD24: 1006.6521 | AE24: 0.005
B25: Basket (Reference) | C25: =C23/C24 -> 548.35539 | D25: 34 | E25: Packaged Foods | H25: =(IF($C$20="Y",U27,V27))*$H$37 -> 15440.716 | I25: =H25*30 -> 463221.49 | R25: Home Care | S25: 419172.22 | T25: 126630.54 | U25: =IFERROR(S25/$S$39,0) -> 0.062005806 | V25: =IFERROR(T25/$T$39,0) -> 0.080238408 | X25: 322 | Y25: 0 TO 800 | AB25: Dhaka OWN Non-PNP | AC25: 0.16518962 | AD25: 487.88106 | AE25: 0.0038256335
B26: Profit (Reference) | C26: =VLOOKUP($B$43,'Reference (LocationType & Dens '!$E:$I,5,0) -> 257639.5 | E26: Personal Care | H26: =(IF($C$20="Y",U28,V28))*$H$37 -> 8345.0713 | I26: =H26*30 -> 250352.14 | R26: Kitchen Additives | S26: 297874.87 | T26: 83014.493 | U26: =IFERROR(S26/$S$39,0) -> 0.044062967 | V26: =IFERROR(T26/$T$39,0) -> 0.052601456 | X26: 323 | Y26: 0 TO 800 | AB26: Khulna OWN Non-PNP | AC26: 0.15726401 | AD26: 602.31421 | AE26: 0.003492622
D27: 38 | R27: Packaged Foods | S27: 1398193.8 | T27: 406136.81 | U27: =IFERROR(S27/$S$39,0) -> 0.20682701 | V27: =IFERROR(T27/$T$39,0) -> 0.25734527 | X27: 324 | Y27: 0 TO 800 | AB27: Khulna OWN PNP | AC27: 0.14245785 | AD27: 524.92641 | AE27: 0.0035921925
B28: Projected Basket Size (Reference) | C28: =VLOOKUP($N$21,$AB$3:$AD$30,3,0) -> 426.75837 | D28: 10 | E28: Commodities | H28: =(IF($C$20="Y",U30,V30))*$H$37 -> 16321.108 | I28: =H28*30 -> 489633.24 | R28: Personal Care | S28: 768455.95 | T28: 219500.22 | U28: =IFERROR(S28/$S$39,0) -> 0.1136734 | V28: =IFERROR(T28/$T$39,0) -> 0.13908452 | X28: 325 | Y28: 0 TO 800 | AB28: Rajshahi OWN PNP | AC28: 0.15853757 | AD28: 635.38947 | AE28: 0.005524236
B29: Projected Per Day Sales for this new location | C29: =Master!C11 -> 60000 | D29: 14 | E29: Electronics & Appl | H29: =(IF($C$20="Y",U31,V31))*$H$37 -> 620.14259 | I29: =H29*30 -> 18604.278 | X29: 326 | Y29: 0 TO 800
B30: Projected Daily Footfall for this new location | C30: =C29/C28 -> 140.59478 | D30: 16 | E30: Gift & Toys | H30: =(IF($C$20="Y",U32,V32))*$H$37 -> 506.64627 | I30: =H30*30 -> 15199.388 | R30: Commodities | S30: 1316426.5 | T30: 429293.73 | U30: =IFERROR(S30/$S$39,0) -> 0.19473163 | V30: =IFERROR(T30/$T$39,0) -> 0.27201846 | X30: 327 | Y30: 0 TO 800 | AB30: Sylhet OWN PNP | AC30: 0.15802485 | AD30: 774.63847 | AE30: 0.0050666935
B31: Existing No. of outlets around 1 KM radius | D31: 20 | E31: Home Accessories | H31: =(IF($C$20="Y",U33,V33))*$H$37 -> 1061.3033 | I31: =H31*30 -> 31839.1 | R31: Electronics & Appl | S31: 70182.755 | T31: 16311.596 | U31: =IFERROR(S31/$S$39,0) -> 0.010381743 | V31: =IFERROR(T31/$T$39,0) -> 0.01033571 | X31: 328 | Y31: 0 TO 800
D32: 22 | E32: Home Appliance | H32: =(IF($C$20="Y",U34,V34))*$H$37 -> 410.11046 | I32: =H32*30 -> 12303.314 | R32: Gift & Toys | S32: 41069.459 | T32: 13326.305 | U32: =IFERROR(S32/$S$39,0) -> 0.0060751758 | V32: =IFERROR(T32/$T$39,0) -> 0.0084441045 | X32: 329 | Y32: 0 TO 800
D33: 44 | E33: Stationeries | H33: =(IF($C$20="Y",U35,V35))*$H$37 -> 228.22896 | I33: =H33*30 -> 6846.8687 | R33: Home Accessories | S33: 118616.29 | T33: 27915.437 | U33: =IFERROR(S33/$S$39,0) -> 0.017546245 | V33: =IFERROR(T33/$T$39,0) -> 0.017688389 | X33: 330 | Y33: 0 TO 800
D34: 32 | E34: Life Style | H34: =(IF($C$20="Y",U36,V36))*$H$37 -> 70.707615 | I34: =H34*30 -> 2121.2285 | R34: Home Appliance | S34: 27205.62 | T34: 10787.126 | U34: =IFERROR(S34/$S$39,0) -> 0.0040243755 | V34: =IFERROR(T34/$T$39,0) -> 0.0068351743 | X34: 331 | Y34: 0 TO 800
D35: 36 | E35: Perishables | H35: =(IF($C$20="Y",U37,V37))*$H$37 -> 0 | I35: =H35*30 -> 0 | R35: Stationeries | S35: 22702.811 | T35: 6003.101 | U35: =IFERROR(S35/$S$39,0) -> 0.0033583 | V35: =IFERROR(T35/$T$39,0) -> 0.0038038159 | X35: 332 | Y35: 0 TO 800
D36: 40 | E36: Protein | H36: =(IF($C$20="Y",U38,V38))*$H$37 -> 76.03702 | I36: =H36*30 -> 2281.1106 | R36: Life Style | S36: 22075.085 | T36: 1859.8208 | U36: =IFERROR(S36/$S$39,0) -> 0.0032654441 | V36: =IFERROR(T36/$T$39,0) -> 0.0011784603 | X36: 333 | Y36: 0 TO 800
H37: =C29 -> 60000 | I37: =H37*30 -> 1800000 | R37: Perishables | S37: 262461.61 | T37: 0 | U37: =IFERROR(S37/$S$39,0) -> 0.038824481 | V37: =IFERROR(T37/$T$39,0) -> 0 | X37: 334 | Y37: 0 TO 800
R38: Protein | S38: 1134133 | T38: 2000 | U38: =IFERROR(S38/$S$39,0) -> 0.16776596 | V38: =IFERROR(T38/$T$39,0) -> 0.0012672837 | X38: 335 | Y38: 0 TO 800
S39: =SUM(S21:S38) -> 6760209.2 | T39: =SUM(T21:T38) -> 1578178.6 | U39: =SUM(U21:U38) -> 1 | V39: =SUM(V21:V38) -> 1 | X39: 336 | Y39: 0 TO 800
X40: 337 | Y40: 0 TO 800
X41: 338 | Y41: 0 TO 800
X42: 339 | Y42: 0 TO 800
B43: =CONCATENATE(E6,F4,C19) -> Commercial HubHDhaka | X43: 340 | Y43: 0 TO 800
X44: 341 | Y44: 0 TO 800
X45: 342 | Y45: 0 TO 800
X46: 343 | Y46: 0 TO 800
X47: 344 | Y47: 0 TO 800
X48: 345 | Y48: 0 TO 800
X49: 346 | Y49: 0 TO 800
X50: 347 | Y50: 0 TO 800
X51: 348 | Y51: 0 TO 800
X52: 349 | Y52: 0 TO 800
X53: 350 | Y53: 0 TO 800
X54: 351 | Y54: 0 TO 800
X55: 352 | Y55: 0 TO 800
... X19703: 20000 | Y19703: 10001 & ABOVE

Sheet Sheet3
A1: 0 TO 800
A2: 801 TO 1000
A3: 1001 TO 1200
A4: 1201 TO 1500
A5: 1501 TO 1800
A6: 1801 TO 2000
A7: 2001 TO 2500
A8: 2501 TO 3000
A9: 3001 TO 5000
A10: 5001 TO 8000
A11: 8001 TO 10000
A12: 10001 & ABOVE

Sheet Reference (LocationType & Dens 
B3: Location Type | C3: Population Density | D3: Division | E3: Unique | F3: AVG Sales | G3: AVG FF | H3: AVG BS | I3: AVG Profit
B4: Commercial Hub | C4: H | D4: Barishal | E4: Commercial HubHBarishal | F4: 4387198 | G4: 7620 | H4: 575.74777 | I4: 187701.59
B5: Commercial Hub | C5: H | D5: Chattogram | E5: Commercial HubHChattogram | F5: 3002746.1 | G5: 5077.7143 | H5: 591.35784 | I5: 231129.94
B6: Commercial Hub | C6: H | D6: Dhaka | E6: Commercial HubHDhaka | F6: 3573803.4 | G6: 6517.3125 | H6: 548.35539 | I6: 257639.5
B7: Commercial Hub | C7: H | D7: DhakaGBUD | E7: Commercial HubHDhakaGBUD | F7: 1887336 | G7: 5767 | H7: 327.26478 | I7: 89633.599
B8: Commercial Hub | C8: H | D8: Mymensingh | E8: Commercial HubHMymensingh | F8: 2873429.3 | G8: 5657 | H8: 507.94225 | I8: 204543.76
B9: Commercial Hub | C9: H | D9: Rajshahi | E9: Commercial HubHRajshahi | F9: 4299581.4 | G9: 7577 | H9: 567.45169 | I9: 345932.7
B10: Commercial Hub | C10: H | D10: Rangpur | E10: Commercial HubHRangpur | F10: 2622345.3 | G10: 4846.6667 | H10: 541.06162 | I10: 68957.558
B11: Commercial Hub | C11: L | D11: Barishal | E11: Commercial HubLBarishal | F11: 774963.5 | G11: 2387.25 | H11: 324.62603 | I11: -181.49326
B12: Commercial Hub | C12: L | D12: Chattogram | E12: Commercial HubLChattogram | F12: 1240578.9 | G12: 2583.625 | H12: 480.16987 | I12: 65745.572
B13: Commercial Hub | C13: L | D13: Dhaka | E13: Commercial HubLDhaka | F13: 1247453.8 | G13: 3001.0952 | H13: 415.66617 | I13: 57830.306
B14: Commercial Hub | C14: L | D14: Khulna | E14: Commercial HubLKhulna | F14: 1709327 | G14: 3937.75 | H14: 434.08723 | I14: 114852.05
B15: Commercial Hub | C15: L | D15: Mymensingh | E15: Commercial HubLMymensingh | F15: 1033326.6 | G15: 2525 | H15: 409.23826 | I15: 20861.937
... B117: Within the Mahalla | C117: M | D117: Rangpur | E117: Within the MahallaMRangpur | F117: 1460791.5 | G117: 3528.3333 | H117: 414.01743 | I117: 22961.877

Sheet INFORMATION
A3: BUSINESS FEASIBILITY INFORMATION
A4: PROJECT NAME | B4: ='Sales forecasting tools'!C18 -> Khilkhet Amtola, Hazibari, House - Kha-53, Khilkhet, Dhaka -1229
D5: MANPOWER ALLOCATION
A6: SFT | B6: ='Sales forecasting tools'!F3 -> 1550 | E6: Qty | F6: Salary | G6: Total Amount
A7: GP SHARE | B7: 0.4 | D7: OM-Parmanent | E7: =IF(UPPER(TRIM($B$14))="Y",INDEX(MANPOWER!$C$25:$AF$38,MATCH(D7,MANPOWER!$B$25:$B$38,0),MATCH($B$9,{0,1500000,1900000,2200000,2500000,2800000,3100000,3400000,3700000,4000000,4300000,4600000,4900000,5200000,5500000,5800000,6100000,6400000,6700000,7000000,7300000,7600000,7900000,8200000,8500000,8800000,9100000,9400000,9700000,10000000},1)),INDEX(MANPOWER!$C$4:$AF$17,MATCH(D7,MANPOWER!$B$4:$B$17,0),MATCH($B$9,{0,1500000,1900000,2200000,2500000,2800000,3100000,3400000,3700000,4000000,4300000,4600000,4900000,5200000,5500000,5800000,6100000,6400000,6700000,7000000,7300000,7600000,7900000,8200000,8500000,8800000,9100000,9400000,9700000,10000000},1))) -> 1 | F7: 23000 | G7: =F7*E7 -> 23000
A8: SALES PER DAY | B8: ='Sales forecasting tools'!C29 -> 60000 | D8: ICMO-Parmanent | E8: =IF(UPPER(TRIM($B$14))="Y",INDEX(MANPOWER!$C$25:$AF$38,MATCH(D8,MANPOWER!$B$25:$B$38,0),MATCH($B$9,{0,1500000,1900000,2200000,2500000,2800000,3100000,3400000,3700000,4000000,4300000,4600000,4900000,5200000,5500000,5800000,6100000,6400000,6700000,7000000,7300000,7600000,7900000,8200000,8500000,8800000,9100000,9400000,9700000,10000000},1)),INDEX(MANPOWER!$C$4:$AF$17,MATCH(D8,MANPOWER!$B$4:$B$17,0),MATCH($B$9,{0,1500000,1900000,2200000,2500000,2800000,3100000,3400000,3700000,4000000,4300000,4600000,4900000,5200000,5500000,5800000,6100000,6400000,6700000,7000000,7300000,7600000,7900000,8200000,8500000,8800000,9100000,9400000,9700000,10000000},1))) -> 0 | F8: 15000 | G8: =F8*E8 -> 0 | J8: Y | K8: 430000
A9: MONTH SALES | B9: =IFERROR(B8*30,0) -> 1800000 | D9: Duty officer | E9: =IF(UPPER(TRIM($B$14))="Y",INDEX(MANPOWER!$C$25:$AF$38,MATCH(D9,MANPOWER!$B$25:$B$38,0),MATCH($B$9,{0,1500000,1900000,2200000,2500000,2800000,3100000,3400000,3700000,4000000,4300000,4600000,4900000,5200000,5500000,5800000,6100000,6400000,6700000,7000000,7300000,7600000,7900000,8200000,8500000,8800000,9100000,9400000,9700000,10000000},1)),INDEX(MANPOWER!$C$4:$AF$17,MATCH(D9,MANPOWER!$B$4:$B$17,0),MATCH($B$9,{0,1500000,1900000,2200000,2500000,2800000,3100000,3400000,3700000,4000000,4300000,4600000,4900000,5200000,5500000,5800000,6100000,6400000,6700000,7000000,7300000,7600000,7900000,8200000,8500000,8800000,9100000,9400000,9700000,10000000},1))) -> 1 | F9: 12000 | G9: =F9*E9 -> 12000 | J9: N | K9: 330000
A10: GP% | B10: ='Sales forecasting tools'!C21 -> 0.15969476
A11: BASKET SIZE | B11: ='Sales forecasting tools'!C28 -> 426.75837
A12: FF/Day | B12: ='Sales forecasting tools'!C30 -> 140.59478 | D12: CG | E12: =IF(UPPER(TRIM($B$14))="Y",INDEX(MANPOWER!$C$25:$AF$38,MATCH(D12,MANPOWER!$B$25:$B$38,0),MATCH($B$9,{0,1500000,1900000,2200000,2500000,2800000,3100000,3400000,3700000,4000000,4300000,4600000,4900000,5200000,5500000,5800000,6100000,6400000,6700000,7000000,7300000,7600000,7900000,8200000,8500000,8800000,9100000,9400000,9700000,10000000},1)),INDEX(MANPOWER!$C$4:$AF$17,MATCH(D12,MANPOWER!$B$4:$B$17,0),MATCH($B$9,{0,1500000,1900000,2200000,2500000,2800000,3100000,3400000,3700000,4000000,4300000,4600000,4900000,5200000,5500000,5800000,6100000,6400000,6700000,7000000,7300000,7600000,7900000,8200000,8500000,8800000,9100000,9400000,9700000,10000000},1))) -> 2 | F12: 8000 | G12: =F12*E12 -> 16000
A13: OTHER INCOME % | B13: 0.03 | D13: COMMODITY | E13: =IF(UPPER(TRIM($B$14))="Y",INDEX(MANPOWER!$C$25:$AF$38,MATCH(D13,MANPOWER!$B$25:$B$38,0),MATCH($B$9,{0,1500000,1900000,2200000,2500000,2800000,3100000,3400000,3700000,4000000,4300000,4600000,4900000,5200000,5500000,5800000,6100000,6400000,6700000,7000000,7300000,7600000,7900000,8200000,8500000,8800000,9100000,9400000,9700000,10000000},1)),INDEX(MANPOWER!$C$4:$AF$17,MATCH(D13,MANPOWER!$B$4:$B$17,0),MATCH($B$9,{0,1500000,1900000,2200000,2500000,2800000,3100000,3400000,3700000,4000000,4300000,4600000,4900000,5200000,5500000,5800000,6100000,6400000,6700000,7000000,7300000,7600000,7900000,8200000,8500000,8800000,9100000,9400000,9700000,10000000},1))) -> 0 | F13: 8000 | G13: =F13*E13 -> 0
A14: P&P (Y/N) | B14: ='Sales forecasting tools'!C20 -> N | D14: PROTEIN | E14: =IF(UPPER(TRIM($B$14))="Y",INDEX(MANPOWER!$C$25:$AF$38,MATCH(D14,MANPOWER!$B$25:$B$38,0),MATCH($B$9,{0,1500000,1900000,2200000,2500000,2800000,3100000,3400000,3700000,4000000,4300000,4600000,4900000,5200000,5500000,5800000,6100000,6400000,6700000,7000000,7300000,7600000,7900000,8200000,8500000,8800000,9100000,9400000,9700000,10000000},1)),INDEX(MANPOWER!$C$4:$AF$17,MATCH(D14,MANPOWER!$B$4:$B$17,0),MATCH($B$9,{0,1500000,1900000,2200000,2500000,2800000,3100000,3400000,3700000,4000000,4300000,4600000,4900000,5200000,5500000,5800000,6100000,6400000,6700000,7000000,7300000,7600000,7900000,8200000,8500000,8800000,9100000,9400000,9700000,10000000},1))) -> 0 | F14: 10000 | G14: =F14*E14 -> 0
A15: MONTHLY RENT | B15: =Master!C12 -> 61000 | D15: PERISHABLES | E15: =IF(UPPER(TRIM($B$14))="Y",INDEX(MANPOWER!$C$25:$AF$38,MATCH(D15,MANPOWER!$B$25:$B$38,0),MATCH($B$9,{0,1500000,1900000,2200000,2500000,2800000,3100000,3400000,3700000,4000000,4300000,4600000,4900000,5200000,5500000,5800000,6100000,6400000,6700000,7000000,7300000,7600000,7900000,8200000,8500000,8800000,9100000,9400000,9700000,10000000},1)),INDEX(MANPOWER!$C$4:$AF$17,MATCH(D15,MANPOWER!$B$4:$B$17,0),MATCH($B$9,{0,1500000,1900000,2200000,2500000,2800000,3100000,3400000,3700000,4000000,4300000,4600000,4900000,5200000,5500000,5800000,6100000,6400000,6700000,7000000,7300000,7600000,7900000,8200000,8500000,8800000,9100000,9400000,9700000,10000000},1))) -> 0 | F15: 8000 | G15: =F15*E15 -> 0
A16: ADVANCE | B16: =Master!C13 -> 1200000 | D16: GM & LIFESTYLE | E16: =IF(UPPER(TRIM($B$14))="Y",INDEX(MANPOWER!$C$25:$AF$38,MATCH(D16,MANPOWER!$B$25:$B$38,0),MATCH($B$9,{0,1500000,1900000,2200000,2500000,2800000,3100000,3400000,3700000,4000000,4300000,4600000,4900000,5200000,5500000,5800000,6100000,6400000,6700000,7000000,7300000,7600000,7900000,8200000,8500000,8800000,9100000,9400000,9700000,10000000},1)),INDEX(MANPOWER!$C$4:$AF$17,MATCH(D16,MANPOWER!$B$4:$B$17,0),MATCH($B$9,{0,1500000,1900000,2200000,2500000,2800000,3100000,3400000,3700000,4000000,4300000,4600000,4900000,5200000,5500000,5800000,6100000,6400000,6700000,7000000,7300000,7600000,7900000,8200000,8500000,8800000,9100000,9400000,9700000,10000000},1))) -> 0 | F16: 8000 | G16: =F16*E16 -> 0
A17: CEP VALUE | B17: =VLOOKUP(B14,$J$8:$K$9,2,) -> 330000 | D17: POS | E17: =IF(UPPER(TRIM($B$14))="Y",INDEX(MANPOWER!$C$25:$AF$38,MATCH(D17,MANPOWER!$B$25:$B$38,0),MATCH($B$9,{0,1500000,1900000,2200000,2500000,2800000,3100000,3400000,3700000,4000000,4300000,4600000,4900000,5200000,5500000,5800000,6100000,6400000,6700000,7000000,7300000,7600000,7900000,8200000,8500000,8800000,9100000,9400000,9700000,10000000},1)),INDEX(MANPOWER!$C$4:$AF$17,MATCH(D17,MANPOWER!$B$4:$B$17,0),MATCH($B$9,{0,1500000,1900000,2200000,2500000,2800000,3100000,3400000,3700000,4000000,4300000,4600000,4900000,5200000,5500000,5800000,6100000,6400000,6700000,7000000,7300000,7600000,7900000,8200000,8500000,8800000,9100000,9400000,9700000,10000000},1))) -> 1 | F17: 9500 | G17: =F17*E17 -> 9500
A18: AREA OUT OF DHAKA (Y/N) | B18: =IF('Sales forecasting tools'!C19="Dhaka","N","Y") -> N | D18: PORTER | E18: =IF(UPPER(TRIM($B$14))="Y",INDEX(MANPOWER!$C$25:$AF$38,MATCH(D18,MANPOWER!$B$25:$B$38,0),MATCH($B$9,{0,1500000,1900000,2200000,2500000,2800000,3100000,3400000,3700000,4000000,4300000,4600000,4900000,5200000,5500000,5800000,6100000,6400000,6700000,7000000,7300000,7600000,7900000,8200000,8500000,8800000,9100000,9400000,9700000,10000000},1)),INDEX(MANPOWER!$C$4:$AF$17,MATCH(D18,MANPOWER!$B$4:$B$17,0),MATCH($B$9,{0,1500000,1900000,2200000,2500000,2800000,3100000,3400000,3700000,4000000,4300000,4600000,4900000,5200000,5500000,5800000,6100000,6400000,6700000,7000000,7300000,7600000,7900000,8200000,8500000,8800000,9100000,9400000,9700000,10000000},1))) -> 0 | F18: 7500 | G18: =F18*E18 -> 0
A19: DECORATION COST | B19: =MAX(1500000,IF(B14="N",B6*1000,B6*1000+2000000)) -> 1550000 | D19: BSM | E19: =IF(UPPER(TRIM($B$14))="Y",INDEX(MANPOWER!$C$25:$AF$38,MATCH(D19,MANPOWER!$B$25:$B$38,0),MATCH($B$9,{0,1500000,1900000,2200000,2500000,2800000,3100000,3400000,3700000,4000000,4300000,4600000,4900000,5200000,5500000,5800000,6100000,6400000,6700000,7000000,7300000,7600000,7900000,8200000,8500000,8800000,9100000,9400000,9700000,10000000},1)),INDEX(MANPOWER!$C$4:$AF$17,MATCH(D19,MANPOWER!$B$4:$B$17,0),MATCH($B$9,{0,1500000,1900000,2200000,2500000,2800000,3100000,3400000,3700000,4000000,4300000,4600000,4900000,5200000,5500000,5800000,6100000,6400000,6700000,7000000,7300000,7600000,7900000,8200000,8500000,8800000,9100000,9400000,9700000,10000000},1))) -> 0 | F19: 11000 | G19: =F19*E19 -> 0
D20: BK STR | E20: =IF(UPPER(TRIM($B$14))="Y",INDEX(MANPOWER!$C$25:$AF$38,MATCH(D20,MANPOWER!$B$25:$B$38,0),MATCH($B$9,{0,1500000,1900000,2200000,2500000,2800000,3100000,3400000,3700000,4000000,4300000,4600000,4900000,5200000,5500000,5800000,6100000,6400000,6700000,7000000,7300000,7600000,7900000,8200000,8500000,8800000,9100000,9400000,9700000,10000000},1)),INDEX(MANPOWER!$C$4:$AF$17,MATCH(D20,MANPOWER!$B$4:$B$17,0),MATCH($B$9,{0,1500000,1900000,2200000,2500000,2800000,3100000,3400000,3700000,4000000,4300000,4600000,4900000,5200000,5500000,5800000,6100000,6400000,6700000,7000000,7300000,7600000,7900000,8200000,8500000,8800000,9100000,9400000,9700000,10000000},1))) -> 0 | F20: 8000 | G20: =F20*E20 -> 0
D21: SECURITY | E21: =IF(UPPER(TRIM($B$14))="Y",INDEX(MANPOWER!$C$25:$AF$38,MATCH(D21,MANPOWER!$B$25:$B$38,0),MATCH($B$9,{0,1500000,1900000,2200000,2500000,2800000,3100000,3400000,3700000,4000000,4300000,4600000,4900000,5200000,5500000,5800000,6100000,6400000,6700000,7000000,7300000,7600000,7900000,8200000,8500000,8800000,9100000,9400000,9700000,10000000},1)),INDEX(MANPOWER!$C$4:$AF$17,MATCH(D21,MANPOWER!$B$4:$B$17,0),MATCH($B$9,{0,1500000,1900000,2200000,2500000,2800000,3100000,3400000,3700000,4000000,4300000,4600000,4900000,5200000,5500000,5800000,6100000,6400000,6700000,7000000,7300000,7600000,7900000,8200000,8500000,8800000,9100000,9400000,9700000,10000000},1))) -> 0 | F21: 11500 | G21: =F21*E21 -> 0
D22: CLEANER | E22: =IF(UPPER(TRIM($B$14))="Y",INDEX(MANPOWER!$C$25:$AF$38,MATCH(D22,MANPOWER!$B$25:$B$38,0),MATCH($B$9,{0,1500000,1900000,2200000,2500000,2800000,3100000,3400000,3700000,4000000,4300000,4600000,4900000,5200000,5500000,5800000,6100000,6400000,6700000,7000000,7300000,7600000,7900000,8200000,8500000,8800000,9100000,9400000,9700000,10000000},1)),INDEX(MANPOWER!$C$4:$AF$17,MATCH(D22,MANPOWER!$B$4:$B$17,0),MATCH($B$9,{0,1500000,1900000,2200000,2500000,2800000,3100000,3400000,3700000,4000000,4300000,4600000,4900000,5200000,5500000,5800000,6100000,6400000,6700000,7000000,7300000,7600000,7900000,8200000,8500000,8800000,9100000,9400000,9700000,10000000},1))) -> 0 | F22: 7500 | G22: =F22*E22 -> 0
E23: =SUM(E7:E22) -> 5 | G23: =SUM(G7:G22) -> 60500

Sheet AUTO GENERATED FEASIBILITY
A1: =INFORMATION!B4 -> Khilkhet Amtola, Hazibari, House - Kha-53, Khilkhet, Dhaka -1229 | C1: Prepare Date | E1: =TODAY() -> 46295
B2: Number/ Percentage | C2: 1st Month | D2: 2nd Month | E2: 3rd Month | G2: 1st year | H2: 2nd year | I2: 3rd year | J2: 4th year | K2: 5th year | L2: Total
A3: Fixed asset investment( CEP Value) | C3: =INFORMATION!B17 -> 330000 | G3: =C3 -> 330000
A4: Average Stock | C4: =C6*1650 -> 2557500 | D4: =C4 -> 2557500 | E4: =D4 -> 2557500 | G4: =E4 -> 2557500 | H4: =G4 -> 2557500 | I4: =H4 -> 2557500 | J4: =I4 -> 2557500 | K4: =J4 -> 2557500
A5: Stock Holding Days | C5: =(C4*30)/(C10*(1-C14)) -> 50.725615 | D5: =(D4*30)/(D10*(1-D14)) -> 50.725615 | E5: =(E4*30)/(E10*(1-E14)) -> 50.725615 | G5: =(G4*365)/(G10*(1-G14)) -> 51.430137 | H5: =(H4*365)/(H10*(1-H14)) -> 46.029319 | I5: =(I4*365)/(I10*(1-I14)) -> 41.944906 | J5: =(J4*365)/(J10*(1-J14)) -> 38.223142 | K5: =(K4*365)/(K10*(1-K14)) -> 35.476844
A6: Area in SFT | C6: ='Sales forecasting tools'!F3 -> 1550 | D6: =C6 -> 1550 | E6: =D6 -> 1550 | G6: =E6 -> 1550 | H6: =G6 -> 1550 | I6: =H6 -> 1550 | J6: =I6 -> 1550 | K6: =J6 -> 1550
A7: Day Average Foot Fall | C7: =C9/C8 -> 140.59478 | D7: =D9/D8 -> 140.59478 | E7: =E9/E8 -> 140.59478 | G7: =AVERAGE(C7:E7) -> 140.59478 | H7: =H9/H8 -> 151.40977 | I7: =I9/I8 -> 160.14495 | J7: =J9/J8 -> 169.38408 | K7: =K9/K8 -> 175.89885
A8: Average Basket Size | C8: =INFORMATION!B11 -> 426.75837 | D8: =C8 -> 426.75837 | E8: =D8 -> 426.75837 | G8: =G9/G7 -> 426.75837 | H8: =G8*1.04 -> 443.8287 | I8: =H8*1.04 -> 461.58185 | J8: =I8*1.04 -> 480.04512 | K8: =J8*1.04 -> 499.24693
A9: Day Average Sales | C9: =INFORMATION!B8 -> 60000 | D9: =D10/30 -> 60000 | E9: =E10/30 -> 60000 | G9: =G10/360 -> 60000 | H9: =H10/360 -> 67200 | I9: =I10/360 -> 73920 | J9: =J10/360 -> 81312 | K9: =K10/360 -> 87816.96
A10: Sales Revenue | C10: =C9*30 -> 1800000 | D10: =C10 -> 1800000 | E10: =D10 -> 1800000 | G10: =C10*12 -> 21600000 | H10: =G10*1.12 -> 24192000 | I10: =H10*1.1 -> 26611200 | J10: =I10*1.1 -> 29272320 | K10: =J10*1.08 -> 31614106 | L10: =SUM(G10:K10) -> 1.3328963e+08
A12: COGS | C12: =C10-C13 -> 1512549.4 | D12: =D10-D13 -> 1512549.4 | E12: =E10-E13 -> 1512549.4 | G12: =G10-G13 -> 18150593 | H12: =H10-H13 -> 20280280 | I12: =I10-I13 -> 22255086 | J12: =J10-J13 -> 24422050 | K12: =K10-K13 -> 26312586 | L12: =SUM(G12:K12) -> 1.114206e+08
A13: GPV | C13: =C10*C14 -> 287450.56 | D13: =D10*D14 -> 287450.56 | E13: =E10*E14 -> 287450.56 | G13: =G10*G14 -> 3449406.7 | H13: =H10*H14 -> 3911719.5 | I13: =I10*I14 -> 4356113.9 | J13: =J10*J14 -> 4850269.9 | K13: =K10*K14 -> 5301519.7 | L13: =SUM(G13:K13) -> 21869030
A14: GP % | C14: =INFORMATION!B10 -> 0.15969476 | D14: =C14 -> 0.15969476 | E14: =D14 -> 0.15969476 | G14: =E14 -> 0.15969476 | H14: =G14+0.2% -> 0.16169476 | I14: =H14+0.2% -> 0.16369476 | J14: =I14+0.2% -> 0.16569476 | K14: =J14+0.2% -> 0.16769476 | L14: =L13/L10 -> 0.16407151
A15: Space Rent & Other Income | B15: =INFORMATION!B13 -> 0.03 | C15: =$B$15*C10 -> 54000 | D15: =$B$15*D10 -> 54000 | E15: =$B$15*E10 -> 54000 | G15: =$B$15*G10 -> 648000 | H15: =$B$15*H10 -> 725760 | I15: =$B$15*I10 -> 798336 | J15: =$B$15*J10 -> 878169.6 | K15: =$B$15*K10 -> 948423.17 | L15: =SUM(G15:K15) -> 3998688.8
A16: TOTAL INCOME | C16: =C15+C13 -> 341450.56 | D16: =D15+D13 -> 341450.56 | E16: =E15+E13 -> 341450.56 | G16: =G15+G13 -> 4097406.7 | H16: =H15+H13 -> 4637479.5 | I16: =I15+I13 -> 5154449.9 | J16: =J15+J13 -> 5728439.5 | K16: =K15+K13 -> 6249942.9 | L16: =SUM(G16:K16) -> 25867718
A18: Franchisee Commission | B18: =INFORMATION!B7 -> 0.4 | C18: =($B$18*C16) -> 136580.22 | D18: =($B$18*D16) -> 136580.22 | E18: =($B$18*E16) -> 136580.22 | G18: =($B$18*G16) -> 1638962.7 | H18: =($B$18*H16) -> 1854991.8 | I18: =($B$18*I16) -> 2061779.9 | J18: =($B$18*J16) -> 2291375.8 | K18: =($B$18*K16) -> 2499977.1 | L18: =SUM(G18:K18) -> 10347087
A19: Rent | L19: =SUM(G19:K19) -> 0
A20: Outlet staff salary (Contractual) | B20: =SUM(INFORMATION!E9:E20) -> 4 | C20: =SUM(INFORMATION!G9:G20) -> 37500 | D20: =C20 -> 37500 | E20: =D20 -> 37500 | G20: =SUM(C20:E20)*4 -> 450000 | H20: =G20+G20*8% -> 486000 | I20: =H20+H20*8% -> 524880 | J20: =I20+I20*8% -> 566870.4 | K20: =J20+J20*8% -> 612220.03 | L20: =SUM(G20:K20) -> 2639970.4
A21: Outlet staff salary (Permanent) | B21: =SUM(INFORMATION!E7) -> 1 | C21: =SUM(INFORMATION!G7:G8) -> 23000 | D21: =C21 -> 23000 | E21: =D21 -> 23000 | G21: =SUM(C21:E21)*4 -> 276000 | H21: =G21+G21*8% -> 298080 | I21: =H21+H21*8% -> 321926.4 | J21: =I21+I21*8% -> 347680.51 | K21: =J21+J21*8% -> 375494.95 | L21: =SUM(G21:K21) -> 1619181.9
A22: Outlet staff salary (Support team) | C22: 0 | D22: =C22 -> 0 | E22: =D22 -> 0 | L22: =SUM(G22:K22) -> 0
A23: Depreciation | C23: =(C3*0.7)/60 -> 3850 | D23: =C23 -> 3850 | E23: =D23 -> 3850 | G23: =SUM(C23:E23)*4 -> 46200 | H23: =G23 -> 46200 | I23: =H23 -> 46200 | J23: =I23 -> 46200 | K23: =J23 -> 46200 | L23: =SUM(G23:K23) -> 231000
A24: Consumption-Consumable | B24: =IF('Sales forecasting tools'!C20="Y",0.8%,0.65%) -> 0.0065 | C24: =$B$24*C10 -> 11700 | D24: =$B$24*D10 -> 11700 | E24: =$B$24*E10 -> 11700 | G24: =$B$24*G10 -> 140400 | H24: =$B$24*H10 -> 157248 | I24: =$B$24*I10 -> 172972.8 | J24: =$B$24*J10 -> 190270.08 | K24: =$B$24*K10 -> 205491.69 | L24: =SUM(G24:K24) -> 866382.57
A25: Electricity & Utility | C25: 0 | D25: 0 | E25: 0 | L25: =SUM(G25:K25) -> 0
A26: Product Wastage | B26: =INFORMATION!B14 -> N | C26: =IF($B$26="Y",(C10*0.23%),(C10*0.06%)) -> 1080 | D26: =IF($B$26="Y",(D10*0.58%),0) -> 0 | E26: =IF($B$26="Y",(E10*0.58%),0) -> 0 | G26: =IF($B$26="Y",(G10*0.58%),0) -> 0 | H26: =IF($B$26="Y",(H10*0.58%),0) -> 0 | I26: =IF($B$26="Y",(I10*0.58%),0) -> 0 | J26: =IF($B$26="Y",(J10*0.58%),0) -> 0 | K26: =IF($B$26="Y",(K10*0.58%),0) -> 0 | L26: =SUM(G26:K26) -> 0
A27: Maintenance | C27: 0 | D27: 0 | E27: 0 | L27: =SUM(G27:K27) -> 0
A28: Security | B28: =INFORMATION!E21 -> 0 | C28: =INFORMATION!G21 -> 0 | D28: =C28 -> 0 | E28: =D28 -> 0 | G28: =SUM(C28:E28)*4 -> 0 | H28: =G28*108% -> 0 | I28: =H28*108% -> 0 | J28: =I28*108% -> 0 | K28: =J28*108% -> 0 | L28: =SUM(G28:K28) -> 0
A29: Generator Running Expense | G29: =SUM(C29:E29)*4 -> 0 | H29: =G29+G29*5% -> 0 | I29: =H29+H29*5% -> 0 | J29: =I29+I29*5% -> 0 | K29: =J29+J29*5% -> 0 | L29: =SUM(G29:K29) -> 0
A30: Cleaning | B30: =INFORMATION!E22 -> 0 | C30: =INFORMATION!G22 -> 0 | D30: =C30 -> 0 | E30: =D30 -> 0 | G30: =SUM(C30:E30)*4 -> 0 | H30: =G30*108% -> 0 | I30: =H30*108% -> 0 | J30: =I30*108% -> 0 | K30: =J30*108% -> 0 | L30: =SUM(G30:K30) -> 0
A31: Outlet operational Expense | C31: 25000 | D31: 5000 | E31: =D31 -> 5000 | G31: =E31*11+C31 -> 80000 | H31: =(E31*12)*105% -> 63000 | I31: =H31*105% -> 66150 | J31: =I31*105% -> 69457.5 | K31: =J31*105% -> 72930.375 | L31: =SUM(G31:K31) -> 351537.88
A32: Connectivity Charge | B32: =INFORMATION!B18 -> N | C32: =IF(B32="Y",6500,4500) -> 4500 | D32: =C32 -> 4500 | E32: =D32 -> 4500 | G32: =SUM(C32:E32)*4 -> 54000 | H32: =G32 -> 54000 | I32: =H32 -> 54000 | J32: =I32 -> 54000 | K32: =J32 -> 54000 | L32: =SUM(G32:K32) -> 270000
A33: Membership Discount | B33: 0.0025 | C33: =$B$33*C10 -> 4500 | D33: =$B$33*D10 -> 4500 | E33: =$B$33*E10 -> 4500 | G33: =$B$33*G10 -> 54000 | H33: =$B$33*H10 -> 60480 | I33: =$B$33*I10 -> 66528 | J33: =$B$33*J10 -> 73180.8 | K33: =$B$33*K10 -> 79035.264 | L33: =SUM(G33:K33) -> 333224.06
A34: Insurance Charges | C34: 2500 | D34: =C34 -> 2500 | E34: =D34 -> 2500 | G34: =SUM(C34:E34)*4 -> 30000 | H34: =G34 -> 30000 | I34: =H34 -> 30000 | J34: =I34 -> 30000 | K34: =J34 -> 30000 | L34: =SUM(G34:K34) -> 150000
A35: Promotional Expense | C35: 0 | D35: =C35 -> 0 | E35: =D35 -> 0 | G35: =SUM(C35:E35)*4 -> 0 | H35: =G35 -> 0 | I35: =H35 -> 0 | J35: =I35 -> 0 | K35: =J35 -> 0 | L35: =SUM(G35:K35) -> 0
A36: Ice Expenses | B36: =B26 -> N | C36: =IF(B36="Y",C10*0.5%,"") | D36: =IF(B36="Y",D10*0.5%,"") | E36: =IF(B36="Y",E10*0.5%,"") | G36: =SUM(C36:E36)*4 -> 0 | H36: =G36*105% -> 0 | I36: =H36*105% -> 0 | J36: =I36*105% -> 0 | K36: =J36*105% -> 0 | L36: =SUM(G36:K36) -> 0
A37: Denomination charge | B37: 0.0003 | C37: =$B$37*C10 -> 540 | D37: =$B$37*D10 -> 540 | E37: =$B$37*E10 -> 540 | G37: =$B$37*G10 -> 6480 | H37: =$B$37*H10 -> 7257.6 | I37: =$B$37*I10 -> 7983.36 | J37: =$B$37*J10 -> 8781.696 | K37: =$B$37*K10 -> 9484.2317 | L37: =SUM(G37:K37) -> 39986.888
A38: Credit card charge | B38: 0.003 | C38: =$B$38*C10 -> 5400 | D38: =$B$38*D10 -> 5400 | E38: =$B$38*E10 -> 5400 | G38: =$B$38*G10 -> 64800 | H38: =$B$38*H10 -> 72576 | I38: =$B$38*I10 -> 79833.6 | J38: =$B$38*J10 -> 87816.96 | K38: =$B$38*K10 -> 94842.317 | L38: =SUM(G38:K38) -> 399868.88
A39: Conveyance Expenses | C39: 4000 | D39: =C39 -> 4000 | E39: =D39 -> 4000 | G39: =SUM(C39:E39)*4 -> 48000 | H39: =G39*105% -> 50400 | I39: =H39*105% -> 52920 | J39: =I39*105% -> 55566 | K39: =J39*105% -> 58344.3 | L39: =SUM(G39:K39) -> 265230.3
A40: Printing and Stationary | C40: 2500 | D40: =C40 -> 2500 | E40: =D40 -> 2500 | G40: =SUM(C40:E40)*4 -> 30000 | H40: =G40*105% -> 31500 | I40: =H40*105% -> 33075 | J40: =I40*105% -> 34728.75 | K40: =J40*105% -> 36465.188 | L40: =SUM(G40:K40) -> 165768.94
A41: Entertainment | C41: 1000 | D41: =C41 -> 1000 | E41: =D41 -> 1000 | G41: =SUM(C41:E41)*4 -> 12000 | H41: =G41*105% -> 12600 | I41: =H41*105% -> 13230 | J41: =I41*105% -> 13891.5 | K41: =J41*105% -> 14586.075 | L41: =SUM(G41:K41) -> 66307.575
A42: Stock write off (Prov.) | B42: =VLOOKUP('Sales forecasting tools'!$N$21,'Sales forecasting tools'!$AB:$AE,4,0) -> 0.0048407649 | C42: =$B$42*C10 -> 8713.3769 | D42: =$B$42*D10 -> 8713.3769 | E42: =$B$42*E10 -> 8713.3769 | G42: =$B$42*G10 -> 104560.52 | H42: =$B$42*H10 -> 117107.78 | I42: =$B$42*I10 -> 128818.56 | J42: =$B$42*J10 -> 141700.42 | K42: =$B$42*K10 -> 153036.45 | L42: =SUM(G42:K42) -> 645223.74
A44: Total Outlet Level OPEX | C44: =SUM(C18:C42) -> 272363.6 | D44: =SUM(D18:D42) -> 251283.6 | E44: =SUM(E18:E42) -> 251283.6 | G44: =SUM(G18:G42) -> 3035403.2 | H44: =SUM(H18:H42) -> 3341441.2 | I44: =SUM(I18:I42) -> 3660297.7 | J44: =SUM(J18:J42) -> 4011520.4 | K44: =SUM(K18:K42) -> 4342108 | L44: =SUM(G44:K44) -> 18390771
A46: Outlet level Gain/Loss Before OFC | C46: =C16-C44 -> 69086.959 | D46: =D16-D44 -> 90166.959 | E46: =E16-E44 -> 90166.959 | G46: =G16-G44 -> 1062003.5 | H46: =H16-H44 -> 1296038.3 | I46: =I16-I44 -> 1494152.2 | J46: =J16-J44 -> 1716919.1 | K46: =K16-K44 -> 1907834.8 | L46: =L16-L44 -> 7476947.9
A48: Operating Financing Cost | B48: 0.14 | C48: =($C$3*70%)*$B$48/12+IF(C5>55,(C5-55)*C9*(1-C14)*$B$48/12,0) -> 2695 | D48: =($C$3*70%)*$B$48/12+IF(D5>55,(D5-55)*D9*(1-D14)*$B$48/12,0) -> 2695 | E48: =($C$3*70%)*$B$48/12+IF(E5>55,(E5-55)*E9*(1-E14)*$B$48/12,0) -> 2695 | G48: =SUM(C48:E48)*4 -> 32340 | H48: =($C$3*70%)*$B$48+IF(H5>55,(H5-55)*H9*(1-H14)*$B$48,0) -> 32340 | I48: =($C$3*70%)*$B$48+IF(I5>55,(I5-55)*I9*(1-I14)*$B$48,0) -> 32340 | J48: =($C$3*70%)*$B$48+IF(J5>55,(J5-55)*J9*(1-J14)*$B$48,0) -> 32340 | K48: =($C$3*70%)*$B$48+IF(K5>55,(K5-55)*K9*(1-K14)*$B$48,0) -> 32340 | L48: =SUM(G48:K48) -> 161700
A50: Outlet level P/L after OFC | C50: =C46-C48 -> 66391.959 | D50: =D46-D48 -> 87471.959 | E50: =E46-E48 -> 87471.959 | G50: =G46-G48 -> 1029663.5 | H50: =H46-H48 -> 1263698.3 | I50: =I46-I48 -> 1461812.2 | J50: =J46-J48 -> 1684579.1 | K50: =K46-K48 -> 1875494.8 | L50: =SUM(G50:K50) -> 7315247.9
A52: Outbound Transport | C52: =Master!C14 -> 10000 | D52: =C52 -> 10000 | E52: =D52 -> 10000 | G52: =SUM(C52:E52)*4 -> 120000 | H52: =G52*105% -> 126000 | I52: =H52*105% -> 132300 | J52: =I52*105% -> 138915 | K52: =J52*105% -> 145860.75 | L52: =SUM(G52:K52) -> 663075.75
A54: P/L consideraing Outbound Transport | C54: =C50-C52 -> 56391.959 | D54: =D50-D52 -> 77471.959 | E54: =E50-E52 -> 77471.959 | F54: =F50-F52 -> 0 | G54: =G50-G52 -> 909663.5 | H54: =H50-H52 -> 1137698.3 | I54: =I50-I52 -> 1329512.2 | J54: =J50-J52 -> 1545664.1 | K54: =K50-K52 -> 1729634.1 | L54: =SUM(G54:K54) -> 6652172.2
A56: Franchisee Part
A57: Decoration Cost (Approx..) | C57: =INFORMATION!B19 -> 1550000
A58: Advance | C58: =INFORMATION!B16 -> 1200000
A59: Security deposit
A60: Franchisee Commission | B60: =B18 -> 0.4 | C60: =C18 -> 136580.22 | D60: =D18 -> 136580.22 | E60: =E18 -> 136580.22 | G60: =G18 -> 1638962.7 | H60: =H18 -> 1854991.8 | I60: =I18 -> 2061779.9 | J60: =J18 -> 2291375.8 | K60: =K18 -> 2499977.1 | L60: =SUM(G60:K60) -> 10347087
A62: Rent | C62: =INFORMATION!B15 -> 61000 | D62: =C62 -> 61000 | E62: =D62 -> 61000 | G62: =SUM(C62:E62)*4 -> 732000 | H62: =G62 -> 732000 | I62: =H62 -> 732000 | J62: =I62+I62*10% -> 805200 | K62: =J62 -> 805200 | L62: =SUM(G62:K62) -> 3806400
A63: Rent Vat( 15%) | B63: 0.05 | C63: =C62*15% -> 9150 | D63: =D62*15% -> 9150 | E63: =E62*15% -> 9150 | G63: =G62*15% -> 109800 | H63: =H62*15% -> 109800 | I63: =I62*15% -> 109800 | J63: =J62*15% -> 120780 | K63: =K62*15% -> 120780 | L63: =SUM(G63:K63) -> 570960
A64: Depreciation | C64: =(C57*50%)/60 -> 12916.667 | D64: =C64 -> 12916.667 | E64: =D64 -> 12916.667 | G64: =SUM(C64:E64)*4 -> 155000 | H64: =G64 -> 155000 | I64: =H64 -> 155000 | J64: =I64 -> 155000 | K64: =J64 -> 155000 | L64: =SUM(G64:K64) -> 775000
A65: Financing cost | B65: 0.14 | C65: =($C$57+$C$59+$C$58)*$B$65/12 -> 32083.333 | D65: =($C$57+$C$59+$C$58)*$B$65/12 -> 32083.333 | E65: =($C$57+$C$59+$C$58)*$B$65/12 -> 32083.333 | G65: =SUM(C65:E65)*4 -> 385000 | H65: =G65 -> 385000 | I65: =H65 -> 385000 | J65: =I65 -> 385000 | K65: =J65 -> 385000 | L65: =SUM(G65:K65) -> 1925000
A66: Adjustment with Rent | G66: =SUM(C66:E66)*4 -> 0 | H66: =G66 -> 0 | I66: =H66 -> 0 | J66: =I66 -> 0 | K66: =J66 -> 0 | L66: =SUM(G66:K66) -> 0
A67: Closing Balance after rent adjustment | G67: 3000000 | H67: =G67-H66 -> 3000000 | I67: =H67-I66 -> 3000000 | J67: =I67-J66 -> 3000000 | K67: =J67-K66 -> 3000000 | L67: =SUM(G67:K67) -> 15000000
A68: Electricity & Utility | B68: =CONCATENATE('Sales forecasting tools'!N3,'Sales forecasting tools'!C20) -> 1501 TO 1800N | C68: =ROUND(AVERAGEIFS(Electricity!$F$2:$F$4570,Electricity!$E$2:$E$4570,'AUTO GENERATED FEASIBILITY'!B68),0) -> 27788 | D68: =C68 -> 27788 | E68: =D68 -> 27788 | G68: =SUM(C68:E68)*4 -> 333456 | H68: =G68+G68*3% -> 343459.68 | I68: =H68+H68*3% -> 353763.47 | J68: =I68+I68*3% -> 364376.37 | K68: =J68+J68*3% -> 375307.67 | L68: =SUM(G68:K68) -> 1770363.2
A69: Maintenance | C69: 2000 | D69: =C69 -> 2000 | E69: =D69 -> 2000 | G69: =SUM(C69:E69)*4 -> 24000 | H69: =G69 -> 24000 | I69: =H69 -> 24000 | J69: =I69 -> 24000 | K69: =J69 -> 24000 | L69: =SUM(G69:K69) -> 120000
A70: Generator Running Exp | C70: 2000 | D70: =C70 -> 2000 | E70: =D70 -> 2000 | G70: =SUM(C70:E70)*4 -> 24000 | H70: =G70 -> 24000 | I70: =H70 -> 24000 | J70: =I70 -> 24000 | K70: =J70 -> 24000 | L70: =SUM(G70:K70) -> 120000
A71: ICE bill | D71: =C71 -> 0 | E71: =D71 -> 0 | G71: =SUM(C71:E71)*4 -> 0 | H71: =G71 -> 0 | I71: =H71 -> 0 | J71: =I71*115% -> 0 | K71: =J71 -> 0 | L71: =SUM(G71:K71) -> 0
A72: Service charge & Others | D72: =C72 -> 0 | E72: =D72 -> 0 | G72: =SUM(C72:E72)*4 -> 0 | H72: =G72 -> 0 | I72: =H72 -> 0 | J72: =I72*115% -> 0 | K72: =J72 -> 0 | L72: =SUM(G72:K72) -> 0
A73: Total Franchisee Operating Expenses | C73: =C62+C63+C68+C69+C70+C71+C72 -> 101938 | D73: =D62+D63+D68+D69+D70+D71+D72 -> 101938 | E73: =E62+E63+E68+E69+E70+E71+E72 -> 101938 | G73: =G62+G63+G68+G69+G70+G71+G72 -> 1223256 | H73: =H62+H63+H68+H69+H70+H71+H72 -> 1233259.7 | I73: =I62+I63+I68+I69+I70+I71+I72 -> 1243563.5 | J73: =J62+J63+J68+J69+J70+J71+J72 -> 1338356.4 | K73: =K62+K63+K68+K69+K70+K71+K72 -> 1349287.7 | L73: =SUM(G73:K73) -> 6387723.2
A75: Franchisee Operating Cash Flow/ EBITDA | C75: =C60-C73 -> 34642.224 | D75: =D60-D73 -> 34642.224 | E75: =E60-E73 -> 34642.224 | G75: =G60-G73 -> 415706.68 | H75: =H60-H73 -> 621732.13 | I75: =I60-I73 -> 818216.48 | J75: =J60-J73 -> 953019.42 | K75: =K60-K73 -> 1150689.5 | L75: =SUM(G75:K75) -> 3959364.2
A77: Total Franchisee Expenses | C77: =C73+C65+C64 -> 146938 | D77: =D73+D65+D64 -> 146938 | E77: =E73+E64+E65 -> 146938 | G77: =G73+G64+G65 -> 1763256 | H77: =H73+H64+H65 -> 1773259.7 | I77: =I73+I64+I65 -> 1783563.5 | J77: =J73+J64+J65 -> 1878356.4 | K77: =K73+K64+K65 -> 1889287.7 | L77: =SUM(G77:K77) -> 9087723.2
A79: Franchisee PBT | C79: =C60-C77 -> -10357.776 | D79: =D60-D77 -> -10357.776 | E79: =E60-E77 -> -10357.776 | G79: =G60-G77 -> -124293.32 | H79: =H60-H77 -> 81732.126 | I79: =I60-I77 -> 278216.48 | J79: =J60-J77 -> 413019.42 | K79: =K60-K77 -> 610689.48 | L79: =SUM(G79:K79) -> 1259364.2
A81: Total Profit | C81: =C79+C50 -> 56034.182 | D81: =D79+D50 -> 77114.182 | E81: =E79+E50 -> 77114.182 | G81: =G79+G50 -> 905370.19 | H81: =H79+H50 -> 1345430.4 | I81: =I79+I50 -> 1740028.7 | J81: =J79+J50 -> 2097598.5 | K81: =K79+K50 -> 2486184.3 | L81: =SUM(G81:K81) -> 8574612.1
A83: Period | G83: YR-1 | H83: YR-2 | I83: YR-3 | J83: YR-4 | K83: YR-5
A84: Net Cash Flow/Year | F84: =-SUM(C57:C59) -> -2750000 | G84: =G75-G65+G66 -> 30706.684 | H84: =H75-H65+H66 -> 236732.13 | I84: =I75-I65+I66 -> 433216.48 | J84: =J75-J65+J66 -> 568019.42 | K84: =K75-K65+K66+K67 -> 3765689.5
A85: Cumulative Cash Flow | G85: =F84+G84 -> -2719293.3 | H85: =G85+H84 -> -2482561.2 | I85: =H85+I84 -> -2049344.7 | J85: =I85+J84 -> -1481325.3 | K85: =J85+K84 -> 2284364.2
A86: ROI Cash Flow | G86: =G84/SUM($C$57:$C$59) -> 0.011166067 | H86: =H84/SUM($C$57:$C$59) -> 0.086084409 | I86: =I84/SUM($C$57:$C$59) -> 0.15753326 | J86: =J84/SUM($C$57:$C$59) -> 0.20655252 | K86: =K84/SUM($C$57:$C$59) -> 1.3693416
A88: Discount Rate | B88: 0.09
A89: NPV | B89: =NPV(B88,G84:K84)+F84 -> 661785.63
A90: NPV Return | B90: =B89/SUM(C57:C59) -> 0.24064932
A91: IRR | B91: =IRR(F84:K84) -> 0.1440508
A92: PBP (Year) | B92: =IF(G85>0,G85/G84,IF(H85>0,1-G85/H84,IF(I85>0,2-H85/I84,IF(J85>0,3-I85/J84,IF(K85>0,4-J85/K84,"NA"))))) -> 4.3933743
A95: Prepared by | C95: Sales Given By | G95: Opened by | J95: Viewed by
A96: Md Aftab Ul Islam | C96: =Master!C15 -> Mr. Ersadul Haque | G96: =Master!C16 -> Mr. Fakhrul Alamgir | J96: Salah Uddin Misbah
A97: Senior Executive, Retail Operations | C97: Leader's Name | G97: =Master!C17 -> Head Of Business Expansion | J97: Head Of Business, CG
A103: Viewed by | D103: Viewed by | J103: Approved bY
A104: Saiful Alam Rasel | D104: Tamal Paul | J104: Abu Naser
A105: Assistant Director, Operations | D105: Director – Business Planning & Investor Relations | J105: Chief Business Officer

Sheet MANPOWER
C1: Non-PNP | D1: Non-PNP | E1: Non-PNP | F1: Non-PNP | G1: Non-PNP | H1: Non-PNP | I1: Non-PNP | J1: Non-PNP | K1: Non-PNP | L1: Non-PNP | M1: Non-PNP | N1: Non-PNP | O1: Non-PNP | P1: Non-PNP | Q1: Non-PNP | R1: Non-PNP
C2: =SUM(C4:C17) -> 4 | D2: =SUM(D4:D17) -> 5 | E2: =SUM(E4:E17) -> 6 | F2: =SUM(F4:F17) -> 8 | G2: =SUM(G4:G17) -> 9 | H2: =SUM(H4:H17) -> 10 | I2: =SUM(I4:I17) -> 12 | J2: =SUM(J4:J17) -> 13 | ... R2: =SUM(R4:R17) -> 0
C3: Below 15 Lac | D3: 15 - 18 Lac | E3: 19 - 21 Lac | F3: 22 - 24 Lac | G3: 25 - 27 Lac | H3: 28 - 30 Lac | I3: 31 - 33 Lac | J3: 34 - 36 Lac | K3: 37 - 39 Lac | L3: 40 - 42 Lac | M3: 43 - 45 Lac | N3: 46 - 48 Lac | O3: 49 - 51 Lac | P3: 52 - 54 Lac | Q3: 55 - 57 Lac | R3: 58 - 60 Lac | S3: 61 - 63 Lac | T3: 64 - 66 Lac | U3: 67 - 69 Lac | V3: 70 - 72 Lac | W3: 73 - 75 Lac | X3: 76 - 78 Lac | Y3: 79 - 81 Lac | Z3: 82 - 84 Lac | AA3: 85 - 87 Lac | AB3: 88 - 90 Lac | AC3: 91 - 93 Lac | AD3: 94 - 96 Lac | AE3: 97 - 99 Lac | AF3: 1 Cr
B4: OM-Parmanent | C4: 1 | D4: 1 | E4: 1 | F4: 1 | G4: 1 | H4: 1 | I4: 1 | J4: 1 | K4: 1 | L4: 1 | M4: 1 | N4: 1 | O4: 1
B5: ICMO-Parmanent
B6: Duty officer | C6: 1 | D6: 1 | E6: 1 | F6: 1 | G6: 1 | H6: 1 | I6: 1 | J6: 1 | K6: 1 | L6: 1 | M6: 1 | N6: 1 | O6: 1
B7: CG | C7: 1 | D7: 2 | E7: 2 | F7: 4 | G7: 5 | H7: 4 | I7: 4 | J7: 5 | K7: 5 | L7: 6 | M7: 6 | N7: 7 | O7: 7
B8: COMMODITY | H8: 1 | I8: 1 | J8: 1 | K8: 1 | L8: 1 | M8: 2 | N8: 2 | O8: 2
B9: PROTEIN
B10: PERISHABLES
B11: GM & LIFESTYLE
B12: POS | C12: 1 | D12: 1 | E12: 2 | F12: 2 | G12: 2 | H12: 2 | I12: 2 | J12: 2 | K12: 2 | L12: 2 | M12: 2 | N12: 2 | O12: 2
B13: PORTER
B14: BSM | I14: 1 | J14: 1 | K14: 1 | L14: 1 | M14: 1 | N14: 1 | O14: 1
B15: BK STR | H15: 1 | I15: 2 | J15: 2 | K15: 3 | L15: 3 | M15: 3 | N15: 3 | O15: 4
B16: SECURITY
B17: CLEANER
C18: =C3&C1 -> Below 15 LacNon-PNP | D18: =D3&D1 -> 15 - 18 LacNon-PNP | E18: =E3&E1 -> 19 - 21 LacNon-PNP | F18: =F3&F1 -> 22 - 24 LacNon-PNP | G18: =G3&G1 -> 25 - 27 LacNon-PNP | H18: =H3&H1 -> 28 - 30 LacNon-PNP | I18: =I3&I1 -> 31 - 33 LacNon-PNP | J18: =J3&J1 -> 34 - 36 LacNon-PNP | ... O18: =O3&O1 -> 49 - 51 LacNon-PNP
C22: PNP | D22: PNP | E22: PNP | F22: PNP | G22: PNP | H22: PNP | I22: PNP | J22: PNP | K22: PNP | L22: PNP | M22: PNP | N22: PNP | O22: PNP | P22: PNP | Q22: PNP | R22: PNP | S22: PNP | T22: PNP | U22: PNP | V22: PNP | W22: PNP | X22: PNP | Y22: PNP | Z22: PNP | AA22: PNP | AB22: PNP | AC22: PNP | AD22: PNP | AE22: PNP
C23: =SUM(C25:C36,C38) -> 0 | D23: =SUM(D25:D36,D38) -> 0 | E23: =SUM(E25:E36,E38) -> 0 | F23: =SUM(F25:F36,F38) -> 0 | G23: =SUM(G25:G36,G38) -> 14 | H23: =SUM(H25:H36,H38) -> 16 | I23: =SUM(I25:I36,I38) -> 17 | J23: =SUM(J25:J36,J38) -> 17 | ... AE23: =SUM(AE25:AE36,AE38) -> 33
C24: Below 15 Lac | D24: 15 - 18 Lac | E24: 19 - 21 Lac | F24: 22 - 24 Lac | G24: 25 - 27 Lac | H24: 28 - 30 Lac | I24: 31 - 33 Lac | J24: 34 - 36 Lac | K24: 37 - 39 Lac | L24: 40 - 42 Lac | M24: 43 - 45 Lac | N24: 46 - 48 Lac | O24: 49 - 51 Lac | P24: 52 - 54 Lac | Q24: 55 - 57 Lac | R24: 58 - 60 Lac | S24: 61 - 63 Lac | T24: 64 - 66 Lac | U24: 67 - 69 Lac | V24: 70 - 72 Lac | W24: 73 - 75 Lac | X24: 76 - 78 Lac | Y24: 79 - 81 Lac | Z24: 82 - 84 Lac | AA24: 85 - 87 Lac | AB24: 88 - 90 Lac | AC24: 91 - 93 Lac | AD24: 94 - 96 Lac | AE24: 97 - 99 Lac | AF24: 1 Cr
B25: OM-Parmanent | G25: 1 | H25: 1 | I25: 1 | J25: 1 | K25: 1 | L25: 1 | M25: 1 | N25: 1 | O25: 1 | P25: 1 | Q25: 1 | R25: 1 | S25: 1 | T25: 1 | U25: 1 | V25: 1 | W25: 1 | X25: 1 | Y25: 1 | Z25: 1 | AA25: 1 | AB25: 1 | AC25: 1 | AD25: 1 | AE25: 1
B26: ICMO-Parmanent | G26: 1 | H26: 1 | I26: 1 | J26: 1 | K26: 1 | L26: 1 | M26: 1 | N26: 1 | O26: 1 | P26: 1 | Q26: 1 | R26: 1 | S26: 1 | T26: 1 | U26: 1 | V26: 1 | W26: 1 | X26: 1 | Y26: 1 | Z26: 1 | AA26: 1 | AB26: 1 | AC26: 1 | AD26: 1 | AE26: 1
B27: Duty officer
B28: CG | G28: 2 | H28: 4 | I28: 5 | J28: 4 | K28: 4 | L28: 5 | M28: 5 | N28: 6 | O28: 6 | P28: 7 | Q28: 7 | R28: 7 | S28: 7 | T28: 7 | U28: 7 | V28: 7 | W28: 7 | X28: 7 | Y28: 8 | Z28: 8 | AA28: 8 | AB28: 8 | AC28: 8 | AD28: 8 | AE28: 8
B29: COMMODITY | J29: 1 | K29: 1 | L29: 1 | M29: 1 | N29: 1 | O29: 2 | P29: 2 | Q29: 2 | R29: 2 | S29: 2 | T29: 2 | U29: 2 | V29: 3 | W29: 3 | X29: 3 | Y29: 3 | Z29: 3 | AA29: 3 | AB29: 3 | AC29: 3 | AD29: 3 | AE29: 3
B30: PROTEIN | G30: 4 | H30: 4 | I30: 4 | J30: 4 | K30: 4 | L30: 4 | M30: 4 | N30: 4 | O30: 4 | P30: 4 | Q30: 4 | R30: 4 | S30: 4 | T30: 4 | U30: 5 | V30: 5 | W30: 5 | X30: 5 | Y30: 5 | Z30: 5 | AA30: 5 | AB30: 5 | AC30: 5 | AD30: 5 | AE30: 5
B31: PERISHABLES
B32: GM & LIFESTYLE
B33: POS | G33: 2 | H33: 2 | I33: 2 | J33: 2 | K33: 3 | L33: 3 | M33: 3 | N33: 3 | O33: 3 | P33: 3 | Q33: 3 | R33: 3 | S33: 3 | T33: 3 | U33: 4 | V33: 4 | W33: 4 | X33: 4 | Y33: 5 | Z33: 5 | AA33: 5 | AB33: 5 | AC33: 5 | AD33: 5 | AE33: 5
B34: PORTER
B35: BSM | K35: 1 | L35: 1 | M35: 1 | N35: 1 | O35: 1 | P35: 1 | Q35: 1 | R35: 1 | S35: 1 | T35: 1 | U35: 1 | V35: 1 | W35: 1 | X35: 1 | Y35: 1 | Z35: 1 | AA35: 1 | AB35: 1 | AC35: 1 | AD35: 1 | AE35: 1
B36: BK STR | G36: 2 | H36: 2 | I36: 2 | J36: 2 | K36: 2 | L36: 2 | M36: 3 | N36: 3 | O36: 3 | P36: 3 | Q36: 4 | R36: 4 | S36: 4 | T36: 4 | U36: 4 | V36: 4 | W36: 4 | X36: 4 | Y36: 4 | Z36: 4 | AA36: 4 | AB36: 4 | AC36: 4 | AD36: 4 | AE36: 4
B37: SECURITY | G37: 1 | H37: 1 | I37: 1 | J37: 1 | K37: 1 | L37: 1 | M37: 1 | N37: 1 | O37: 1 | P37: 1 | Q37: 1 | R37: 2 | S37: 2 | T37: 2 | U37: 2 | V37: 2 | W37: 2 | X37: 2 | Y37: 2 | Z37: 2 | AA37: 2 | AB37: 2 | AC37: 2 | AD37: 2 | AE37: 2
B38: CLEANER | G38: 2 | H38: 2 | I38: 2 | J38: 2 | K38: 2 | L38: 2 | M38: 2 | N38: 2 | O38: 2 | P38: 2 | Q38: 2 | R38: 4 | S38: 4 | T38: 4 | U38: 4 | V38: 4 | W38: 4 | X38: 5 | Y38: 5 | Z38: 5 | AA38: 5 | AB38: 5 | AC38: 5 | AD38: 5 | AE38: 5
C39: =C24&C22 -> Below 15 LacPNP | D39: =D24&D22 -> 15 - 18 LacPNP | E39: =E24&E22 -> 19 - 21 LacPNP | F39: =F24&F22 -> 22 - 24 LacPNP | G39: =G24&G22 -> 25 - 27 LacPNP | H39: =H24&H22 -> 28 - 30 LacPNP | I39: =I24&I22 -> 31 - 33 LacPNP | J39: =J24&J22 -> 34 - 36 LacPNP | ... AE39: =AE24&AE22 -> 97 - 99 LacPNP

Sheet Outlet Data
A1: SL No | B1: CODE | C1: Outlet Name | D1: LOOK | E1: LOOK 2 | F1: Look 3 | G1: Look 4 | H1: Lunching Date | I1: SFT | J1: SFT Band | K1: Division | L1: District | M1: PNP Non PNP status | N1: Location Type | O1: Population Density | P1: Income Level | Q1: Location Type (D,T,D) | R1: Dhaka/Out of Dhaka N | S1: Avg Monthly Sales | T1: Sales/SFT | U1: Outlet Own P25 Sales | V1: Outlet Own P75 Sales | W1: Should-be Sales | X1: Benchmark P25 Sales | Y1: Benchmark P75 Sales | Z1: Benchmark Store Count | AA1: Benchmark Level | AB1: Benchmark Criteria Used | AC1: Sales Position | AD1: Gap vs Should-be Sales | AE1: Gap % vs Should-be | AF1: Profit % | AG1: Sales Jan-26 | AH1: Sales Feb-26 | AI1: Sales Mar-26 | AJ1: Sales Apr-26 | AK1: Sales May-26 | AL1: Profit Jan-26 | AM1: Profit Feb-26 | AN1: Profit Mar-26 | AO1: Profit Apr-26 | AP1: Profit May-26 | AQ1: GP AVG | AR1: DV & DI | AS1: Stock write off (Prov.) | AT1: Layout shape | AU1: Floor type | AV1: Status
A2: 0 | B2: D002 | C2: Postogola | D2: =CONCATENATE(J2,K2,L2,M2,,N2,O2,P2,Q2,AT2,AU2) -> 5001 - 5500 SFTDhakaDhakaPNPHigh Street W Residential BlockMCবিভাগীয় শহরL shapeGround floor | E2: =CONCATENATE('Outlet Data'!K2,L2,'Outlet Data'!N2,M2) -> DhakaDhakaHigh Street W Residential BlockPNP | F2: =CONCATENATE(L2,Q2,M2) -> Dhakaবিভাগীয় শহরPNP | G2: =CONCATENATE(L2,M2) -> DhakaPNP | H2: 39749 | I2: 5100 | J2: =IF(I2="","",IF(I2<=1000,"Below 1000 SFT",IF(I2>10000,"More Then 10000 SFT",(INT((I2-1001)/500)*500+1001)&" - "&(INT((I2-1001)/500)*500+1500)&" SFT"))) -> 5001 - 5500 SFT | K2: Dhaka | L2: Dhaka | M2: PNP | N2: High Street W Residential Block | O2: M | P2: C | Q2: বিভাগীয় শহর | R2: Dhaka | S2: 4532111.2 | T2: 888.64925 | U2: 4265797 | V2: 4896351 | W2: 12869518 | X2: 10195629 | Y2: 14771974 | Z2: 24 | AA2: L6 Practical: SFT+PNP+Dhaka | AB2: SFT Band + PNP Non PNP status + Dhaka/Out of Dhaka N | AC2: Below P25 | AD2: -8337406.7 | AE2: -0.64784142 | AF2: 0.045444952 | AG2: 4222622 | AH2: 4265797 | AI2: 5004180 | AJ2: 4271606 | AK2: 4896351 | AL2: 16641.222 | AM2: 191061.98 | AN2: 311253.39 | AO2: 239239.52 | AP2: 271611.77 | AQ2: 0.17508522 | AR2: =K2&L2 -> DhakaDhaka | AS2: 0.011484892 | AT2: L shape | AU2: Ground floor | AV2: OWN
A3: 102 | B3: D004 | C3: Nakhal Para | D3: =CONCATENATE(J3,K3,L3,M3,,N3,O3,P3,Q3,AT3,AU3) -> 2501 - 3000 SFTDhakaDhakaPNPHigh Street W Residential BlockMCবিভাগীয় শহরSquare ⬜ shapeGround floor | E3: =CONCATENATE('Outlet Data'!K3,L3,'Outlet Data'!N3,M3) -> DhakaDhakaHigh Street W Residential BlockPNP | F3: =CONCATENATE(L3,Q3,M3) -> Dhakaবিভাগীয় শহরPNP | G3: =CONCATENATE(L3,M3) -> DhakaPNP | H3: 39814 | I3: 2670 | J3: =IF(I3="","",IF(I3<=1000,"Below 1000 SFT",IF(I3>10000,"More Then 10000 SFT",(INT((I3-1001)/500)*500+1001)&" - "&(INT((I3-1001)/500)*500+1500)&" SFT"))) -> 2501 - 3000 SFT | K3: Dhaka | L3: Dhaka | M3: PNP | N3: High Street W Residential Block | O3: M | P3: C | Q3: বিভাগীয় শহর | R3: Dhaka | S3: 6512140.8 | T3: 2439.004 | U3: 6246545 | V3: 6664462 | W3: 7985832.2 | X3: 5306408.2 | Y3: 10796483 | Z3: 23 | AA3: L6 Practical: SFT+PNP+Dhaka | AB3: SFT Band + PNP Non PNP status + Dhaka/Out of Dhaka N | AC3: Within P25–P75 | AD3: -1473691.4 | AE3: -0.18453824 | AF3: 0.071120974 | AG3: 5790385 | AH3: 6248284 | AI3: 6664462 | AJ3: 6246545 | AK3: 7611028 | AL3: 311332.17 | AM3: 390243.98 | AN3: 458037.27 | AO3: 479242.03 | AP3: 676893.53 | AQ3: 0.17161895 | AR3: =K3&L3 -> DhakaDhaka | AS3: 0.0037810806 | AT3: Square ⬜ shape | AU3: Ground floor | AV3: OWN
A4: 37 | B4: D003 | C4: Uttara 6 | D4: =CONCATENATE(J4,K4,L4,M4,,N4,O4,P4,Q4,AT4,AU4) -> 4001 - 4500 SFTDhakaGBUDDhakaPNPHigh Street W Residential BlockHAবিভাগীয় শহরOthersSlightly upper than Ground floor | E4: =CONCATENATE('Outlet Data'!K4,L4,'Outlet Data'!N4,M4) -> DhakaGBUDDhakaHigh Street W Residential BlockPNP | F4: =CONCATENATE(L4,Q4,M4) -> Dhakaবিভাগীয় শহরPNP | G4: =CONCATENATE(L4,M4) -> DhakaPNP | H4: 39879 | I4: 4135 | J4: =IF(I4="","",IF(I4<=1000,"Below 1000 SFT",IF(I4>10000,"More Then 10000 SFT",(INT((I4-1001)/500)*500+1001)&" - "&(INT((I4-1001)/500)*500+1500)&" SFT"))) -> 4001 - 4500 SFT | K4: DhakaGBUD | L4: Dhaka | M4: PNP | N4: High Street W Residential Block | O4: H | P4: A | Q4: বিভাগীয় শহর | R4: Dhaka | S4: 11183320 | T4: 2704.5513 | U4: 10685233 | V4: 11561194 | W4: 13530057 | X4: 11573069 | Y4: 21008994 | Z4: 6 | AA4: L4 Balanced: SFT+PNP+Pop+Income+Dhaka | AB4: SFT Band + PNP Non PNP status + Population Density + Income Level + Dhaka/Out of Dhaka N | AC4: Below P25 | AD4: -2346737.6 | AE4: -0.17344624 | AF4: 0.078988582 | AG4: 11047635 | AH4: 11561194 | AI4: 11961481 | AJ4: 10685233 | AK4: 10661055 | AL4: 928154.41 | AM4: 997005.18 | AN4: 842141.3 | AO4: 819121.67 | AP4: 830350.24 | AQ4: 0.16839338 | AR4: =K4&L4 -> DhakaGBUDDhaka | AS4: 0.0074812257 | AT4: Others | AU4: Slightly upper than Ground floor | AV4: OWN
A5: 44 | B5: D011 | C5: Nazim Uddin | D5: =CONCATENATE(J5,K5,L5,M5,,N5,O5,P5,Q5,AT5,AU5) -> 3501 - 4000 SFTDhakaDhakaPNPHigh Street W Residential BlockMBবিভাগীয় শহরI shapeGround floor | E5: =CONCATENATE('Outlet Data'!K5,L5,'Outlet Data'!N5,M5) -> DhakaDhakaHigh Street W Residential BlockPNP | F5: =CONCATENATE(L5,Q5,M5) -> Dhakaবিভাগীয় শহরPNP | G5: =CONCATENATE(L5,M5) -> DhakaPNP | H5: 39913 | I5: 3880 | J5: =IF(I5="","",IF(I5<=1000,"Below 1000 SFT",IF(I5>10000,"More Then 10000 SFT",(INT((I5-1001)/500)*500+1001)&" - "&(INT((I5-1001)/500)*500+1500)&" SFT"))) -> 3501 - 4000 SFT | K5: Dhaka | L5: Dhaka | M5: PNP | N5: High Street W Residential Block | O5: M | P5: B | Q5: বিভাগীয় শহর | R5: Dhaka | S5: 12706758 | T5: 3274.9377 | U5: 12546417 | V5: 13004230 | W5: 5686926.4 | X5: 5216051.6 | Y5: 9581427.1 | Z5: 11 | AA5: L2 Strong: SFT+Division+PNP+Pop+Income+Dhaka | AB5: SFT Band + Division + PNP Non PNP status + Population Density + Income Level + Dhaka/Out of Dhaka N | AC5: Above P75 | AD5: 7019831.8 | AE5: 1.2343806 | AF5: 0.080608825 | AG5: 11217517 | AH5: 12546417 | AI5: 13004230 | AJ5: 12929492 | AK5: 13836135 | AL5: 763486.04 | AM5: 945495.02 | AN5: 1119922.7 | AO5: 934627.84 | AP5: 1357852.7 | AQ5: 0.16774025 | AR5: =K5&L5 -> DhakaDhaka | AS5: 0.016676137 | AT5: I shape | AU5: Ground floor | AV5: OWN
A6: 1 | B6: D007 | C6: Green Road | D6: =CONCATENATE(J6,K6,L6,M6,,N6,O6,P6,Q6,AT6,AU6) -> More Then 10000 SFTDhakaGBUDDhakaPNPHigh Street W Residential BlockHAবিভাগীয় শহরI shapeSlightly upper than Ground floor | E6: =CONCATENATE('Outlet Data'!K6,L6,'Outlet Data'!N6,M6) -> DhakaGBUDDhakaHigh Street W Residential BlockPNP | F6: =CONCATENATE(L6,Q6,M6) -> Dhakaবিভাগীয় শহরPNP | G6: =CONCATENATE(L6,M6) -> DhakaPNP | H6: 39933 | I6: 11648 | J6: =IF(I6="","",IF(I6<=1000,"Below 1000 SFT",IF(I6>10000,"More Then 10000 SFT",(INT((I6-1001)/500)*500+1001)&" - "&(INT((I6-1001)/500)*500+1500)&" SFT"))) -> More Then 10000 SFT | K6: DhakaGBUD | L6: Dhaka | M6: PNP | N6: High Street W Residential Block | O6: H | P6: A | Q6: বিভাগীয় শহর | R6: Dhaka | S6: 53466145 | T6: 4590.1567 | U6: 52080094 | V6: 54837942 | W6: 44929501 | X6: 27706765 | Y6: 53466145 | Z6: 5 | AA6: L1 Exact: All Criteria | AB6: SFT Band + Division + PNP Non PNP status + Location Type + Population Density + Income Level + Location Type (D,T,D) + E-Com + Dhaka/Out of Dhaka N | AC6: Within P25–P75 | AD6: 8536644.6 | AE6: 0.19000088 | AF6: 0.12404784 | AG6: 50454151 | AH6: 53736528 | AI6: 54837942 | AJ6: 52080094 | AK6: 56222012 | AL6: 6309925.7 | AM6: 6419560.2 | AN6: 6859472.3 | AO6: 6409962.4 | AP6: 7162877.4 | AQ6: 0.17625854 | AR6: =K6&L6 -> DhakaGBUDDhaka | AS6: 0.0030964648 | AT6: I shape | AU6: Slightly upper than Ground floor | AV6: OWN
A7: 15 | B7: D006 | C7: Malibag | D7: =CONCATENATE(J7,K7,L7,M7,,N7,O7,P7,Q7,AT7,AU7) -> 5001 - 5500 SFTDhakaDhakaPNPHigh Street W Residential BlockHBবিভাগীয় শহরSquare ⬜ shapeGround floor | E7: =CONCATENATE('Outlet Data'!K7,L7,'Outlet Data'!N7,M7) -> DhakaDhakaHigh Street W Residential BlockPNP | F7: =CONCATENATE(L7,Q7,M7) -> Dhakaবিভাগীয় শহরPNP | G7: =CONCATENATE(L7,M7) -> DhakaPNP | H7: 39933 | I7: 5465 | J7: =IF(I7="","",IF(I7<=1000,"Below 1000 SFT",IF(I7>10000,"More Then 10000 SFT",(INT((I7-1001)/500)*500+1001)&" - "&(INT((I7-1001)/500)*500+1500)&" SFT"))) -> 5001 - 5500 SFT | K7: Dhaka | L7: Dhaka | M7: PNP | N7: High Street W Residential Block | O7: H | P7: B | Q7: বিভাগীয় শহর | R7: Dhaka | S7: 18175815 | T7: 3325.8582 | U7: 17711796 | V7: 19183610 | W7: 15950606 | X7: 15318650 | Y7: 18175815 | Z7: 5 | AA7: L1 Exact: All Criteria | AB7: SFT Band + Division + PNP Non PNP status + Location Type + Population Density + Income Level + Location Type (D,T,D) + E-Com + Dhaka/Out of Dhaka N | AC7: Within P25–P75 | AD7: 2225208.8 | AE7: 0.13950622 | AF7: 0.098656155 | AG7: 16243175 | AH7: 19183610 | AI7: 19437700 | AJ7: 17711796 | AK7: 18302795 | AL7: 1752652.5 | AM7: 1863186.4 | AN7: 1904056.7 | AO7: 1624879.5 | AP7: 1821005.1 | AQ7: 0.16701474 | AR7: =K7&L7 -> DhakaDhaka | AS7: 0.0037278323 | AT7: Square ⬜ shape | AU7: Ground floor | AV7: OWN
A8: 359 | B8: D017 | C8: West Kafrul | D8: =CONCATENATE(J8,K8,L8,M8,,N8,O8,P8,Q8,AT8,AU8) -> 3001 - 3500 SFTDhakaDhakaPNPHigh Street W Residential BlockHBবিভাগীয় শহরI shapeSlightly upper than Ground floor | E8: =CONCATENATE('Outlet Data'!K8,L8,'Outlet Data'!N8,M8) -> DhakaDhakaHigh Street W Residential BlockPNP | F8: =CONCATENATE(L8,Q8,M8) -> Dhakaবিভাগীয় শহরPNP | G8: =CONCATENATE(L8,M8) -> DhakaPNP | H8: 39933 | I8: 3200 | J8: =IF(I8="","",IF(I8<=1000,"Below 1000 SFT",IF(I8>10000,"More Then 10000 SFT",(INT((I8-1001)/500)*500+1001)&" - "&(INT((I8-1001)/500)*500+1500)&" SFT"))) -> 3001 - 3500 SFT | K8: Dhaka | L8: Dhaka | M8: PNP | N8: High Street W Residential Block | O8: H | P8: B | Q8: বিভাগীয় শহর | R8: Dhaka | S8: 9061673.8 | T8: 2831.7731 | U8: 8773290 | V8: 9368454 | W8: 9019007.8 | X8: 7985832.2 | Y8: 9061673.8 | Z8: 5 | AA8: L2 Strong: SFT+Division+PNP+Pop+Income+Dhaka | AB8: SFT Band + Division + PNP Non PNP status + Population Density + Income Level + Dhaka/Out of Dhaka N | AC8: Within P25–P75 | AD8: 42666 | AE8: 0.0047306756 | AF8: 0.050039052 | AG8: 8684770 | AH8: 8773290 | AI8: 9368454 | AJ8: 8919724 | AK8: 9562131 | AL8: 543579.63 | AM8: 277027.06 | AN8: 639692.19 | AO8: 907838.4 | AP8: -100949.44 | AQ8: 0.16406384 | AR8: =K8&L8 -> DhakaDhaka | AS8: 0.045222242 | AT8: I shape | AU8: Slightly upper than Ground floor | AV8: OWN
A9: 21 | B9: D014 | C9: Missionpara | D9: =CONCATENATE(J9,K9,L9,M9,,N9,O9,P9,Q9,AT9,AU9) -> 4001 - 4500 SFTDhakaNarayanganjPNPHigh Street W Residential BlockHBজেলা শহরSquare ⬜ shapeGround floor | E9: =CONCATENATE('Outlet Data'!K9,L9,'Outlet Data'!N9,M9) -> DhakaNarayanganjHigh Street W Residential BlockPNP | F9: =CONCATENATE(L9,Q9,M9) -> Narayanganjজেলা শহরPNP | G9: =CONCATENATE(L9,M9) -> NarayanganjPNP | H9: 39977 | I9: 4440 | J9: =IF(I9="","",IF(I9<=1000,"Below 1000 SFT",IF(I9>10000,"More Then 10000 SFT",(INT((I9-1001)/500)*500+1001)&" - "&(INT((I9-1001)/500)*500+1500)&" SFT"))) -> 4001 - 4500 SFT | K9: Dhaka | L9: Narayanganj | M9: PNP | N9: High Street W Residential Block | O9: H | P9: B | Q9: জেলা শহর | R9: Dhaka | S9: 13137813 | T9: 2958.9669 | U9: 12627536 | V9: 13561719 | W9: 13067267 | X9: 10570136 | Y9: 15136425 | Z9: 14 | AA9: L2 Strong: SFT+Division+PNP+Pop+Income+Dhaka | AB9: SFT Band + Division + PNP Non PNP status + Population Density + Income Level + Dhaka/Out of Dhaka N | AC9: Within P25–P75 | AD9: 70546.5 | AE9: 0.0053987189 | AF9: 0.099566665 | AG9: 12627536 | AH9: 13123400 | AI9: 13950843 | AJ9: 12425568 | AK9: 13561719 | AL9: 1322133.7 | AM9: 1109071.4 | AN9: 1451310.6 | AO9: 1265576.5 | AP9: 1392349.1 | AQ9: 0.17894502 | AR9: =K9&L9 -> DhakaNarayanganj | AS9: 0.0033932992 | AT9: Square ⬜ shape | AU9: Ground floor | AV9: OWN
A10: 38 | B10: S001 | C10: Shahjalal | D10: =CONCATENATE(J10,K10,L10,M10,,N10,O10,P10,Q10,AT10,AU10) -> 8501 - 9000 SFTSylhetSylhetPNPHigh Street W Residential BlockHAবিভাগীয় শহরSquare ⬜ shapeGround floor | E10: =CONCATENATE('Outlet Data'!K10,L10,'Outlet Data'!N10,M10) -> SylhetSylhetHigh Street W Residential BlockPNP | F10: =CONCATENATE(L10,Q10,M10) -> Sylhetবিভাগীয় শহরPNP | G10: =CONCATENATE(L10,M10) -> SylhetPNP | H10: 39989 | I10: 9000 | J10: =IF(I10="","",IF(I10<=1000,"Below 1000 SFT",IF(I10>10000,"More Then 10000 SFT",(INT((I10-1001)/500)*500+1001)&" - "&(INT((I10-1001)/500)*500+1500)&" SFT"))) -> 8501 - 9000 SFT | K10: Sylhet | L10: Sylhet | M10: PNP | N10: High Street W Residential Block | O10: H | P10: A | Q10: বিভাগীয় শহর | R10: Non Dhaka | S10: 17663356 | T10: 1962.5952 | U10: 17219522 | V10: 18237650 | W10: 27706765 | X10: 20466397 | Y10: 44929501 | Z10: 13 | AA10: L5 Balanced: SFT+PNP+Pop+Income | AB10: SFT Band + PNP Non PNP status + Population Density + Income Level | AC10: Below P25 | AD10: -10043408 | AE10: -0.36248939 | AF10: 0.065861249 | AG10: 18237650 | AH10: 18143843 | AI10: 19136596 | AJ10: 15579171 | AK10: 17219522 | AL10: 1413108.7 | AM10: 941408.04 | AN10: 1452206.4 | AO10: 783557.15 | AP10: 1226373.3 | AQ10: 0.15549144 | AR10: =K10&L10 -> SylhetSylhet | AS10: 0.0034285409 | AT10: Square ⬜ shape | AU10: Ground floor | AV10: OWN
A11: 39 | B11: C001 | C11: Gol Pahar | D11: =CONCATENATE(J11,K11,L11,M11,,N11,O11,P11,Q11,AT11,AU11) -> 5001 - 5500 SFTChattogramChattogramPNPHigh Street W Residential BlockHBবিভাগীয় শহরOthersGround floor | E11: =CONCATENATE('Outlet Data'!K11,L11,'Outlet Data'!N11,M11) -> ChattogramChattogramHigh Street W Residential BlockPNP | F11: =CONCATENATE(L11,Q11,M11) -> Chattogramবিভাগীয় শহরPNP | G11: =CONCATENATE(L11,M11) -> ChattogramPNP | H11: 39990 | I11: 5350 | J11: =IF(I11="","",IF(I11<=1000,"Below 1000 SFT",IF(I11>10000,"More Then 10000 SFT",(INT((I11-1001)/500)*500+1001)&" - "&(INT((I11-1001)/500)*500+1500)&" SFT"))) -> 5001 - 5500 SFT | K11: Chattogram | L11: Chattogram | M11: PNP | N11: High Street W Residential Block | O11: H | P11: B | Q11: বিভাগীয় শহর | R11: Non Dhaka | S11: 13101040 | T11: 2448.7924 | U11: 12018873 | V11: 13597285 | W11: 13359380 | X11: 12301783 | Y11: 14004254 | Z11: 6 | AA11: L2 Strong: SFT+Division+PNP+Pop+Income+Dhaka | AB11: SFT Band + Division + PNP Non PNP status + Population Density + Income Level + Dhaka/Out of Dhaka N | AC11: Within P25–P75 | AD11: -258339.9 | AE11: -0.019337717 | AF11: 0.075878471 | AG11: 12018873 | AH11: 13237854 | AI11: 15296393 | AJ11: 11354793 | AK11: 13597285 | AL11: 961343.89 | AM11: 937581.09 | AN11: 1275639 | AO11: 627176.02 | AP11: 1168694.3 | AQ11: 0.15527368 | AR11: =K11&L11 -> ChattogramChattogram | AS11: 0.0037420794 | AT11: Others | AU11: Ground floor | AV11: OWN
A12: 151 | B12: S003 | C12: Pathantola | D12: =CONCATENATE(J12,K12,L12,M12,,N12,O12,P12,Q12,AT12,AU12) -> 3501 - 4000 SFTSylhetSylhetPNPHigh Street W Residential BlockHCবিভাগীয় শহরSquare ⬜ shapeSlightly upper than Ground floor | E12: =CONCATENATE('Outlet Data'!K12,L12,'Outlet Data'!N12,M12) -> SylhetSylhetHigh Street W Residential BlockPNP | F12: =CONCATENATE(L12,Q12,M12) -> Sylhetবিভাগীয় শহরPNP | G12: =CONCATENATE(L12,M12) -> SylhetPNP | H12: 39990 | I12: 4000 | J12: =IF(I12="","",IF(I12<=1000,"Below 1000 SFT",IF(I12>10000,"More Then 10000 SFT",(INT((I12-1001)/500)*500+1001)&" - "&(INT((I12-1001)/500)*500+1500)&" SFT"))) -> 3501 - 4000 SFT | K12: Sylhet | L12: Sylhet | M12: PNP | N12: High Street W Residential Block | O12: H | P12: C | Q12: বিভাগীয় শহর | R12: Non Dhaka | S12: 6881612.2 | T12: 1720.4031 | U12: 6592029 | V12: 7244868 | W12: 3627509.1 | X12: 1818884.2 | Y12: 6001045.4 | Z12: 6 | AA12: L6 Practical: SFT+PNP+Dhaka | AB12: SFT Band + PNP Non PNP status + Dhaka/Out of Dhaka N | AC12: Above P75 | AD12: 3254103.1 | AE12: 0.8970627 | AF12: 0.051164204 | AG12: 6972837 | AH12: 7521874 | AI12: 7244868 | AJ12: 6076453 | AK12: 6592029 | AL12: 406996.2 | AM12: 389392.77 | AN12: 324676.97 | AO12: 277945.55 | AP12: 361449.57 | AQ12: 0.15081311 | AR12: =K12&L12 -> SylhetSylhet | AS12: 0.0036556127 | AT12: Square ⬜ shape | AU12: Slightly upper than Ground floor | AV12: OWN
A13: 145 | B13: S002 | C13: Shibgong | D13: =CONCATENATE(J13,K13,L13,M13,,N13,O13,P13,Q13,AT13,AU13) -> 5501 - 6000 SFTSylhetSylhetPNPHigh Street W Residential BlockHCবিভাগীয় শহরSquare ⬜ shapeGround floor | E13: =CONCATENATE('Outlet Data'!K13,L13,'Outlet Data'!N13,M13) -> SylhetSylhetHigh Street W Residential BlockPNP | F13: =CONCATENATE(L13,Q13,M13) -> Sylhetবিভাগীয় শহরPNP | G13: =CONCATENATE(L13,M13) -> SylhetPNP | H13: 39990 | I13: 5600 | J13: =IF(I13="","",IF(I13<=1000,"Below 1000 SFT",IF(I13>10000,"More Then 10000 SFT",(INT((I13-1001)/500)*500+1001)&" - "&(INT((I13-1001)/500)*500+1500)&" SFT"))) -> 5501 - 6000 SFT | K13: Sylhet | L13: Sylhet | M13: PNP | N13: High Street W Residential Block | O13: H | P13: C | Q13: বিভাগীয় শহর | R13: Non Dhaka | S13: 8176873.2 | T13: 1460.1559 | U13: 7942348 | V13: 8730687 | W13: 11786996 | X13: 7989742.5 | Y13: 13536837 | Z13: 18 | AA13: L6 Practical: SFT+PNP+Dhaka | AB13: SFT Band + PNP Non PNP status + Dhaka/Out of Dhaka N | AC13: Within P25–P75 | AD13: -3610123.2 | AE13: -0.30628016 | AF13: 0.080094466 | AG13: 7942348 | AH13: 8730687 | AI13: 8947506 | AJ13: 7287667 | AK13: 7976158 | AL13: 745209.12 | AM13: 602522.27 | AN13: 674511.03 | AO13: 560555.48 | AP13: 691813.56 | AQ13: 0.16134291 | AR13: =K13&L13 -> SylhetSylhet | AS13: 0.0037797935 | AT13: Square ⬜ shape | AU13: Ground floor | AV13: OWN
... A650: 520 | B650: F718 | C650: Bamnartek Turag Outlet | D650: =CONCATENATE(J650,K650,L650,M650,,N650,O650,P650,Q650,AT650,AU650) -> 1001 - 1500 SFTDhakaDhakaNon-PNPHigh Street W Residential BlockHBবিভাগীয় শহরL shapeSlightly upper than Ground floor | E650: =CONCATENATE('Outlet Data'!K650,L650,'Outlet Data'!N650,M650) -> DhakaDhakaHigh Street W Residential BlockNon-PNP | F650: =CONCATENATE(L650,Q650,M650) -> Dhakaবিভাগীয় শহরNon-PNP | G650: =CONCATENATE(L650,M650) -> DhakaNon-PNP | H650: 45869 | I650: 1038 | J650: =IF(I650="","",IF(I650<=1000,"Below 1000 SFT",IF(I650>10000,"More Then 10000 SFT",(INT((I650-1001)/500)*500+1001)&" - "&(INT((I650-1001)/500)*500+1500)&" SFT"))) -> 1001 - 1500 SFT | K650: Dhaka | L650: Dhaka | M650: Non-PNP | N650: High Street W Residential Block | O650: H | P650: B | Q650: বিভাগীয় শহর | R650: Dhaka | S650: 1533741.2 | T650: 1477.5927 | U650: 1506617 | V650: 1563621 | W650: 2400604 | X650: 1727011.1 | Y650: 2506160.1 | Z650: 6 | AA650: L1 Exact: All Criteria | AB650: SFT Band + Division + PNP Non PNP status + Location Type + Population Density + Income Level + Location Type (D,T,D) + E-Com + Dhaka/Out of Dhaka N | AC650: Below P25 | AD650: -866862.8 | AE650: -0.36110196 | AF650: 0.031689106 | AG650: 1539491 | AH650: 1563621 | AI650: 1506617 | AJ650: 1481286 | AK650: 1577691 | AL650: 65279.516 | AM650: 60622.347 | AN650: 44827.746 | AO650: 19227.629 | AP650: 53057.197 | AQ650: 0.15760296 | AR650: =K650&L650 -> DhakaDhaka | AS650: 0.004 | AT650: L shape | AU650: Slightly upper than Ground floor | AV650: FR
A651: 1007 | B651: F973 | C651: Thana Road Mirjapur Tangail Outlet | D651: =CONCATENATE(J651,K651,L651,M651,,N651,O651,P651,Q651,AT651,AU651) -> 1001 - 1500 SFTDhakaTangailNon-PNPHigh StreetMBথানা সদরL shapeSlightly upper than Ground floor | E651: =CONCATENATE('Outlet Data'!K651,L651,'Outlet Data'!N651,M651) -> DhakaTangailHigh StreetNon-PNP | F651: =CONCATENATE(L651,Q651,M651) -> Tangailথানা সদরNon-PNP | G651: =CONCATENATE(L651,M651) -> TangailNon-PNP | H651: 46142 | I651: 1250 | J651: =IF(I651="","",IF(I651<=1000,"Below 1000 SFT",IF(I651>10000,"More Then 10000 SFT",(INT((I651-1001)/500)*500+1001)&" - "&(INT((I651-1001)/500)*500+1500)&" SFT"))) -> 1001 - 1500 SFT | K651: Dhaka | L651: Tangail | M651: Non-PNP | N651: High Street | O651: M | P651: B | Q651: থানা সদর | R651: Dhaka | S651: 181689.5 | T651: 145.3516 | U651: 92164.25 | V651: 271214.75 | W651: 1445730 | X651: 953500.6 | Y651: 1792550.9 | Z651: 55 | AA651: L2 Strong: SFT+Division+PNP+Pop+Income+Dhaka | AB651: SFT Band + Division + PNP Non PNP status + Population Density + Income Level + Dhaka/Out of Dhaka N | AC651: Below P25 | AD651: -1264040.5 | AE651: -0.87432681 | AF651: -0.11911208 | AJ651: 2639 | AK651: 360740 | AO651: 270.06657 | AP651: -43552.895 | AQ651: 0.10586555 | AR651: =K651&L651 -> DhakaTangail | AS651: 0.004 | AT651: L shape | AU651: Slightly upper than Ground floor | AV651: FR
A652: 770 | B652: F721 | C652: Beltola Bazar Amanatganj Barishal Outlet | D652: =CONCATENATE(J652,K652,L652,M652,,N652,O652,P652,Q652,AT652,AU652) -> 1001 - 1500 SFTBarishalBarishalNon-PNPHigh Street W Residential BlockLCবিভাগীয় শহরSquare ⬜ shapeGround floor | E652: =CONCATENATE('Outlet Data'!K652,L652,'Outlet Data'!N652,M652) -> BarishalBarishalHigh Street W Residential BlockNon-PNP | F652: =CONCATENATE(L652,Q652,M652) -> Barishalবিভাগীয় শহরNon-PNP | G652: =CONCATENATE(L652,M652) -> BarishalNon-PNP | H652: 45869 | I652: 1441 | J652: =IF(I652="","",IF(I652<=1000,"Below 1000 SFT",IF(I652>10000,"More Then 10000 SFT",(INT((I652-1001)/500)*500+1001)&" - "&(INT((I652-1001)/500)*500+1500)&" SFT"))) -> 1001 - 1500 SFT | K652: Barishal | L652: Barishal | M652: Non-PNP | N652: High Street W Residential Block | O652: L | P652: C | Q652: বিভাগীয় শহর | R652: Non Dhaka | S652: 775265.8 | T652: 538.00541 | U652: 717777 | V652: 804119 | W652: 1254815 | X652: 792070.6 | Y652: 1562156.4 | Z652: 14 | AA652: L2 Strong: SFT+Division+PNP+Pop+Income+Dhaka | AB652: SFT Band + Division + PNP Non PNP status + Population Density + Income Level + Dhaka/Out of Dhaka N | AC652: Below P25 | AD652: -479549.2 | AE652: -0.38216725 | AF652: -0.02305604 | AG652: 773825 | AH652: 717777 | AI652: 804119 | AJ652: 600810 | AK652: 979798 | AL652: -29829.865 | AM652: -4914.7579 | AN652: 1956.2956 | AO652: -44994.814 | AP652: -11589.656 | AQ652: 0.14887987 | AR652: =K652&L652 -> BarishalBarishal | AS652: 0.004 | AT652: Square ⬜ shape | AU652: Ground floor | AV652: FR
A653: 521 | B653: F719 | C653: Chanpara Uttarkhan Outlet | D653: =CONCATENATE(J653,K653,L653,M653,,N653,O653,P653,Q653,AT653,AU653) -> 1001 - 1500 SFTDhakaDhakaNon-PNPWithin the MahallaMCবিভাগীয় শহরSquare ⬜ shapeGround floor | E653: =CONCATENATE('Outlet Data'!K653,L653,'Outlet Data'!N653,M653) -> DhakaDhakaWithin the MahallaNon-PNP | F653: =CONCATENATE(L653,Q653,M653) -> Dhakaবিভাগীয় শহরNon-PNP | G653: =CONCATENATE(L653,M653) -> DhakaNon-PNP | H653: 45869 | I653: 1210 | J653: =IF(I653="","",IF(I653<=1000,"Below 1000 SFT",IF(I653>10000,"More Then 10000 SFT",(INT((I653-1001)/500)*500+1001)&" - "&(INT((I653-1001)/500)*500+1500)&" SFT"))) -> 1001 - 1500 SFT | K653: Dhaka | L653: Dhaka | M653: Non-PNP | N653: Within the Mahalla | O653: M | P653: C | Q653: বিভাগীয় শহর | R653: Dhaka | S653: 1210215.2 | T653: 1000.1779 | U653: 1150720 | V653: 1281983 | W653: 1796385.8 | X653: 1234693.5 | Y653: 2351918.3 | Z653: 14 | AA653: L1 Exact: All Criteria | AB653: SFT Band + Division + PNP Non PNP status + Location Type + Population Density + Income Level + Location Type (D,T,D) + E-Com + Dhaka/Out of Dhaka N | AC653: Below P25 | AD653: -586170.6 | AE653: -0.32630552 | AF653: 0.042002667 | AG653: 1150720 | AH653: 1100496 | AI653: 1352071 | AJ653: 1165806 | AK653: 1281983 | AL653: 57681.537 | AM653: 41342.708 | AN653: 70388.038 | AO653: 33294.231 | AP653: 51454.818 | AQ653: 0.16603939 | AR653: =K653&L653 -> DhakaDhaka | AS653: 0.004 | AT653: Square ⬜ shape | AU653: Ground floor | AV653: FR
A654: 656 | B654: F601 | C654: Chirirbandar Dinajpur | D654: =CONCATENATE(J654,K654,L654,M654,,N654,O654,P654,Q654,AT654,AU654) -> 1001 - 1500 SFTRangpurDinajpurNon-PNPHigh Street W Residential BlockMBথানা সদরSquare ⬜ shapeGround floor | E654: =CONCATENATE('Outlet Data'!K654,L654,'Outlet Data'!N654,M654) -> RangpurDinajpurHigh Street W Residential BlockNon-PNP | F654: =CONCATENATE(L654,Q654,M654) -> Dinajpurথানা সদরNon-PNP | G654: =CONCATENATE(L654,M654) -> DinajpurNon-PNP | H654: 45869 | I654: 1303 | J654: =IF(I654="","",IF(I654<=1000,"Below 1000 SFT",IF(I654>10000,"More Then 10000 SFT",(INT((I654-1001)/500)*500+1001)&" - "&(INT((I654-1001)/500)*500+1500)&" SFT"))) -> 1001 - 1500 SFT | K654: Rangpur | L654: Dinajpur | M654: Non-PNP | N654: High Street W Residential Block | O654: M | P654: B | Q654: থানা সদর | R654: Non Dhaka | S654: 1352007.2 | T654: 1037.6111 | U654: 1231168 | V654: 1469953 | W654: 843340 | X654: 568975.3 | Y654: 1144384.5 | Z654: 7 | AA654: L2 Strong: SFT+Division+PNP+Pop+Income+Dhaka | AB654: SFT Band + Division + PNP Non PNP status + Population Density + Income Level + Dhaka/Out of Dhaka N | AC654: Above P75 | AD654: 508667.2 | AE654: 0.60315792 | AF654: 0.04531719 | AG654: 1294243 | AH654: 1189832 | AI654: 1469953 | AJ654: 1231168 | AK654: 1574840 | AL654: 64554.307 | AM654: 45684.611 | AN654: 82079.274 | AO654: 44443.737 | AP654: 69583.909 | AQ654: 0.16233776 | AR654: =K654&L654 -> RangpurDinajpur | AS654: 0.004 | AT654: Square ⬜ shape | AU654: Ground floor | AV654: FR
A655: 602 | B655: F695 | C655: Dainkini Road Chandra Outlet | D655: =CONCATENATE(J655,K655,L655,M655,,N655,O655,P655,Q655,AT655,AU655) -> 1001 - 1500 SFTDhakaGazipurNon-PNPHigh Street W Residential BlockLCথানা সদরL shapeSlightly upper than Ground floor | E655: =CONCATENATE('Outlet Data'!K655,L655,'Outlet Data'!N655,M655) -> DhakaGazipurHigh Street W Residential BlockNon-PNP | F655: =CONCATENATE(L655,Q655,M655) -> Gazipurথানা সদরNon-PNP | G655: =CONCATENATE(L655,M655) -> GazipurNon-PNP | H655: 45869 | I655: 1290 | J655: =IF(I655="","",IF(I655<=1000,"Below 1000 SFT",IF(I655>10000,"More Then 10000 SFT",(INT((I655-1001)/500)*500+1001)&" - "&(INT((I655-1001)/500)*500+1500)&" SFT"))) -> 1001 - 1500 SFT | K655: Dhaka | L655: Gazipur | M655: Non-PNP | N655: High Street W Residential Block | O655: L | P655: C | Q655: থানা সদর | R655: Dhaka | S655: 1141515.6 | T655: 884.89581 | U655: 1111164 | V655: 1153166 | W655: 1126199.5 | X655: 866075.6 | Y655: 1499334.4 | Z655: 28 | AA655: L2 Strong: SFT+Division+PNP+Pop+Income+Dhaka | AB655: SFT Band + Division + PNP Non PNP status + Population Density + Income Level + Dhaka/Out of Dhaka N | AC655: Within P25–P75 | AD655: 15316.1 | AE655: 0.013599811 | AF655: 0.026959451 | AG655: 1111164 | AH655: 1153166 | AI655: 1359601 | AJ655: 971312 | AK655: 1112335 | AL655: 27252.733 | AM655: 22839.496 | AN655: 53545.889 | AO655: 6705.662 | AP655: 43529.391 | AQ655: 0.15038556 | AR655: =K655&L655 -> DhakaGazipur | AS655: 0.004 | AT655: L shape | AU655: Slightly upper than Ground floor | AV655: FR
A656: 663 | B656: F724 | C656: Dhalla Bazar, Manikganj Outlet | D656: =CONCATENATE(J656,K656,L656,M656,,N656,O656,P656,Q656,AT656,AU656) -> 1001 - 1500 SFTDhakaManikganjNon-PNPCommercial HubMCঅন্যান্যI shapeGround floor | E656: =CONCATENATE('Outlet Data'!K656,L656,'Outlet Data'!N656,M656) -> DhakaManikganjCommercial HubNon-PNP | F656: =CONCATENATE(L656,Q656,M656) -> Manikganjঅন্যান্যNon-PNP | G656: =CONCATENATE(L656,M656) -> ManikganjNon-PNP | H656: 45869 | I656: 1230 | J656: =IF(I656="","",IF(I656<=1000,"Below 1000 SFT",IF(I656>10000,"More Then 10000 SFT",(INT((I656-1001)/500)*500+1001)&" - "&(INT((I656-1001)/500)*500+1500)&" SFT"))) -> 1001 - 1500 SFT | K656: Dhaka | L656: Manikganj | M656: Non-PNP | N656: Commercial Hub | O656: M | P656: C | Q656: অন্যান্য | R656: Dhaka | S656: 675960.8 | T656: 549.56163 | U656: 662860 | V656: 722418 | W656: 1435127.3 | X656: 920723.95 | Y656: 2028621.2 | Z656: 50 | AA656: L2 Strong: SFT+Division+PNP+Pop+Income+Dhaka | AB656: SFT Band + Division + PNP Non PNP status + Population Density + Income Level + Dhaka/Out of Dhaka N | AC656: Below P25 | AD656: -759166.5 | AE656: -0.52898896 | AF656: 0.022840038 | AG656: 662860 | AH656: 722418 | AI656: 771294 | AJ656: 522018 | AK656: 701214 | AL656: 11917.183 | AM656: 10334.665 | AN656: 30584.037 | AO656: -969.55809 | AP656: 25328.526 | AQ656: 0.17307356 | AR656: =K656&L656 -> DhakaManikganj | AS656: 0.004 | AT656: I shape | AU656: Ground floor | AV656: FR
A657: 351 | B657: F673 | C657: Dogair Bazar Demra Outlet | D657: =CONCATENATE(J657,K657,L657,M657,,N657,O657,P657,Q657,AT657,AU657) -> 1501 - 2000 SFTDhakaDhakaNon-PNPWithin the MahallaMBথানা সদরOthersGround floor | E657: =CONCATENATE('Outlet Data'!K657,L657,'Outlet Data'!N657,M657) -> DhakaDhakaWithin the MahallaNon-PNP | F657: =CONCATENATE(L657,Q657,M657) -> Dhakaথানা সদরNon-PNP | G657: =CONCATENATE(L657,M657) -> DhakaNon-PNP | H657: 45869 | I657: 1951 | J657: =IF(I657="","",IF(I657<=1000,"Below 1000 SFT",IF(I657>10000,"More Then 10000 SFT",(INT((I657-1001)/500)*500+1001)&" - "&(INT((I657-1001)/500)*500+1500)&" SFT"))) -> 1501 - 2000 SFT | K657: Dhaka | L657: Dhaka | M657: Non-PNP | N657: Within the Mahalla | O657: M | P657: B | Q657: থানা সদর | R657: Dhaka | S657: 1653471.8 | T657: 847.49964 | U657: 1647151 | V657: 1751928 | W657: 2241169.2 | X657: 1560783.8 | Y657: 3069073.6 | Z657: 59 | AA657: L2 Strong: SFT+Division+PNP+Pop+Income+Dhaka | AB657: SFT Band + Division + PNP Non PNP status + Population Density + Income Level + Dhaka/Out of Dhaka N | AC657: Within P25–P75 | AD657: -587697.4 | AE657: -0.26222804 | AF657: 0.051312607 | AG657: 1656791 | AH657: 1403253 | AI657: 1751928 | AJ657: 1647151 | AK657: 1808236 | AL657: 60822.306 | AM657: 49657.16 | AN657: 104029.78 | AO657: 72045.259 | AP657: 137665.24 | AQ657: 0.16418749 | AR657: =K657&L657 -> DhakaDhaka | AS657: 0.004 | AT657: Others | AU657: Ground floor | AV657: FR
A658: 496 | B658: F714 | C658: Dumuria Bus Stand Khulna Outlet | D658: =CONCATENATE(J658,K658,L658,M658,,N658,O658,P658,Q658,AT658,AU658) -> 1001 - 1500 SFTKhulnaKhulnaNon-PNPHigh Street W Residential BlockMCথানা সদরL shapeGround floor | E658: =CONCATENATE('Outlet Data'!K658,L658,'Outlet Data'!N658,M658) -> KhulnaKhulnaHigh Street W Residential BlockNon-PNP | F658: =CONCATENATE(L658,Q658,M658) -> Khulnaথানা সদরNon-PNP | G658: =CONCATENATE(L658,M658) -> KhulnaNon-PNP | H658: 45869 | I658: 1450 | J658: =IF(I658="","",IF(I658<=1000,"Below 1000 SFT",IF(I658>10000,"More Then 10000 SFT",(INT((I658-1001)/500)*500+1001)&" - "&(INT((I658-1001)/500)*500+1500)&" SFT"))) -> 1001 - 1500 SFT | K658: Khulna | L658: Khulna | M658: Non-PNP | N658: High Street W Residential Block | O658: M | P658: C | Q658: থানা সদর | R658: Non Dhaka | S658: 837919 | T658: 577.87517 | U658: 861829 | V658: 926948 | W658: 1121570.1 | X658: 952503.3 | Y658: 1526574.5 | Z658: 44 | AA658: L4 Balanced: SFT+PNP+Pop+Income+Dhaka | AB658: SFT Band + PNP Non PNP status + Population Density + Income Level + Dhaka/Out of Dhaka N | AC658: Below P25 | AD658: -283651.1 | AE658: -0.25290537 | AF658: 0.032659932 | AG658: 936921 | AH658: 926948 | AI658: 861829 | AJ658: 570658 | AK658: 893239 | AL658: 24280.715 | AM658: 32743.051 | AN658: 47829.175 | AO658: -7428.385 | AP658: 39407.332 | AQ658: 0.15674817 | AR658: =K658&L658 -> KhulnaKhulna | AS658: 0.004 | AT658: L shape | AU658: Ground floor | AV658: FR
A659: 597 | B659: F496 | C659: Kanaighat Sylhet | D659: =CONCATENATE(J659,K659,L659,M659,,N659,O659,P659,Q659,AT659,AU659) -> 1001 - 1500 SFTSylhetSylhetNon-PNPHigh Street W Residential BlockLCথানা সদরI shapeGround floor | E659: =CONCATENATE('Outlet Data'!K659,L659,'Outlet Data'!N659,M659) -> SylhetSylhetHigh Street W Residential BlockNon-PNP | F659: =CONCATENATE(L659,Q659,M659) -> Sylhetথানা সদরNon-PNP | G659: =CONCATENATE(L659,M659) -> SylhetNon-PNP | H659: 45503 | I659: 1500 | J659: =IF(I659="","",IF(I659<=1000,"Below 1000 SFT",IF(I659>10000,"More Then 10000 SFT",(INT((I659-1001)/500)*500+1001)&" - "&(INT((I659-1001)/500)*500+1500)&" SFT"))) -> 1001 - 1500 SFT | K659: Sylhet | L659: Sylhet | M659: Non-PNP | N659: High Street W Residential Block | O659: L | P659: C | Q659: থানা সদর | R659: Non Dhaka | S659: 976932.8 | T659: 651.28853 | U659: 903756 | V659: 1070613 | W659: 1489607.2 | X659: 1476583.2 | Y659: 1653290.4 | Z659: 5 | AA659: L2 Strong: SFT+Division+PNP+Pop+Income+Dhaka | AB659: SFT Band + Division + PNP Non PNP status + Population Density + Income Level + Dhaka/Out of Dhaka N | AC659: Below P25 | AD659: -512674.4 | AE659: -0.34416751 | AF659: 0.02228014 | AG659: 963271 | AH659: 1081936 | AI659: 1070613 | AJ659: 865088 | AK659: 903756 | AL659: 3501.0778 | AM659: 24586.966 | AN659: 30636.514 | AO659: 22900.134 | AP659: 27206.303 | AQ659: 0.14603759 | AR659: =K659&L659 -> SylhetSylhet | AS659: 0.004 | AT659: I shape | AU659: Ground floor | AV659: FR
A660: 777 | B660: F722 | C660: F722 - Rupsa Traffic Mor, Khulna Outlet | D660: =CONCATENATE(J660,K660,L660,M660,,N660,O660,P660,Q660,AT660,AU660) -> 1501 - 2000 SFTKhulnaKhulnaNon-PNPHigh Street W Residential BlockMCবিভাগীয় শহরL shapeGround floor | E660: =CONCATENATE('Outlet Data'!K660,L660,'Outlet Data'!N660,M660) -> KhulnaKhulnaHigh Street W Residential BlockNon-PNP | F660: =CONCATENATE(L660,Q660,M660) -> Khulnaবিভাগীয় শহরNon-PNP | G660: =CONCATENATE(L660,M660) -> KhulnaNon-PNP | H660: 45869 | I660: 1720 | J660: =IF(I660="","",IF(I660<=1000,"Below 1000 SFT",IF(I660>10000,"More Then 10000 SFT",(INT((I660-1001)/500)*500+1001)&" - "&(INT((I660-1001)/500)*500+1500)&" SFT"))) -> 1501 - 2000 SFT | K660: Khulna | L660: Khulna | M660: Non-PNP | N660: High Street W Residential Block | O660: M | P660: C | Q660: বিভাগীয় শহর | R660: Non Dhaka | S660: 961358.2 | T660: 558.92919 | U660: 864568 | V660: 1058967 | W660: 1414944.4 | X660: 1342188.4 | Y660: 1422184 | Z660: 5 | AA660: L2 Strong: SFT+Division+PNP+Pop+Income+Dhaka | AB660: SFT Band + Division + PNP Non PNP status + Population Density + Income Level + Dhaka/Out of Dhaka N | AC660: Below P25 | AD660: -453586.2 | AE660: -0.32056821 | AF660: 0.015877558 | AG660: 939306 | AH660: 864568 | AI660: 1058967 | AJ660: 788508 | AK660: 1155442 | AL660: 17265.547 | AM660: 4428.3307 | AN660: 29457.65 | AO660: -11064.43 | AP660: 36233.003 | AQ660: 0.13839436 | AR660: =K660&L660 -> KhulnaKhulna | AS660: -1.8891362e-17 | AT660: L shape | AU660: Ground floor | AV660: FR
A661: 505 | B661: F726 | C661: F726 - Fire Service Mor Jhalakathi Outlet | D661: =CONCATENATE(J661,K661,L661,M661,,N661,O661,P661,Q661,AT661,AU661) -> Below 1000 SFTBarishalBarishalNon-PNPCommercial HubMBজেলা শহরSquare ⬜ shapeGround floor | E661: =CONCATENATE('Outlet Data'!K661,L661,'Outlet Data'!N661,M661) -> BarishalBarishalCommercial HubNon-PNP | F661: =CONCATENATE(L661,Q661,M661) -> Barishalজেলা শহরNon-PNP | G661: =CONCATENATE(L661,M661) -> BarishalNon-PNP | H661: 45869 | I661: 941 | J661: =IF(I661="","",IF(I661<=1000,"Below 1000 SFT",IF(I661>10000,"More Then 10000 SFT",(INT((I661-1001)/500)*500+1001)&" - "&(INT((I661-1001)/500)*500+1500)&" SFT"))) -> Below 1000 SFT | K661: Barishal | L661: Barishal | M661: Non-PNP | N661: Commercial Hub | O661: M | P661: B | Q661: জেলা শহর | R661: Non Dhaka | S661: 1245551.2 | T661: 1323.6463 | U661: 1240053 | V661: 1317247 | W661: 1188929 | X661: 909090.2 | Y661: 1190597.4 | Z661: 5 | AA661: L2 Strong: SFT+Division+PNP+Pop+Income+Dhaka | AB661: SFT Band + Division + PNP Non PNP status + Population Density + Income Level + Dhaka/Out of Dhaka N | AC661: Above P75 | AD661: 56622.2 | AE661: 0.047624543 | AF661: 0.043503094 | AG661: 1240695 | AH661: 1240053 | AI661: 1427677 | AJ661: 1002084 | AK661: 1317247 | AL661: 55846.502 | AM661: 46025.899 | AN661: 79386.372 | AO661: 26324.341 | AP661: 63343.538 | AQ661: 0.16544906 | AR661: =K661&L661 -> BarishalBarishal | AS661: 0.004 | AT661: Square ⬜ shape | AU661: Ground floor | AV661: FR
A662: 633 | B662: F723 | C662: Harich Chowdhury Bazar, Subarnachar Outlet | D662: =CONCATENATE(J662,K662,L662,M662,,N662,O662,P662,Q662,AT662,AU662) -> 1001 - 1500 SFTChattogramNoakhaliNon-PNPCommercial HubMCথানা সদরI shapeGround floor | E662: =CONCATENATE('Outlet Data'!K662,L662,'Outlet Data'!N662,M662) -> ChattogramNoakhaliCommercial HubNon-PNP | F662: =CONCATENATE(L662,Q662,M662) -> Noakhaliথানা সদরNon-PNP | G662: =CONCATENATE(L662,M662) -> NoakhaliNon-PNP | H662: 45869 | I662: 1148 | J662: =IF(I662="","",IF(I662<=1000,"Below 1000 SFT",IF(I662>10000,"More Then 10000 SFT",(INT((I662-1001)/500)*500+1001)&" - "&(INT((I662-1001)/500)*500+1500)&" SFT"))) -> 1001 - 1500 SFT | K662: Chattogram | L662: Noakhali | M662: Non-PNP | N662: Commercial Hub | O662: M | P662: C | Q662: থানা সদর | R662: Non Dhaka | S662: 934977 | T662: 814.4399 | U662: 782116 | V662: 1001263 | W662: 1536884.6 | X662: 1100730.4 | Y662: 2035829.4 | Z662: 9 | AA662: L2 Strong: SFT+Division+PNP+Pop+Income+Dhaka | AB662: SFT Band + Division + PNP Non PNP status + Population Density + Income Level + Dhaka/Out of Dhaka N | AC662: Below P25 | AD662: -601907.6 | AE662: -0.39164138 | AF662: 0.0002428663 | AG662: 782116 | AH662: 1001263 | AI662: 1148410 | AJ662: 764938 | AK662: 978158 | AL662: 5110.1921 | AM662: -9778.9884 | AN662: 52960.553 | AO662: -51280.413 | AP662: 4124.0283 | AQ662: 0.16006127 | AR662: =K662&L662 -> ChattogramNoakhali | AS662: 0.004 | AT662: I shape | AU662: Ground floor | AV662: FR
A663: 536 | B663: F637 | C663: Hospital Road Nilphamari Outlet | D663: =CONCATENATE(J663,K663,L663,M663,,N663,O663,P663,Q663,AT663,AU663) -> 2001 - 2500 SFTRangpurNilphamariNon-PNPHigh Street W InstitutionsMCজেলা শহরI shapeGround floor | E663: =CONCATENATE('Outlet Data'!K663,L663,'Outlet Data'!N663,M663) -> RangpurNilphamariHigh Street W InstitutionsNon-PNP | F663: =CONCATENATE(L663,Q663,M663) -> Nilphamariজেলা শহরNon-PNP | G663: =CONCATENATE(L663,M663) -> NilphamariNon-PNP | H663: 45869 | I663: 2324 | J663: =IF(I663="","",IF(I663<=1000,"Below 1000 SFT",IF(I663>10000,"More Then 10000 SFT",(INT((I663-1001)/500)*500+1001)&" - "&(INT((I663-1001)/500)*500+1500)&" SFT"))) -> 2001 - 2500 SFT | K663: Rangpur | L663: Nilphamari | M663: Non-PNP | N663: High Street W Institutions | O663: M | P663: C | Q663: জেলা শহর | R663: Non Dhaka | S663: 1208426.4 | T663: 519.97694 | U663: 1178622 | V663: 1235480 | W663: 1739100.6 | X663: 985635.15 | Y663: 2574781 | Z663: 10 | AA663: L2 Strong: SFT+Division+PNP+Pop+Income+Dhaka | AB663: SFT Band + Division + PNP Non PNP status + Population Density + Income Level + Dhaka/Out of Dhaka N | AC663: Within P25–P75 | AD663: -530674.2 | AE663: -0.3051429 | AF663: 0.051824881 | AG663: 1178622 | AH663: 1235480 | AI663: 1209470 | AJ663: 1064038 | AK663: 1354522 | AL663: 61878.933 | AM663: 60416.456 | AN663: 67372.595 | AO663: 51512.34 | AP663: 71952.45 | AQ663: 0.16078849 | AR663: =K663&L663 -> RangpurNilphamari | AS663: 0.004 | AT663: I shape | AU663: Ground floor | AV663: FR
... A820: 922 | B820: F889 | C820: Office Road Burichang Cumilla | D820: =CONCATENATE(J820,K820,L820,M820,,N820,O820,P820,Q820,AT820,AU820) -> 2501 - 3000 SFTChattogramCumillaNon-PNPHigh Street W Residential BlockMBথানা সদরI shapeGround floor | E820: =CONCATENATE('Outlet Data'!K820,L820,'Outlet Data'!N820,M820) -> ChattogramCumillaHigh Street W Residential BlockNon-PNP | F820: =CONCATENATE(L820,Q820,M820) -> Cumillaথানা সদরNon-PNP | G820: =CONCATENATE(L820,M820) -> CumillaNon-PNP | H820: 46056 | I820: 3000 | J820: =IF(I820="","",IF(I820<=1000,"Below 1000 SFT",IF(I820>10000,"More Then 10000 SFT",(INT((I820-1001)/500)*500+1001)&" - "&(INT((I820-1001)/500)*500+1500)&" SFT"))) -> 2501 - 3000 SFT | K820: Chattogram | L820: Cumilla | M820: Non-PNP | N820: High Street W Residential Block | O820: M | P820: B | Q820: থানা সদর | R820: Non Dhaka | S820: 1577742.8 | T820: 525.91427 | U820: 1485933 | V820: 2132850 | W820: 2362499.7 | X820: 2124690 | Y820: 3717922.6 | Z820: 6 | AA820: L2 Strong: SFT+Division+PNP+Pop+Income+Dhaka | AB820: SFT Band + Division + PNP Non PNP status + Population Density + Income Level + Dhaka/Out of Dhaka N | AC820: Below P25 | AD820: -784756.9 | AE820: -0.33217227 | AF820: 0.060765651 | AG820: 19005 | AH820: 2087170 | AI820: 2163756 | AJ820: 1485933 | AK820: 2132850 | AL820: 2478.9265 | AM820: 144526.91 | AN820: 183097.02 | AO820: -1313.9653 | AP820: 150573.95 | AQ820: 0.18313887 | AR820: =K820&L820 -> ChattogramCumilla | AS820: 0.004 | AT820: I shape | AU820: Ground floor | AV820: FR
A821: 931 | B821: F867 | C821: Himardighi | D821: =CONCATENATE(J821,K821,L821,M821,,N821,O821,P821,Q821,AT821,AU821) -> 1001 - 1500 SFTDhakaGazipurNon-PNPHigh Street W Residential BlockMBথানা সদরSquare ⬜ shapeGround floor | E821: =CONCATENATE('Outlet Data'!K821,L821,'Outlet Data'!N821,M821) -> DhakaGazipurHigh Street W Residential BlockNon-PNP | F821: =CONCATENATE(L821,Q821,M821) -> Gazipurথানা সদরNon-PNP | G821: =CONCATENATE(L821,M821) -> GazipurNon-PNP | H821: 46057 | I821: 1025 | J821: =IF(I821="","",IF(I821<=1000,"Below 1000 SFT",IF(I821>10000,"More Then 10000 SFT",(INT((I821-1001)/500)*500+1001)&" - "&(INT((I821-1001)/500)*500+1500)&" SFT"))) -> 1001 - 1500 SFT | K821: Dhaka | L821: Gazipur | M821: Non-PNP | N821: High Street W Residential Block | O821: M | P821: B | Q821: থানা সদর | R821: Dhaka | S821: 765795.75 | T821: 747.1178 | U821: 743408.75 | V821: 875346.5 | W821: 1096480.2 | X821: 805383.79 | Y821: 1965543.3 | Z821: 8 | AA821: L1 Exact: All Criteria | AB821: SFT Band + Division + PNP Non PNP status + Location Type + Population Density + Income Level + Location Type (D,T,D) + E-Com + Dhaka/Out of Dhaka N | AC821: Below P25 | AD821: -330684.45 | AE821: -0.30158725 | AF821: 0.0051186445 | AH821: 435674 | AI821: 921590 | AJ821: 845987 | AK821: 859932 | AM821: -16579.096 | AN821: 4274.9437 | AO821: 14539.325 | AP821: 13444.172 | AQ821: 0.10877543 | AR821: =K821&L821 -> DhakaGazipur | AS821: 0 | AT821: Square ⬜ shape | AU821: Ground floor | AV821: FR
A822: 937 | B822: F886 | C822: Bangodda Bazar Cumilla | D822: =CONCATENATE(J822,K822,L822,M822,,N822,O822,P822,Q822,AT822,AU822) -> 1501 - 2000 SFTChattogramCumillaNon-PNPHigh Street W Residential BlockMBঅন্যান্যL shapeGround floor | E822: =CONCATENATE('Outlet Data'!K822,L822,'Outlet Data'!N822,M822) -> ChattogramCumillaHigh Street W Residential BlockNon-PNP | F822: =CONCATENATE(L822,Q822,M822) -> Cumillaঅন্যান্যNon-PNP | G822: =CONCATENATE(L822,M822) -> CumillaNon-PNP | H822: 46062 | I822: 1650 | J822: =IF(I822="","",IF(I822<=1000,"Below 1000 SFT",IF(I822>10000,"More Then 10000 SFT",(INT((I822-1001)/500)*500+1001)&" - "&(INT((I822-1001)/500)*500+1500)&" SFT"))) -> 1501 - 2000 SFT | K822: Chattogram | L822: Cumilla | M822: Non-PNP | N822: High Street W Residential Block | O822: M | P822: B | Q822: অন্যান্য | R822: Non Dhaka | S822: 784455.25 | T822: 475.42742 | U822: 643886.75 | V822: 927409 | W822: 1730070.3 | X822: 1191184.5 | Y822: 3396251.9 | Z822: 16 | AA822: L2 Strong: SFT+Division+PNP+Pop+Income+Dhaka | AB822: SFT Band + Division + PNP Non PNP status + Population Density + Income Level + Dhaka/Out of Dhaka N | AC822: Below P25 | AD822: -945615.05 | AE822: -0.54657608 | AF822: 0.016977994 | AH822: 579731 | AI822: 984409 | AJ822: 665272 | AK822: 908409 | AM822: -19149.307 | AN822: 59972.675 | AO822: -19744.258 | AP822: 32194.797 | AQ822: 0.11823342 | AR822: =K822&L822 -> ChattogramCumilla | AS822: 0.015116684 | AT822: L shape | AU822: Ground floor | AV822: FR
A823: 936 | B823: F885 | C823: Munshirhat Cumilla | D823: =CONCATENATE(J823,K823,L823,M823,,N823,O823,P823,Q823,AT823,AU823) -> 1501 - 2000 SFTChattogramCumillaNon-PNPHigh Street W Residential BlockLBঅন্যান্যI shapeGround floor | E823: =CONCATENATE('Outlet Data'!K823,L823,'Outlet Data'!N823,M823) -> ChattogramCumillaHigh Street W Residential BlockNon-PNP | F823: =CONCATENATE(L823,Q823,M823) -> Cumillaঅন্যান্যNon-PNP | G823: =CONCATENATE(L823,M823) -> CumillaNon-PNP | H823: 46063 | I823: 1630 | J823: =IF(I823="","",IF(I823<=1000,"Below 1000 SFT",IF(I823>10000,"More Then 10000 SFT",(INT((I823-1001)/500)*500+1001)&" - "&(INT((I823-1001)/500)*500+1500)&" SFT"))) -> 1501 - 2000 SFT | K823: Chattogram | L823: Cumilla | M823: Non-PNP | N823: High Street W Residential Block | O823: L | P823: B | Q823: অন্যান্য | R823: Non Dhaka | S823: 852352.5 | T823: 522.91564 | U823: 642557 | V823: 999514.5 | W823: 1348528.2 | X823: 907985.2 | Y823: 1744457 | Z823: 13 | AA823: L4 Balanced: SFT+PNP+Pop+Income+Dhaka | AB823: SFT Band + PNP Non PNP status + Population Density + Income Level + Dhaka/Out of Dhaka N | AC823: Below P25 | AD823: -496175.7 | AE823: -0.36793869 | AF823: -0.0092360103 | AH823: 585911 | AI823: 1244061 | AJ823: 661439 | AK823: 917999 | AM823: -45379.861 | AN823: 33207.983 | AO823: -3218.8754 | AP823: -16098.593 | AQ823: 0.11526279 | AR823: =K823&L823 -> ChattogramCumilla | AS823: 0.004 | AT823: I shape | AU823: Ground floor | AV823: FR
A824: 939 | B824: F895 | C824: New Market Debidwar,Cumilla | D824: =CONCATENATE(J824,K824,L824,M824,,N824,O824,P824,Q824,AT824,AU824) -> Below 1000 SFTChattogramCumillaNon-PNPHigh Street W Residential BlockMBথানা সদরI shapeGround floor | E824: =CONCATENATE('Outlet Data'!K824,L824,'Outlet Data'!N824,M824) -> ChattogramCumillaHigh Street W Residential BlockNon-PNP | F824: =CONCATENATE(L824,Q824,M824) -> Cumillaথানা সদরNon-PNP | G824: =CONCATENATE(L824,M824) -> CumillaNon-PNP | H824: 46078 | I824: 1000 | J824: =IF(I824="","",IF(I824<=1000,"Below 1000 SFT",IF(I824>10000,"More Then 10000 SFT",(INT((I824-1001)/500)*500+1001)&" - "&(INT((I824-1001)/500)*500+1500)&" SFT"))) -> Below 1000 SFT | K824: Chattogram | L824: Cumilla | M824: Non-PNP | N824: High Street W Residential Block | O824: M | P824: B | Q824: থানা সদর | R824: Non Dhaka | S824: 1805093.5 | T824: 1805.0935 | U824: 1323805 | V824: 2402301 | W824: 1039476.4 | X824: 672568 | Y824: 1386312.2 | Z824: 5 | AA824: L2 Strong: SFT+Division+PNP+Pop+Income+Dhaka | AB824: SFT Band + Division + PNP Non PNP status + Population Density + Income Level + Dhaka/Out of Dhaka N | AC824: Above P75 | AD824: 765617.1 | AE824: 0.73654111 | AF824: 0.079822238 | AH824: 297223 | AI824: 3081126 | AJ824: 1665999 | AK824: 2176026 | AM824: 40925.003 | AN824: 255439.19 | AO824: 96459.319 | AP824: 183522.9 | AQ824: 0.12194731 | AR824: =K824&L824 -> ChattogramCumilla | AS824: 0.004 | AT824: I shape | AU824: Ground floor | AV824: FR
A825: 940 | B825: F896 | C825: Singair Busstand | D825: =CONCATENATE(J825,K825,L825,M825,,N825,O825,P825,Q825,AT825,AU825) -> 1001 - 1500 SFTDhakaManikganjNon-PNPHigh Street W Residential BlockMBজেলা শহরSquare ⬜ shapeGround floor | E825: =CONCATENATE('Outlet Data'!K825,L825,'Outlet Data'!N825,M825) -> DhakaManikganjHigh Street W Residential BlockNon-PNP | F825: =CONCATENATE(L825,Q825,M825) -> Manikganjজেলা শহরNon-PNP | G825: =CONCATENATE(L825,M825) -> ManikganjNon-PNP | H825: 46080 | I825: 1168 | J825: =IF(I825="","",IF(I825<=1000,"Below 1000 SFT",IF(I825>10000,"More Then 10000 SFT",(INT((I825-1001)/500)*500+1001)&" - "&(INT((I825-1001)/500)*500+1500)&" SFT"))) -> 1001 - 1500 SFT | K825: Dhaka | L825: Manikganj | M825: Non-PNP | N825: High Street W Residential Block | O825: M | P825: B | Q825: জেলা শহর | R825: Dhaka | S825: 431277.5 | T825: 369.24443 | U825: 371642.75 | V825: 591045.75 | W825: 1445730 | X825: 953500.6 | Y825: 1792550.9 | Z825: 55 | AA825: L2 Strong: SFT+Division+PNP+Pop+Income+Dhaka | AB825: SFT Band + Division + PNP Non PNP status + Population Density + Income Level + Dhaka/Out of Dhaka N | AC825: Below P25 | AD825: -1014452.5 | AE825: -0.70168877 | AF825: -0.038611849 | AH825: 9899 | AI825: 570598 | AJ825: 492224 | AK825: 652389 | AM825: 1314.3536 | AN825: -56532.762 | AO825: -3087.6011 | AP825: -8303.6769 | AQ825: 0.12036542 | AR825: =K825&L825 -> DhakaManikganj | AS825: 0.004 | AT825: Square ⬜ shape | AU825: Ground floor | AV825: FR
A826: 896 | B826: F841 | C826: Natun Bazar,Santahar,Bogura | D826: =CONCATENATE(J826,K826,L826,M826,,N826,O826,P826,Q826,AT826,AU826) -> 1501 - 2000 SFTRajshahiBoguraNon-PNPCommercial HubMBথানা সদরI shapeGround floor | E826: =CONCATENATE('Outlet Data'!K826,L826,'Outlet Data'!N826,M826) -> RajshahiBoguraCommercial HubNon-PNP | F826: =CONCATENATE(L826,Q826,M826) -> Boguraথানা সদরNon-PNP | G826: =CONCATENATE(L826,M826) -> BoguraNon-PNP | H826: 46081 | I826: 1800 | J826: =IF(I826="","",IF(I826<=1000,"Below 1000 SFT",IF(I826>10000,"More Then 10000 SFT",(INT((I826-1001)/500)*500+1001)&" - "&(INT((I826-1001)/500)*500+1500)&" SFT"))) -> 1501 - 2000 SFT | K826: Rajshahi | L826: Bogura | M826: Non-PNP | N826: Commercial Hub | O826: M | P826: B | Q826: থানা সদর | R826: Non Dhaka | S826: 354467.2 | T826: 196.92622 | U826: 81253 | V826: 505585 | W826: 1626061.4 | X826: 1156354.2 | Y826: 1862342.6 | Z826: 5 | AA826: L2 Strong: SFT+Division+PNP+Pop+Income+Dhaka | AB826: SFT Band + Division + PNP Non PNP status + Population Density + Income Level + Dhaka/Out of Dhaka N | AC826: Below P25 | AD826: -1271594.2 | AE826: -0.78200872 | AF826: -0.09325384 | AG826: 0 | AH826: 81253 | AI826: 735296 | AJ826: 450202 | AK826: 505585 | AL826: -26419.36 | AM826: -79670.704 | AN826: 10744.445 | AO826: -65739.289 | AP826: -4192.2303 | AQ826: 0.11943651 | AR826: =K826&L826 -> RajshahiBogura | AS826: 0.004 | AT826: I shape | AU826: Ground floor | AV826: FR
A827: 901 | B827: F855 | C827: Police Line Rangpur | D827: =CONCATENATE(J827,K827,L827,M827,,N827,O827,P827,Q827,AT827,AU827) -> 2501 - 3000 SFTRangpurRangpurPNPCommercial HubMBবিভাগীয় শহরSquare ⬜ shapeGround floor | E827: =CONCATENATE('Outlet Data'!K827,L827,'Outlet Data'!N827,M827) -> RangpurRangpurCommercial HubPNP | F827: =CONCATENATE(L827,Q827,M827) -> Rangpurবিভাগীয় শহরPNP | G827: =CONCATENATE(L827,M827) -> RangpurPNP | H827: 46081 | I827: 2750 | J827: =IF(I827="","",IF(I827<=1000,"Below 1000 SFT",IF(I827>10000,"More Then 10000 SFT",(INT((I827-1001)/500)*500+1001)&" - "&(INT((I827-1001)/500)*500+1500)&" SFT"))) -> 2501 - 3000 SFT | K827: Rangpur | L827: Rangpur | M827: PNP | N827: Commercial Hub | O827: M | P827: B | Q827: বিভাগীয় শহর | R827: Non Dhaka | S827: 1131382.8 | T827: 411.41193 | U827: 3886 | V827: 1800581 | W827: 5357420.8 | X827: 4351776.4 | Y827: 9094796.8 | Z827: 13 | AA827: L5 Balanced: SFT+PNP+Pop+Income | AB827: SFT Band + PNP Non PNP status + Population Density + Income Level | AC827: Below P25 | AD827: -4226038 | AE827: -0.7888195 | AF827: 0.02739101 | AG827: 0 | AH827: 3886 | AI827: 1682370 | AJ827: 1800581 | AK827: 2170077 | AL827: -23467.73 | AM827: -111430.17 | AN827: 39268.798 | AO827: 112761.53 | AP827: 137816.15 | AQ827: 0.1378157 | AR827: =K827&L827 -> RangpurRangpur | AS827: 0.004 | AT827: Square ⬜ shape | AU827: Ground floor | AV827: FR
A828: 930 | B828: F865 | C828: Polashbari Gaibandha | D828: =CONCATENATE(J828,K828,L828,M828,,N828,O828,P828,Q828,AT828,AU828) -> 1001 - 1500 SFTRangpurGaibandhaNon-PNPHigh StreetMAথানা সদরL shapeSlightly upper than Ground floor | E828: =CONCATENATE('Outlet Data'!K828,L828,'Outlet Data'!N828,M828) -> RangpurGaibandhaHigh StreetNon-PNP | F828: =CONCATENATE(L828,Q828,M828) -> Gaibandhaথানা সদরNon-PNP | G828: =CONCATENATE(L828,M828) -> GaibandhaNon-PNP | H828: 46081 | I828: 1500 | J828: =IF(I828="","",IF(I828<=1000,"Below 1000 SFT",IF(I828>10000,"More Then 10000 SFT",(INT((I828-1001)/500)*500+1001)&" - "&(INT((I828-1001)/500)*500+1500)&" SFT"))) -> 1001 - 1500 SFT | K828: Rangpur | L828: Gaibandha | M828: Non-PNP | N828: High Street | O828: M | P828: A | Q828: থানা সদর | R828: Non Dhaka | S828: 948607.75 | T828: 632.40517 | U828: 765094.25 | V828: 1294793 | W828: 1079839.5 | X828: 843126.25 | Y828: 1494620.3 | Z828: 148 | AA828: L6 Practical: SFT+PNP+Dhaka | AB828: SFT Band + PNP Non PNP status + Dhaka/Out of Dhaka N | AC828: Within P25–P75 | AD828: -131231.75 | AE828: -0.12152894 | AF828: 0.014727495 | AH828: 2180 | AI828: 1203160 | AJ828: 1019399 | AK828: 1569692 | AM828: 107.04471 | AN828: -22094.09 | AO828: -9621.1175 | AP828: 87490.627 | AQ828: 0.079666722 | AR828: =K828&L828 -> RangpurGaibandha | AS828: 0.004 | AT828: L shape | AU828: Slightly upper than Ground floor | AV828: FR
A829: 932 | B829: F871 | C829: Aam Chattar, Rajshahi Outlet | D829: =CONCATENATE(J829,K829,L829,M829,,N829,O829,P829,Q829,AT829,AU829) -> 1001 - 1500 SFTRajshahiRajshahiNon-PNPCommercial HubMBবিভাগীয় শহরSquare ⬜ shapeSlightly upper than Ground floor | E829: =CONCATENATE('Outlet Data'!K829,L829,'Outlet Data'!N829,M829) -> RajshahiRajshahiCommercial HubNon-PNP | F829: =CONCATENATE(L829,Q829,M829) -> Rajshahiবিভাগীয় শহরNon-PNP | G829: =CONCATENATE(L829,M829) -> RajshahiNon-PNP | H829: 46081 | I829: 1360 | J829: =IF(I829="","",IF(I829<=1000,"Below 1000 SFT",IF(I829>10000,"More Then 10000 SFT",(INT((I829-1001)/500)*500+1001)&" - "&(INT((I829-1001)/500)*500+1500)&" SFT"))) -> 1001 - 1500 SFT | K829: Rajshahi | L829: Rajshahi | M829: Non-PNP | N829: Commercial Hub | O829: M | P829: B | Q829: বিভাগীয় শহর | R829: Non Dhaka | S829: 556364 | T829: 409.09118 | U829: 465116.75 | V829: 795821.25 | W829: 949666.7 | X829: 686228.35 | Y829: 1376057.9 | Z829: 32 | AA829: L4 Balanced: SFT+PNP+Pop+Income+Dhaka | AB829: SFT Band + PNP Non PNP status + Population Density + Income Level + Dhaka/Out of Dhaka N | AC829: Below P25 | AD829: -393302.7 | AE829: -0.41414814 | AF829: -0.023426091 | AH829: 1163 | AI829: 619768 | AJ829: 789380 | AK829: 815145 | AM829: -5057.112 | AN829: -57843.265 | AO829: 7611.0428 | AP829: 3155.599 | AQ829: 0.13368908 | AR829: =K829&L829 -> RajshahiRajshahi | AS829: 0.004 | AT829: Square ⬜ shape | AU829: Slightly upper than Ground floor | AV829: FR
A830: 938 | B830: F891 | C830: Muktarpara Netrokona | D830: =CONCATENATE(J830,K830,L830,M830,,N830,O830,P830,Q830,AT830,AU830) -> 2001 - 2500 SFTMymensinghNetrokonaNon-PNPCommercial HubMBজেলা শহরL shapeGround floor | E830: =CONCATENATE('Outlet Data'!K830,L830,'Outlet Data'!N830,M830) -> MymensinghNetrokonaCommercial HubNon-PNP | F830: =CONCATENATE(L830,Q830,M830) -> Netrokonaজেলা শহরNon-PNP | G830: =CONCATENATE(L830,M830) -> NetrokonaNon-PNP | H830: 46081 | I830: 2370 | J830: =IF(I830="","",IF(I830<=1000,"Below 1000 SFT",IF(I830>10000,"More Then 10000 SFT",(INT((I830-1001)/500)*500+1001)&" - "&(INT((I830-1001)/500)*500+1500)&" SFT"))) -> 2001 - 2500 SFT | K830: Mymensingh | L830: Netrokona | M830: Non-PNP | N830: Commercial Hub | O830: M | P830: B | Q830: জেলা শহর | R830: Non Dhaka | S830: 679014.25 | T830: 286.5039 | U830: 583883.25 | V830: 906528.5 | W830: 1599551.6 | X830: 1167925.5 | Y830: 2319376.6 | Z830: 60 | AA830: L4 Balanced: SFT+PNP+Pop+Income+Dhaka | AB830: SFT Band + PNP Non PNP status + Population Density + Income Level + Dhaka/Out of Dhaka N | AC830: Below P25 | AD830: -920537.35 | AE830: -0.57549713 | AF830: -0.031142091 | AH830: 60717 | AI830: 1032545 | AJ830: 758272 | AK830: 864523 | AM830: -14605.645 | AN830: -72989.857 | AO830: -18744.855 | AP830: 21756.663 | AQ830: 0.11441282 | AR830: =K830&L830 -> MymensinghNetrokona | AS830: 0.004 | AT830: L shape | AU830: Ground floor | AV830: FR
A831: 941 | B831: F897 | C831: Mukul Cinema hall Road Patuakhali | D831: =CONCATENATE(J831,K831,L831,M831,,N831,O831,P831,Q831,AT831,AU831) -> Below 1000 SFTBarishalPatuakhaliNon-PNPCommercial HubLBজেলা শহরSquare ⬜ shapeGround floor | E831: =CONCATENATE('Outlet Data'!K831,L831,'Outlet Data'!N831,M831) -> BarishalPatuakhaliCommercial HubNon-PNP | F831: =CONCATENATE(L831,Q831,M831) -> Patuakhaliজেলা শহরNon-PNP | G831: =CONCATENATE(L831,M831) -> PatuakhaliNon-PNP | H831: 46081 | I831: 1000 | J831: =IF(I831="","",IF(I831<=1000,"Below 1000 SFT",IF(I831>10000,"More Then 10000 SFT",(INT((I831-1001)/500)*500+1001)&" - "&(INT((I831-1001)/500)*500+1500)&" SFT"))) -> Below 1000 SFT | K831: Barishal | L831: Patuakhali | M831: Non-PNP | N831: Commercial Hub | O831: L | P831: B | Q831: জেলা শহর | R831: Non Dhaka | S831: 266423.5 | T831: 266.4235 | U831: 200594.5 | V831: 382857.5 | W831: 672715.6 | X831: 494034.8 | Y831: 1190597.4 | Z831: 33 | AA831: L6 Practical: SFT+PNP+Dhaka | AB831: SFT Band + PNP Non PNP status + Dhaka/Out of Dhaka N | AC831: Below P25 | AD831: -406292.1 | AE831: -0.6039582 | AF831: -0.22883736 | AH831: 6265 | AI831: 425372 | AJ831: 265371 | AK831: 368686 | AM831: 722.78578 | AN831: -85045.383 | AO831: -76115.464 | AP831: -83432.543 | AQ831: 0.10828417 | AR831: =K831&L831 -> BarishalPatuakhali | AS831: 0.004 | AT831: Square ⬜ shape | AU831: Ground floor | AV831: FR
A832: 942 | B832: F898 | C832: Razabari Chourasta Turag, Dhaka | D832: =CONCATENATE(J832,K832,L832,M832,,N832,O832,P832,Q832,AT832,AU832) -> Below 1000 SFTDhakaDhakaNon-PNPCommercial HubMBবিভাগীয় শহরSquare ⬜ shapeGround floor | E832: =CONCATENATE('Outlet Data'!K832,L832,'Outlet Data'!N832,M832) -> DhakaDhakaCommercial HubNon-PNP | F832: =CONCATENATE(L832,Q832,M832) -> Dhakaবিভাগীয় শহরNon-PNP | G832: =CONCATENATE(L832,M832) -> DhakaNon-PNP | H832: 46081 | I832: 1000 | J832: =IF(I832="","",IF(I832<=1000,"Below 1000 SFT",IF(I832>10000,"More Then 10000 SFT",(INT((I832-1001)/500)*500+1001)&" - "&(INT((I832-1001)/500)*500+1500)&" SFT"))) -> Below 1000 SFT | K832: Dhaka | L832: Dhaka | M832: Non-PNP | N832: Commercial Hub | O832: M | P832: B | Q832: বিভাগীয় শহর | R832: Dhaka | S832: 1100252 | T832: 1100.252 | U832: 945053 | V832: 1532617.5 | W832: 1100252 | X832: 723334 | Y832: 1342015 | Z832: 13 | AA832: L2 Strong: SFT+Division+PNP+Pop+Income+Dhaka | AB832: SFT Band + Division + PNP Non PNP status + Population Density + Income Level + Dhaka/Out of Dhaka N | AC832: Within P25–P75 | AD832: 0 | AE832: 0 | AF832: 0.024289544 | AH832: 84842 | AI832: 1523047 | AJ832: 1231790 | AK832: 1561329 | AM832: -16182.894 | AN832: 19734.982 | AO832: 46539.687 | AP832: 56806.702 | AQ832: 0.11186141 | AR832: =K832&L832 -> DhakaDhaka | AS832: 0.004 | AT832: Square ⬜ shape | AU832: Ground floor | AV832: FR
A833: 943 | B833: F899 | C833: Hossainpur Bazar Kishoreganj | D833: =CONCATENATE(J833,K833,L833,M833,,N833,O833,P833,Q833,AT833,AU833) -> 1001 - 1500 SFTMymensinghKishoreganjNon-PNPCommercial HubLCথানা সদরL shapeGround floor | E833: =CONCATENATE('Outlet Data'!K833,L833,'Outlet Data'!N833,M833) -> MymensinghKishoreganjCommercial HubNon-PNP | F833: =CONCATENATE(L833,Q833,M833) -> Kishoreganjথানা সদরNon-PNP | G833: =CONCATENATE(L833,M833) -> KishoreganjNon-PNP | H833: 46081 | I833: 1382 | J833: =IF(I833="","",IF(I833<=1000,"Below 1000 SFT",IF(I833>10000,"More Then 10000 SFT",(INT((I833-1001)/500)*500+1001)&" - "&(INT((I833-1001)/500)*500+1500)&" SFT"))) -> 1001 - 1500 SFT | K833: Mymensingh | L833: Kishoreganj | M833: Non-PNP | N833: Commercial Hub | O833: L | P833: C | Q833: থানা সদর | R833: Non Dhaka | S833: 862916 | T833: 624.39653 | U833: 689323.25 | V833: 1228710.8 | W833: 1079839.5 | X833: 868062.35 | Y833: 1495543 | Z833: 58 | AA833: L4 Balanced: SFT+PNP+Pop+Income+Dhaka | AB833: SFT Band + PNP Non PNP status + Population Density + Income Level + Dhaka/Out of Dhaka N | AC833: Below P25 | AD833: -216923.5 | AE833: -0.20088495 | AF833: 0.02878179 | AH833: 22832 | AI833: 1198749 | AJ833: 911487 | AK833: 1318596 | AM833: 3336.5321 | AN833: 39429.708 | AO833: 27661.322 | AP833: 28917.507 | AQ833: 0.13249057 | AR833: =K833&L833 -> MymensinghKishoreganj | AS833: 0.004 | AT833: L shape | AU833: Ground floor | AV833: FR
A834: 944 | B834: F900 | C834: Mollar Hat, Shariatpur | D834: =CONCATENATE(J834,K834,L834,M834,,N834,O834,P834,Q834,AT834,AU834) -> 1501 - 2000 SFTDhakaShariatpurNon-PNPHigh StreetLBঅন্যান্যSquare ⬜ shapeGround floor | E834: =CONCATENATE('Outlet Data'!K834,L834,'Outlet Data'!N834,M834) -> DhakaShariatpurHigh StreetNon-PNP | F834: =CONCATENATE(L834,Q834,M834) -> Shariatpurঅন্যান্যNon-PNP | G834: =CONCATENATE(L834,M834) -> ShariatpurNon-PNP | H834: 46081 | I834: 1602 | J834: =IF(I834="","",IF(I834<=1000,"Below 1000 SFT",IF(I834>10000,"More Then 10000 SFT",(INT((I834-1001)/500)*500+1001)&" - "&(INT((I834-1001)/500)*500+1500)&" SFT"))) -> 1501 - 2000 SFT | K834: Dhaka | L834: Shariatpur | M834: Non-PNP | N834: High Street | O834: L | P834: B | Q834: অন্যান্য | R834: Dhaka | S834: 595163.5 | T834: 371.5128 | U834: 406370.25 | V834: 817139.25 | W834: 1452852.8 | X834: 1260741 | Y834: 1614909.3 | Z834: 7 | AA834: L2 Strong: SFT+Division+PNP+Pop+Income+Dhaka | AB834: SFT Band + Division + PNP Non PNP status + Population Density + Income Level + Dhaka/Out of Dhaka N | AC834: Below P25 | AD834: -857689.3 | AE834: -0.59034838 | AF834: -0.036387203 | AH834: 2541 | AI834: 1121421 | AJ834: 540980 | AK834: 715712 | AM834: 333.78649 | AN834: 9251.2507 | AO834: -20972.604 | AP834: -75237.774 | AQ834: 0.12113778 | AR834: =K834&L834 -> DhakaShariatpur | AS834: 0.0096796628 | AT834: Square ⬜ shape | AU834: Ground floor | AV834: FR
A835: 945 | B835: F901 | C835: Oskhali Hatiya Noakhali | D835: =CONCATENATE(J835,K835,L835,M835,,N835,O835,P835,Q835,AT835,AU835) -> 1501 - 2000 SFTChattogramNoakhaliNon-PNPCommercial HubMBথানা সদরI shapeGround floor | E835: =CONCATENATE('Outlet Data'!K835,L835,'Outlet Data'!N835,M835) -> ChattogramNoakhaliCommercial HubNon-PNP | F835: =CONCATENATE(L835,Q835,M835) -> Noakhaliথানা সদরNon-PNP | G835: =CONCATENATE(L835,M835) -> NoakhaliNon-PNP | H835: 46081 | I835: 2000 | J835: =IF(I835="","",IF(I835<=1000,"Below 1000 SFT",IF(I835>10000,"More Then 10000 SFT",(INT((I835-1001)/500)*500+1001)&" - "&(INT((I835-1001)/500)*500+1500)&" SFT"))) -> 1501 - 2000 SFT | K835: Chattogram | L835: Noakhali | M835: Non-PNP | N835: Commercial Hub | O835: M | P835: B | Q835: থানা সদর | R835: Non Dhaka | S835: 1158798.8 | T835: 579.39937 | U835: 705182.25 | V835: 1578786.5 | W835: 1730070.3 | X835: 1191184.5 | Y835: 3396251.9 | Z835: 16 | AA835: L2 Strong: SFT+Division+PNP+Pop+Income+Dhaka | AB835: SFT Band + Division + PNP Non PNP status + Population Density + Income Level + Dhaka/Out of Dhaka N | AC835: Below P25 | AD835: -571271.55 | AE835: -0.33020135 | AF835: 0.061439915 | AH835: 106821 | AI835: 2278034 | AJ835: 904636 | AK835: 1345704 | AM835: 13557.744 | AN835: 189946.12 | AO835: 35008.687 | AP835: 46273.439 | AQ835: 0.11909 | AR835: =K835&L835 -> ChattogramNoakhali | AS835: 0.004 | AT835: I shape | AU835: Ground floor | AV835: FR
A836: 946 | B836: F902 | C836: Hospital Road, Atwari, Panchagarh | D836: =CONCATENATE(J836,K836,L836,M836,,N836,O836,P836,Q836,AT836,AU836) -> 1001 - 1500 SFTRangpurPanchagarhNon-PNPHigh StreetMCথানা সদরI shapeGround floor | E836: =CONCATENATE('Outlet Data'!K836,L836,'Outlet Data'!N836,M836) -> RangpurPanchagarhHigh StreetNon-PNP | F836: =CONCATENATE(L836,Q836,M836) -> Panchagarhথানা সদরNon-PNP | G836: =CONCATENATE(L836,M836) -> PanchagarhNon-PNP | H836: 46081 | I836: 1078 | J836: =IF(I836="","",IF(I836<=1000,"Below 1000 SFT",IF(I836>10000,"More Then 10000 SFT",(INT((I836-1001)/500)*500+1001)&" - "&(INT((I836-1001)/500)*500+1500)&" SFT"))) -> 1001 - 1500 SFT | K836: Rangpur | L836: Panchagarh | M836: Non-PNP | N836: High Street | O836: M | P836: C | Q836: থানা সদর | R836: Non Dhaka | S836: 587904.25 | T836: 545.36572 | U836: 461253.5 | V836: 819844.25 | W836: 977323.5 | X836: 732609.06 | Y836: 1092969.7 | Z836: 8 | AA836: L2 Strong: SFT+Division+PNP+Pop+Income+Dhaka | AB836: SFT Band + Division + PNP Non PNP status + Population Density + Income Level + Dhaka/Out of Dhaka N | AC836: Below P25 | AD836: -389419.25 | AE836: -0.39845481 | AF836: 0.0067268103 | AH836: 1550 | AI836: 771899 | AJ836: 614488 | AK836: 963680 | AM836: 255.13025 | AN836: 27134.583 | AO836: -46323.825 | AP836: 34752.993 | AQ836: 0.1258468 | AR836: =K836&L836 -> RangpurPanchagarh | AS836: 0.004 | AT836: I shape | AU836: Ground floor | AV836: FR
A837: 947 | B837: F903 | C837: Hatirpool Exp (PNP) | D837: =CONCATENATE(J837,K837,L837,M837,,N837,O837,P837,Q837,AT837,AU837) -> 4001 - 4500 SFTDhakaDhakaPNPCommercial HubHAবিভাগীয় শহরSquare ⬜ shapeSlightly upper than Ground floor | E837: =CONCATENATE('Outlet Data'!K837,L837,'Outlet Data'!N837,M837) -> DhakaDhakaCommercial HubPNP | F837: =CONCATENATE(L837,Q837,M837) -> Dhakaবিভাগীয় শহরPNP | G837: =CONCATENATE(L837,M837) -> DhakaPNP | H837: 46081 | I837: 4236 | J837: =IF(I837="","",IF(I837<=1000,"Below 1000 SFT",IF(I837>10000,"More Then 10000 SFT",(INT((I837-1001)/500)*500+1001)&" - "&(INT((I837-1001)/500)*500+1500)&" SFT"))) -> 4001 - 4500 SFT | K837: Dhaka | L837: Dhaka | M837: PNP | N837: Commercial Hub | O837: H | P837: A | Q837: বিভাগীয় শহর | R837: Dhaka | S837: 3269113.2 | T837: 771.74534 | U837: 2628885.5 | V837: 4561844.8 | W837: 13530057 | X837: 11573069 | Y837: 21008994 | Z837: 6 | AA837: L4 Balanced: SFT+PNP+Pop+Income+Dhaka | AB837: SFT Band + PNP Non PNP status + Population Density + Income Level + Dhaka/Out of Dhaka N | AC837: Below P25 | AD837: -10260944 | AE837: -0.75838142 | AF837: -0.044053453 | AH837: 140 | AI837: 3505134 | AJ837: 4338100 | AK837: 5233079 | AM837: 17003.43 | AN837: -227128.84 | AO837: -110832.42 | AP837: -255105.09 | AQ837: 0.071863895 | AR837: =K837&L837 -> DhakaDhaka | AS837: 0.037150401 | AT837: Square ⬜ shape | AU837: Slightly upper than Ground floor | AV837: FR
A838: 948 | B838: F904 | C838: Digraj Bazar Mongla Baherhat | D838: =CONCATENATE(J838,K838,L838,M838,,N838,O838,P838,Q838,AT838,AU838) -> 1001 - 1500 SFTKhulnaBagerhatNon-PNPHigh StreetMBথানা সদরSquare ⬜ shapeGround floor | E838: =CONCATENATE('Outlet Data'!K838,L838,'Outlet Data'!N838,M838) -> KhulnaBagerhatHigh StreetNon-PNP | F838: =CONCATENATE(L838,Q838,M838) -> Bagerhatথানা সদরNon-PNP | G838: =CONCATENATE(L838,M838) -> BagerhatNon-PNP | H838: 46081 | I838: 1350 | J838: =IF(I838="","",IF(I838<=1000,"Below 1000 SFT",IF(I838>10000,"More Then 10000 SFT",(INT((I838-1001)/500)*500+1001)&" - "&(INT((I838-1001)/500)*500+1500)&" SFT"))) -> 1001 - 1500 SFT | K838: Khulna | L838: Bagerhat | M838: Non-PNP | N838: High Street | O838: M | P838: B | Q838: থানা সদর | R838: Non Dhaka | S838: 729189.25 | T838: 540.14019 | U838: 647910.25 | V838: 997635 | W838: 774190.53 | X838: 651933.81 | Y838: 1290955.3 | Z838: 6 | AA838: L2 Strong: SFT+Division+PNP+Pop+Income+Dhaka | AB838: SFT Band + Division + PNP Non PNP status + Population Density + Income Level + Dhaka/Out of Dhaka N | AC838: Within P25–P75 | AD838: -45001.275 | AE838: -0.058126874 | AF838: -0.0021240364 | AH838: 6964 | AI838: 971153 | AJ838: 861559 | AK838: 1077081 | AM838: 876.99612 | AN838: -13350.405 | AO838: 7849.5259 | AP838: -1571.4152 | AQ838: 0.12888123 | AR838: =K838&L838 -> KhulnaBagerhat | AS838: 0.004 | AT838: Square ⬜ shape | AU838: Ground floor | AV838: FR
A839: 949 | B839: F910 | C839: Raninagar Bazar Naogaon | D839: =CONCATENATE(J839,K839,L839,M839,,N839,O839,P839,Q839,AT839,AU839) -> 1501 - 2000 SFTRajshahiNaogaonNon-PNPCommercial HubLBথানা সদরI shapeGround floor | E839: =CONCATENATE('Outlet Data'!K839,L839,'Outlet Data'!N839,M839) -> RajshahiNaogaonCommercial HubNon-PNP | F839: =CONCATENATE(L839,Q839,M839) -> Naogaonথানা সদরNon-PNP | G839: =CONCATENATE(L839,M839) -> NaogaonNon-PNP | H839: 46081 | I839: 1644 | J839: =IF(I839="","",IF(I839<=1000,"Below 1000 SFT",IF(I839>10000,"More Then 10000 SFT",(INT((I839-1001)/500)*500+1001)&" - "&(INT((I839-1001)/500)*500+1500)&" SFT"))) -> 1501 - 2000 SFT | K839: Rajshahi | L839: Naogaon | M839: Non-PNP | N839: Commercial Hub | O839: L | P839: B | Q839: থানা সদর | R839: Non Dhaka | S839: 413751.5 | T839: 251.67366 | U839: 289048.5 | V839: 605784 | W839: 1139127.4 | X839: 1058350.4 | Y839: 1409869 | Z839: 5 | AA839: L2 Strong: SFT+Division+PNP+Pop+Income+Dhaka | AB839: SFT Band + Division + PNP Non PNP status + Population Density + Income Level + Dhaka/Out of Dhaka N | AC839: Below P25 | AD839: -725375.9 | AE839: -0.63678207 | AF839: -0.036661505 | AH839: 2241 | AI839: 577511 | AJ839: 384651 | AK839: 690603 | AM839: -22816.294 | AN839: -89.032521 | AO839: -56611.431 | AP839: 18841.747 | AQ839: 0.096791624 | AR839: =K839&L839 -> RajshahiNaogaon | AS839: 0.004 | AT839: I shape | AU839: Ground floor | AV839: FR
... A842: 952 | B842: F919 | C842: Mohammadpur Bus Stand, | D842: =CONCATENATE(J842,K842,L842,M842,,N842,O842,P842,Q842,AT842,AU842) -> Below 1000 SFTDhakaDhakaNon-PNPCommercial HubMBবিভাগীয় শহরOthersGround floor | E842: =CONCATENATE('Outlet Data'!K842,L842,'Outlet Data'!N842,M842) -> DhakaDhakaCommercial HubNon-PNP | F842: =CONCATENATE(L842,Q842,M842) -> Dhakaবিভাগীয় শহরNon-PNP | G842: =CONCATENATE(L842,M842) -> DhakaNon-PNP | H842: 46081 | I842: 600 | J842: =IF(I842="","",IF(I842<=1000,"Below 1000 SFT",IF(I842>10000,"More Then 10000 SFT",(INT((I842-1001)/500)*500+1001)&" - "&(INT((I842-1001)/500)*500+1500)&" SFT"))) -> Below 1000 SFT | K842: Dhaka | L842: Dhaka | M842: Non-PNP | N842: Commercial Hub | O842: M | P842: B | Q842: বিভাগীয় শহর | R842: Dhaka | S842: 598025.5 | T842: 996.70917 | U842: 515970.25 | V842: 826393.75 | W842: 1100252 | X842: 723334 | Y842: 1342015 | Z842: 13 | AA842: L2 Strong: SFT+Division+PNP+Pop+Income+Dhaka | AB842: SFT Band + Division + PNP Non PNP status + Population Density + Income Level + Dhaka/Out of Dhaka N | AC842: Below P25 | AD842: -502226.5 | AE842: -0.45646497 | AF842: -0.027544919 | AH842: 3259 | AI842: 686874 | AJ842: 801803 | AK842: 900166 | AM842: 350.79081 | AN842: -33387.746 | AO842: -34624.341 | AP842: 1771.0413 | AQ842: 0.11233756 | AR842: =K842&L842 -> DhakaDhaka | AS842: 0.004 | AT842: Others | AU842: Ground floor | AV842: FR
A843: 957 | B843: F907 | C843: Outpara, Chandona Chowrasta, Gazipur Outlet | D843: =CONCATENATE(J843,K843,L843,M843,,N843,O843,P843,Q843,AT843,AU843) -> 1501 - 2000 SFTDhakaGazipurNon-PNPWithin the MahallaMCথানা সদরSquare ⬜ shapeGround floor | E843: =CONCATENATE('Outlet Data'!K843,L843,'Outlet Data'!N843,M843) -> DhakaGazipurWithin the MahallaNon-PNP | F843: =CONCATENATE(L843,Q843,M843) -> Gazipurথানা সদরNon-PNP | G843: =CONCATENATE(L843,M843) -> GazipurNon-PNP | H843: 46097 | I843: 1784 | J843: =IF(I843="","",IF(I843<=1000,"Below 1000 SFT",IF(I843>10000,"More Then 10000 SFT",(INT((I843-1001)/500)*500+1001)&" - "&(INT((I843-1001)/500)*500+1500)&" SFT"))) -> 1501 - 2000 SFT | K843: Dhaka | L843: Gazipur | M843: Non-PNP | N843: Within the Mahalla | O843: M | P843: C | Q843: থানা সদর | R843: Dhaka | S843: 828048.67 | T843: 464.15284 | U843: 697120 | V843: 1004975.5 | W843: 1992692.2 | X843: 1544437.2 | Y843: 2689592.2 | Z843: 37 | AA843: L2 Strong: SFT+Division+PNP+Pop+Income+Dhaka | AB843: SFT Band + Division + PNP Non PNP status + Population Density + Income Level + Dhaka/Out of Dhaka N | AC843: Below P25 | AD843: -1164643.5 | AE843: -0.58445732 | AF843: -0.0022956206 | AI843: 474195 | AJ843: 920045 | AK843: 1089906 | AN843: 16339.58 | AO843: -3911.9298 | AP843: -18130.307 | AQ843: 0.052244555 | AR843: =K843&L843 -> DhakaGazipur | AS843: 0.004 | AT843: Square ⬜ shape | AU843: Ground floor | AV843: FR
A844: 964 | B844: F923 | C844: Tamirul Millat Road, Uttar Auchpara Ouelet | D844: =CONCATENATE(J844,K844,L844,M844,,N844,O844,P844,Q844,AT844,AU844) -> Below 1000 SFTDhakaGazipurNon-PNPHigh Street W Residential BlockMBথানা সদরSquare ⬜ shapeGround floor | E844: =CONCATENATE('Outlet Data'!K844,L844,'Outlet Data'!N844,M844) -> DhakaGazipurHigh Street W Residential BlockNon-PNP | F844: =CONCATENATE(L844,Q844,M844) -> Gazipurথানা সদরNon-PNP | G844: =CONCATENATE(L844,M844) -> GazipurNon-PNP | H844: 46097 | I844: 700 | J844: =IF(I844="","",IF(I844<=1000,"Below 1000 SFT",IF(I844>10000,"More Then 10000 SFT",(INT((I844-1001)/500)*500+1001)&" - "&(INT((I844-1001)/500)*500+1500)&" SFT"))) -> Below 1000 SFT | K844: Dhaka | L844: Gazipur | M844: Non-PNP | N844: High Street W Residential Block | O844: M | P844: B | Q844: থানা সদর | R844: Dhaka | S844: 663562 | T844: 947.94571 | U844: 584792.5 | V844: 804764 | W844: 1100252 | X844: 723334 | Y844: 1342015 | Z844: 13 | AA844: L2 Strong: SFT+Division+PNP+Pop+Income+Dhaka | AB844: SFT Band + Division + PNP Non PNP status + Population Density + Income Level + Dhaka/Out of Dhaka N | AC844: Below P25 | AD844: -436690 | AE844: -0.39689998 | AF844: -0.0068540555 | AI844: 381158 | AJ844: 788427 | AK844: 821101 | AN844: -3771.2931 | AO844: 20212.176 | AP844: -30085.155 | AQ844: 0.055208551 | AR844: =K844&L844 -> DhakaGazipur | AS844: 0.004 | AT844: Square ⬜ shape | AU844: Ground floor | AV844: FR
A845: 958 | B845: F909 | C845: Banasree A block Titas Road | D845: =CONCATENATE(J845,K845,L845,M845,,N845,O845,P845,Q845,AT845,AU845) -> Below 1000 SFTDhakaDhakaNon-PNPWithin the MahallaMBবিভাগীয় শহরTriangle 🔽 ShapeGround floor | E845: =CONCATENATE('Outlet Data'!K845,L845,'Outlet Data'!N845,M845) -> DhakaDhakaWithin the MahallaNon-PNP | F845: =CONCATENATE(L845,Q845,M845) -> Dhakaবিভাগীয় শহরNon-PNP | G845: =CONCATENATE(L845,M845) -> DhakaNon-PNP | H845: 46098 | I845: 965 | J845: =IF(I845="","",IF(I845<=1000,"Below 1000 SFT",IF(I845>10000,"More Then 10000 SFT",(INT((I845-1001)/500)*500+1001)&" - "&(INT((I845-1001)/500)*500+1500)&" SFT"))) -> Below 1000 SFT | K845: Dhaka | L845: Dhaka | M845: Non-PNP | N845: Within the Mahalla | O845: M | P845: B | Q845: বিভাগীয় শহর | R845: Dhaka | S845: 723334 | T845: 749.56891 | U845: 576615.5 | V845: 909025.5 | W845: 1100252 | X845: 723334 | Y845: 1342015 | Z845: 13 | AA845: L2 Strong: SFT+Division+PNP+Pop+Income+Dhaka | AB845: SFT Band + Division + PNP Non PNP status + Population Density + Income Level + Dhaka/Out of Dhaka N | AC845: Within P25–P75 | AD845: -376918 | AE845: -0.34257425 | AF845: -0.041049896 | AI845: 351951 | AJ845: 801280 | AK845: 1016771 | AN845: -30172.959 | AO845: -34640.008 | AP845: -24265.389 | AQ845: 0.053960163 | AR845: =K845&L845 -> DhakaDhaka | AS845: 0.004 | AT845: Triangle 🔽 Shape | AU845: Ground floor | AV845: FR
A846: 954 | B846: F875 | C846: Bosila Gardn City, Mohammadpur | D846: =CONCATENATE(J846,K846,L846,M846,,N846,O846,P846,Q846,AT846,AU846) -> 1001 - 1500 SFTDhakaDhakaNon-PNPHigh Street W Residential BlockLBথানা সদরSquare ⬜ shapeGround floor | E846: =CONCATENATE('Outlet Data'!K846,L846,'Outlet Data'!N846,M846) -> DhakaDhakaHigh Street W Residential BlockNon-PNP | F846: =CONCATENATE(L846,Q846,M846) -> Dhakaথানা সদরNon-PNP | G846: =CONCATENATE(L846,M846) -> DhakaNon-PNP | H846: 46098 | I846: 1440 | J846: =IF(I846="","",IF(I846<=1000,"Below 1000 SFT",IF(I846>10000,"More Then 10000 SFT",(INT((I846-1001)/500)*500+1001)&" - "&(INT((I846-1001)/500)*500+1500)&" SFT"))) -> 1001 - 1500 SFT | K846: Dhaka | L846: Dhaka | M846: Non-PNP | N846: High Street W Residential Block | O846: L | P846: B | Q846: থানা সদর | R846: Dhaka | S846: 1084169.7 | T846: 752.8956 | U846: 886928 | V846: 1372785 | W846: 924737.8 | X846: 766540.9 | Y846: 1143521.5 | Z846: 8 | AA846: L2 Strong: SFT+Division+PNP+Pop+Income+Dhaka | AB846: SFT Band + Division + PNP Non PNP status + Population Density + Income Level + Dhaka/Out of Dhaka N | AC846: Within P25–P75 | AD846: 159431.87 | AE846: 0.17240765 | AF846: 0.04202334 | AI846: 506939 | AJ846: 1266917 | AK846: 1478653 | AN846: 2137.5051 | AO846: 60205.857 | AP846: 74337.929 | AQ846: 0.054551016 | AR846: =K846&L846 -> DhakaDhaka | AS846: 0.004 | AT846: Square ⬜ shape | AU846: Ground floor | AV846: FR
A847: 956 | B847: F906 | C847: Nayapara Meradia | D847: =CONCATENATE(J847,K847,L847,M847,,N847,O847,P847,Q847,AT847,AU847) -> Below 1000 SFTDhakaDhakaNon-PNPWithin the MahallaMBবিভাগীয় শহরSquare ⬜ shapeGround floor | E847: =CONCATENATE('Outlet Data'!K847,L847,'Outlet Data'!N847,M847) -> DhakaDhakaWithin the MahallaNon-PNP | F847: =CONCATENATE(L847,Q847,M847) -> Dhakaবিভাগীয় শহরNon-PNP | G847: =CONCATENATE(L847,M847) -> DhakaNon-PNP | H847: 46099 | I847: 990 | J847: =IF(I847="","",IF(I847<=1000,"Below 1000 SFT",IF(I847>10000,"More Then 10000 SFT",(INT((I847-1001)/500)*500+1001)&" - "&(INT((I847-1001)/500)*500+1500)&" SFT"))) -> Below 1000 SFT | K847: Dhaka | L847: Dhaka | M847: Non-PNP | N847: Within the Mahalla | O847: M | P847: B | Q847: বিভাগীয় শহর | R847: Dhaka | S847: 860064.33 | T847: 868.75185 | U847: 771061.5 | V847: 1012798 | W847: 1100252 | X847: 723334 | Y847: 1342015 | Z847: 13 | AA847: L2 Strong: SFT+Division+PNP+Pop+Income+Dhaka | AB847: SFT Band + Division + PNP Non PNP status + Population Density + Income Level + Dhaka/Out of Dhaka N | AC847: Within P25–P75 | AD847: -240187.67 | AE847: -0.21830241 | AF847: -0.026794091 | AI847: 554597 | AJ847: 987526 | AK847: 1038070 | AN847: -10435.177 | AO847: -27611.289 | AP847: -31087.46 | AQ847: 0.051400705 | AR847: =K847&L847 -> DhakaDhaka | AS847: 0.004 | AT847: Square ⬜ shape | AU847: Ground floor | AV847: FR
A848: 963 | B848: F922 | C848: Piyajhata Road, Taherpur Rajshahi | D848: =CONCATENATE(J848,K848,L848,M848,,N848,O848,P848,Q848,AT848,AU848) -> 1001 - 1500 SFTRajshahiRajshahiNon-PNPCommercial HubMBঅন্যান্যI shapeGround floor | E848: =CONCATENATE('Outlet Data'!K848,L848,'Outlet Data'!N848,M848) -> RajshahiRajshahiCommercial HubNon-PNP | F848: =CONCATENATE(L848,Q848,M848) -> Rajshahiঅন্যান্যNon-PNP | G848: =CONCATENATE(L848,M848) -> RajshahiNon-PNP | H848: 46100 | I848: 1500 | J848: =IF(I848="","",IF(I848<=1000,"Below 1000 SFT",IF(I848>10000,"More Then 10000 SFT",(INT((I848-1001)/500)*500+1001)&" - "&(INT((I848-1001)/500)*500+1500)&" SFT"))) -> 1001 - 1500 SFT | K848: Rajshahi | L848: Rajshahi | M848: Non-PNP | N848: Commercial Hub | O848: M | P848: B | Q848: অন্যান্য | R848: Non Dhaka | S848: 282005.33 | T848: 188.00356 | U848: 239411.5 | V848: 341394 | W848: 949666.7 | X848: 686228.35 | Y848: 1376057.9 | Z848: 32 | AA848: L4 Balanced: SFT+PNP+Pop+Income+Dhaka | AB848: SFT Band + PNP Non PNP status + Population Density + Income Level + Dhaka/Out of Dhaka N | AC848: Below P25 | AD848: -667661.37 | AE848: -0.7030481 | AF848: -0.15018277 | AI848: 163228 | AJ848: 315595 | AK848: 367193 | AN848: 2988.6585 | AO848: -66222.886 | AP848: -63822.795 | AQ848: 0.058098588 | AR848: =K848&L848 -> RajshahiRajshahi | AS848: 0.004 | AT848: I shape | AU848: Ground floor | AV848: FR
A849: 959 | B849: F912 | C849: Sarkharkhana Gate, Palash, Narsingdi Outlet | D849: =CONCATENATE(J849,K849,L849,M849,,N849,O849,P849,Q849,AT849,AU849) -> 2001 - 2500 SFTDhakaNarsingdiNon-PNPCommercial HubLCথানা সদরL shapeBasement floor | E849: =CONCATENATE('Outlet Data'!K849,L849,'Outlet Data'!N849,M849) -> DhakaNarsingdiCommercial HubNon-PNP | F849: =CONCATENATE(L849,Q849,M849) -> Narsingdiথানা সদরNon-PNP | G849: =CONCATENATE(L849,M849) -> NarsingdiNon-PNP | H849: 46100 | I849: 2326 | J849: =IF(I849="","",IF(I849<=1000,"Below 1000 SFT",IF(I849>10000,"More Then 10000 SFT",(INT((I849-1001)/500)*500+1001)&" - "&(INT((I849-1001)/500)*500+1500)&" SFT"))) -> 2001 - 2500 SFT | K849: Dhaka | L849: Narsingdi | M849: Non-PNP | N849: Commercial Hub | O849: L | P849: C | Q849: থানা সদর | R849: Dhaka | S849: 969955 | T849: 417.00559 | U849: 756188.5 | V849: 1236672.5 | W849: 1527330.2 | X849: 1154607.1 | Y849: 1987166.7 | Z849: 7 | AA849: L1 Exact: All Criteria | AB849: SFT Band + Division + PNP Non PNP status + Location Type + Population Density + Income Level + Location Type (D,T,D) + E-Com + Dhaka/Out of Dhaka N | AC849: Below P25 | AD849: -557375.2 | AE849: -0.36493431 | AF849: 0.006925451 | AI849: 436520 | AJ849: 1075857 | AK849: 1397488 | AN849: -2826.4439 | AO849: 3906.1224 | AP849: 19072.449 | AQ849: 0.054713546 | AR849: =K849&L849 -> DhakaNarsingdi | AS849: 0.004 | AT849: L shape | AU849: Basement floor | AV849: FR
A850: 962 | B850: F921 | C850: Zero Point Senpara | D850: =CONCATENATE(J850,K850,L850,M850,,N850,O850,P850,Q850,AT850,AU850) -> 2001 - 2500 SFTDhakaDhakaNon-PNPWithin the MahallaMBবিভাগীয় শহরSquare ⬜ shapeGround floor | E850: =CONCATENATE('Outlet Data'!K850,L850,'Outlet Data'!N850,M850) -> DhakaDhakaWithin the MahallaNon-PNP | F850: =CONCATENATE(L850,Q850,M850) -> Dhakaবিভাগীয় শহরNon-PNP | G850: =CONCATENATE(L850,M850) -> DhakaNon-PNP | H850: 46100 | I850: 2268 | J850: =IF(I850="","",IF(I850<=1000,"Below 1000 SFT",IF(I850>10000,"More Then 10000 SFT",(INT((I850-1001)/500)*500+1001)&" - "&(INT((I850-1001)/500)*500+1500)&" SFT"))) -> 2001 - 2500 SFT | K850: Dhaka | L850: Dhaka | M850: Non-PNP | N850: Within the Mahalla | O850: M | P850: B | Q850: বিভাগীয় শহর | R850: Dhaka | S850: 1451480 | T850: 639.98236 | U850: 1127106 | V850: 1905559.5 | W850: 1836897.4 | X850: 1451480 | Y850: 2788880.2 | Z850: 9 | AA850: L1 Exact: All Criteria | AB850: SFT Band + Division + PNP Non PNP status + Location Type + Population Density + Income Level + Location Type (D,T,D) + E-Com + Dhaka/Out of Dhaka N | AC850: Within P25–P75 | AD850: -385417.4 | AE850: -0.20981978 | AF850: 0.011213831 | AI850: 543321 | AJ850: 1710891 | AK850: 2100228 | AN850: 8688.5522 | AO850: 858.64447 | AP850: 39282.759 | AQ850: 0.049461731 | AR850: =K850&L850 -> DhakaDhaka | AS850: 0.004 | AT850: Square ⬜ shape | AU850: Ground floor | AV850: FR
A851: 965 | B851: F924 | C851: Jhilim Road Chapainawbganj | D851: =CONCATENATE(J851,K851,L851,M851,,N851,O851,P851,Q851,AT851,AU851) -> Below 1000 SFTRajshahiChapainawabganjNon-PNPWithin the MahallaHBজেলা শহরSquare ⬜ shapeGround floor | E851: =CONCATENATE('Outlet Data'!K851,L851,'Outlet Data'!N851,M851) -> RajshahiChapainawabganjWithin the MahallaNon-PNP | F851: =CONCATENATE(L851,Q851,M851) -> Chapainawabganjজেলা শহরNon-PNP | G851: =CONCATENATE(L851,M851) -> ChapainawabganjNon-PNP | H851: 46106 | I851: 886 | J851: =IF(I851="","",IF(I851<=1000,"Below 1000 SFT",IF(I851>10000,"More Then 10000 SFT",(INT((I851-1001)/500)*500+1001)&" - "&(INT((I851-1001)/500)*500+1500)&" SFT"))) -> Below 1000 SFT | K851: Rajshahi | L851: Chapainawabganj | M851: Non-PNP | N851: Within the Mahalla | O851: H | P851: B | Q851: জেলা শহর | R851: Non Dhaka | S851: 226273.67 | T851: 255.38789 | U851: 154345.5 | V851: 319766 | W851: 496784 | X851: 494034.8 | Y851: 677115 | Z851: 5 | AA851: L4 Balanced: SFT+PNP+Pop+Income+Dhaka | AB851: SFT Band + PNP Non PNP status + Population Density + Income Level + Dhaka/Out of Dhaka N | AC851: Below P25 | AD851: -270510.33 | AE851: -0.54452304 | AF851: -0.21000222 | AI851: 39289 | AJ851: 269402 | AK851: 370130 | AN851: -13646.708 | AO851: -52077.301 | AP851: -76829.905 | AQ851: 0.04852535 | AR851: =K851&L851 -> RajshahiChapainawabganj | AS851: 0.004 | AT851: Square ⬜ shape | AU851: Ground floor | AV851: FR
A852: 709 | B852: F596 | C852: Aditmari Lalmonirhat | D852: =CONCATENATE(J852,K852,L852,M852,,N852,O852,P852,Q852,AT852,AU852) -> 1001 - 1500 SFTRangpurLalmonirhatNon-PNPHigh StreetMBথানা সদরI Shape Ground floor | E852: =CONCATENATE('Outlet Data'!K852,L852,'Outlet Data'!N852,M852) -> RangpurLalmonirhatHigh StreetNon-PNP | F852: =CONCATENATE(L852,Q852,M852) -> Lalmonirhatথানা সদরNon-PNP | G852: =CONCATENATE(L852,M852) -> LalmonirhatNon-PNP | H852: 46112 | I852: 1071 | J852: =IF(I852="","",IF(I852<=1000,"Below 1000 SFT",IF(I852>10000,"More Then 10000 SFT",(INT((I852-1001)/500)*500+1001)&" - "&(INT((I852-1001)/500)*500+1500)&" SFT"))) -> 1001 - 1500 SFT | K852: Rangpur | L852: Lalmonirhat | M852: Non-PNP | N852: High Street | O852: M | P852: B | Q852: থানা সদর | R852: Non Dhaka | S852: 354645.6 | T852: 331.13501 | U852: 0 | V852: 744801 | W852: 843340 | X852: 568975.3 | Y852: 1144384.5 | Z852: 7 | AA852: L2 Strong: SFT+Division+PNP+Pop+Income+Dhaka | AB852: SFT Band + Division + PNP Non PNP status + Population Density + Income Level + Dhaka/Out of Dhaka N | AC852: Below P25 | AD852: -488694.4 | AE852: -0.57947494 | AF852: -0.023276686 | AG852: 0 | AH852: 0 | AI852: 10136 | AJ852: 744801 | AK852: 1018291 | AL852: -1606.3333 | AM852: -1606.3333 | AN852: -1532.4912 | AO852: -17252.93 | AP852: -19276.784 | AQ852: 0.050937229 | AR852: =K852&L852 -> RangpurLalmonirhat | AS852: 0.004 | AT852: I Shape | AU852: Ground floor | AV852: FR
A853: 960 | B853: F915 | C853: Arshinagar Main Road, Keraniganj | D853: =CONCATENATE(J853,K853,L853,M853,,N853,O853,P853,Q853,AT853,AU853) -> 1001 - 1500 SFTDhakaDhakaNon-PNPHigh Street W Residential BlockMCঅন্যান্যSquare ⬜ shapeGround floor | E853: =CONCATENATE('Outlet Data'!K853,L853,'Outlet Data'!N853,M853) -> DhakaDhakaHigh Street W Residential BlockNon-PNP | F853: =CONCATENATE(L853,Q853,M853) -> Dhakaঅন্যান্যNon-PNP | G853: =CONCATENATE(L853,M853) -> DhakaNon-PNP | H853: 46112 | I853: 1212 | J853: =IF(I853="","",IF(I853<=1000,"Below 1000 SFT",IF(I853>10000,"More Then 10000 SFT",(INT((I853-1001)/500)*500+1001)&" - "&(INT((I853-1001)/500)*500+1500)&" SFT"))) -> 1001 - 1500 SFT | K853: Dhaka | L853: Dhaka | M853: Non-PNP | N853: High Street W Residential Block | O853: M | P853: C | Q853: অন্যান্য | R853: Dhaka | S853: 907851.67 | T853: 749.05253 | U853: 525409.5 | V853: 1361541.5 | W853: 1435127.3 | X853: 920723.95 | Y853: 2028621.2 | Z853: 50 | AA853: L2 Strong: SFT+Division+PNP+Pop+Income+Dhaka | AB853: SFT Band + Division + PNP Non PNP status + Population Density + Income Level + Dhaka/Out of Dhaka N | AC853: Below P25 | AD853: -527275.63 | AE853: -0.36740687 | AF853: 0.03788474 | AI853: 472 | AJ853: 1050347 | AK853: 1672736 | AN853: -389.80926 | AO853: 49526.308 | AP853: 54044.676 | AQ853: 0.055014706 | AR853: =K853&L853 -> DhakaDhaka | AS853: 0.004 | AT853: Square ⬜ shape | AU853: Ground floor | AV853: FR
A854: 968 | B854: F930 | C854: Chinispur, Narsingdi | D854: =CONCATENATE(J854,K854,L854,M854,,N854,O854,P854,Q854,AT854,AU854) -> 1001 - 1500 SFTDhakaNarsingdiNon-PNPCommercial HubLCজেলা শহরSquare ⬜ shapeGround floor | E854: =CONCATENATE('Outlet Data'!K854,L854,'Outlet Data'!N854,M854) -> DhakaNarsingdiCommercial HubNon-PNP | F854: =CONCATENATE(L854,Q854,M854) -> Narsingdiজেলা শহরNon-PNP | G854: =CONCATENATE(L854,M854) -> NarsingdiNon-PNP | H854: 46112 | I854: 1038 | J854: =IF(I854="","",IF(I854<=1000,"Below 1000 SFT",IF(I854>10000,"More Then 10000 SFT",(INT((I854-1001)/500)*500+1001)&" - "&(INT((I854-1001)/500)*500+1500)&" SFT"))) -> 1001 - 1500 SFT | K854: Dhaka | L854: Narsingdi | M854: Non-PNP | N854: Commercial Hub | O854: L | P854: C | Q854: জেলা শহর | R854: Dhaka | S854: 672189 | T854: 647.58092 | U854: 449295 | V854: 1007871.5 | W854: 1126199.5 | X854: 866075.6 | Y854: 1499334.4 | Z854: 28 | AA854: L2 Strong: SFT+Division+PNP+Pop+Income+Dhaka | AB854: SFT Band + Division + PNP Non PNP status + Population Density + Income Level + Dhaka/Out of Dhaka N | AC854: Below P25 | AD854: -454010.5 | AE854: -0.40313506 | AF854: 0.017785779 | AI854: 824 | AJ854: 897766 | AK854: 1117977 | AN854: -88.503557 | AO854: 3249.1056 | AP854: 32705.613 | AQ854: 0.057143851 | AR854: =K854&L854 -> DhakaNarsingdi | AS854: 8.1351826e-19 | AT854: Square ⬜ shape | AU854: Ground floor | AV854: FR
A855: 966 | B855: F925 | C855: CEO Office Mor Pirojpur | D855: =CONCATENATE(J855,K855,L855,M855,,N855,O855,P855,Q855,AT855,AU855) -> 1001 - 1500 SFTBarishalBarishalNon-PNPHigh StreetMBজেলা শহরI shapeGround floor | E855: =CONCATENATE('Outlet Data'!K855,L855,'Outlet Data'!N855,M855) -> BarishalBarishalHigh StreetNon-PNP | F855: =CONCATENATE(L855,Q855,M855) -> Barishalজেলা শহরNon-PNP | G855: =CONCATENATE(L855,M855) -> BarishalNon-PNP | H855: 46112 | I855: 1284 | J855: =IF(I855="","",IF(I855<=1000,"Below 1000 SFT",IF(I855>10000,"More Then 10000 SFT",(INT((I855-1001)/500)*500+1001)&" - "&(INT((I855-1001)/500)*500+1500)&" SFT"))) -> 1001 - 1500 SFT | K855: Barishal | L855: Barishal | M855: Non-PNP | N855: High Street | O855: M | P855: B | Q855: জেলা শহর | R855: Non Dhaka | S855: 701522 | T855: 546.3567 | U855: 521741.5 | V855: 1021065.5 | W855: 949666.7 | X855: 686228.35 | Y855: 1376057.9 | Z855: 32 | AA855: L4 Balanced: SFT+PNP+Pop+Income+Dhaka | AB855: SFT Band + PNP Non PNP status + Population Density + Income Level + Dhaka/Out of Dhaka N | AC855: Within P25–P75 | AD855: -248144.7 | AE855: -0.26129662 | AF855: 0.00043326437 | AI855: 62435 | AJ855: 981048 | AK855: 1061083 | AN855: 7011.7591 | AO855: 1128.8948 | AP855: -7228.8205 | AQ855: 0.052929071 | AR855: =K855&L855 -> BarishalBarishal | AS855: 0.004 | AT855: I shape | AU855: Ground floor | AV855: FR
A856: 955 | B856: F905 | C856: Future Town, Bosila, Mohammadpur Outlet | D856: =CONCATENATE(J856,K856,L856,M856,,N856,O856,P856,Q856,AT856,AU856) -> 1001 - 1500 SFTDhakaDhakaNon-PNPWithin the MahallaLBথানা সদরI shapeGround floor | E856: =CONCATENATE('Outlet Data'!K856,L856,'Outlet Data'!N856,M856) -> DhakaDhakaWithin the MahallaNon-PNP | F856: =CONCATENATE(L856,Q856,M856) -> Dhakaথানা সদরNon-PNP | G856: =CONCATENATE(L856,M856) -> DhakaNon-PNP | H856: 46112 | I856: 1288 | J856: =IF(I856="","",IF(I856<=1000,"Below 1000 SFT",IF(I856>10000,"More Then 10000 SFT",(INT((I856-1001)/500)*500+1001)&" - "&(INT((I856-1001)/500)*500+1500)&" SFT"))) -> 1001 - 1500 SFT | K856: Dhaka | L856: Dhaka | M856: Non-PNP | N856: Within the Mahalla | O856: L | P856: B | Q856: থানা সদর | R856: Dhaka | S856: 714190 | T856: 554.49534 | U856: 528109 | V856: 1070885 | W856: 924737.8 | X856: 766540.9 | Y856: 1143521.5 | Z856: 8 | AA856: L2 Strong: SFT+Division+PNP+Pop+Income+Dhaka | AB856: SFT Band + Division + PNP Non PNP status + Population Density + Income Level + Dhaka/Out of Dhaka N | AC856: Below P25 | AD856: -210547.8 | AE856: -0.22768378 | AF856: -0.010534118 | AI856: 800 | AJ856: 1055418 | AK856: 1086352 | AN856: 75.495111 | AO856: -14568 | AP856: -8077.5796 | AQ856: 0.050748956 | AR856: =K856&L856 -> DhakaDhaka | AS856: 0.004 | AT856: I shape | AU856: Ground floor | AV856: FR
A857: 974 | B857: F929 | C857: Godnail, Siddirganj | D857: =CONCATENATE(J857,K857,L857,M857,,N857,O857,P857,Q857,AT857,AU857) -> Below 1000 SFTDhakaDhakaNon-PNPHigh Street W Residential BlockMBঅন্যান্যL shapeGround floor | E857: =CONCATENATE('Outlet Data'!K857,L857,'Outlet Data'!N857,M857) -> DhakaDhakaHigh Street W Residential BlockNon-PNP | F857: =CONCATENATE(L857,Q857,M857) -> Dhakaঅন্যান্যNon-PNP | G857: =CONCATENATE(L857,M857) -> DhakaNon-PNP | H857: 46112 | I857: 200 | J857: =IF(I857="","",IF(I857<=1000,"Below 1000 SFT",IF(I857>10000,"More Then 10000 SFT",(INT((I857-1001)/500)*500+1001)&" - "&(INT((I857-1001)/500)*500+1500)&" SFT"))) -> Below 1000 SFT | K857: Dhaka | L857: Dhaka | M857: Non-PNP | N857: High Street W Residential Block | O857: M | P857: B | Q857: অন্যান্য | R857: Dhaka | S857: 786813.5 | T857: 3934.0675 | U857: 412113.25 | V857: 1161513.8 | W857: 1100252 | X857: 723334 | Y857: 1342015 | Z857: 13 | AA857: L2 Strong: SFT+Division+PNP+Pop+Income+Dhaka | AB857: SFT Band + Division + PNP Non PNP status + Population Density + Income Level + Dhaka/Out of Dhaka N | AC857: Within P25–P75 | AD857: -313438.5 | AE857: -0.28487883 | AF857: -0.0071010798 | AJ857: 37413 | AK857: 1536214 | AO857: -17029.507 | AP857: 5855.0565 | AQ857: 0.2018326 | AR857: =K857&L857 -> DhakaDhaka | AS857: 0.004 | AT857: L shape | AU857: Ground floor | AV857: FR
A858: 967 | B858: F928 | C858: Abul kashem sarak, kamal nagar. Shathkhira | D858: =CONCATENATE(J858,K858,L858,M858,,N858,O858,P858,Q858,AT858,AU858) -> 1501 - 2000 SFTKhulnaSatkhiraNon-PNPHigh Street W Residential BlockMBজেলা শহরSquare ⬜ shapeGround floor | E858: =CONCATENATE('Outlet Data'!K858,L858,'Outlet Data'!N858,M858) -> KhulnaSatkhiraHigh Street W Residential BlockNon-PNP | F858: =CONCATENATE(L858,Q858,M858) -> Satkhiraজেলা শহরNon-PNP | G858: =CONCATENATE(L858,M858) -> SatkhiraNon-PNP | H858: 46112 | I858: 2000 | J858: =IF(I858="","",IF(I858<=1000,"Below 1000 SFT",IF(I858>10000,"More Then 10000 SFT",(INT((I858-1001)/500)*500+1001)&" - "&(INT((I858-1001)/500)*500+1500)&" SFT"))) -> 1501 - 2000 SFT | K858: Khulna | L858: Satkhira | M858: Non-PNP | N858: High Street W Residential Block | O858: M | P858: B | Q858: জেলা শহর | R858: Non Dhaka | S858: 1136249.7 | T858: 568.12483 | U858: 666763.5 | V858: 1703894.5 | W858: 1784220.4 | X858: 1167808 | Y858: 2364199 | Z858: 13 | AA858: L2 Strong: SFT+Division+PNP+Pop+Income+Dhaka | AB858: SFT Band + Division + PNP Non PNP status + Population Density + Income Level + Dhaka/Out of Dhaka N | AC858: Below P25 | AD858: -647970.73 | AE858: -0.36316743 | AF858: 0.024817312 | AI858: 960 | AJ858: 1332567 | AK858: 2075222 | AN858: 56.9036 | AO858: 6115.0708 | AP858: 78424.014 | AQ858: 0.057201396 | AR858: =K858&L858 -> KhulnaSatkhira | AS858: 0.004 | AT858: Square ⬜ shape | AU858: Ground floor | AV858: FR
A859: 928 | B859: D114 | C859: Mogbazar | D859: =CONCATENATE(J859,K859,L859,M859,,N859,O859,P859,Q859,AT859,AU859) -> More Then 10000 SFTDhakaDhakaPNPHigh Street W Residential BlockHBবিভাগীয় শহরSquare ⬜ shapeGround floor | E859: =CONCATENATE('Outlet Data'!K859,L859,'Outlet Data'!N859,M859) -> DhakaDhakaHigh Street W Residential BlockPNP | F859: =CONCATENATE(L859,Q859,M859) -> Dhakaবিভাগীয় শহরPNP | G859: =CONCATENATE(L859,M859) -> DhakaPNP | H859: 46124 | I859: 12600 | J859: =IF(I859="","",IF(I859<=1000,"Below 1000 SFT",IF(I859>10000,"More Then 10000 SFT",(INT((I859-1001)/500)*500+1001)&" - "&(INT((I859-1001)/500)*500+1500)&" SFT"))) -> More Then 10000 SFT | K859: Dhaka | L859: Dhaka | M859: PNP | N859: High Street W Residential Block | O859: H | P859: B | Q859: বিভাগীয় শহর | R859: Dhaka | S859: 9499673.8 | T859: 753.94236 | U859: 0 | V859: 16890265 | W859: 13473965 | X859: 12343334 | Y859: 23910326 | Z859: 5 | AA859: L2 Strong: SFT+Division+PNP+Pop+Income+Dhaka | AB859: SFT Band + Division + PNP Non PNP status + Population Density + Income Level + Dhaka/Out of Dhaka N | AC859: Below P25 | AD859: -3974291.4 | AE859: -0.29496079 | AF859: 0.018573497 | AH859: 0 | AI859: 0 | AJ859: 14781182 | AK859: 23217513 | AM859: -27547.84 | AN859: -273336.44 | AO859: 537176.07 | AP859: 469476.85 | AQ859: 0.057585804 | AR859: =K859&L859 -> DhakaDhaka | AS859: 0.004 | AT859: Square ⬜ shape | AU859: Ground floor | AV859: OWN
A860: 971 | B860: F920 | C860: Sukrabad | D860: =CONCATENATE(J860,K860,L860,M860,,N860,O860,P860,Q860,AT860,AU860) -> Below 1000 SFTDhakaDhakaNon-PNPWithin the MahallaMBবিভাগীয় শহরSquare ⬜ shapeGround floor | E860: =CONCATENATE('Outlet Data'!K860,L860,'Outlet Data'!N860,M860) -> DhakaDhakaWithin the MahallaNon-PNP | F860: =CONCATENATE(L860,Q860,M860) -> Dhakaবিভাগীয় শহরNon-PNP | G860: =CONCATENATE(L860,M860) -> DhakaNon-PNP | H860: 46124 | I860: 1000 | J860: =IF(I860="","",IF(I860<=1000,"Below 1000 SFT",IF(I860>10000,"More Then 10000 SFT",(INT((I860-1001)/500)*500+1001)&" - "&(INT((I860-1001)/500)*500+1500)&" SFT"))) -> Below 1000 SFT | K860: Dhaka | L860: Dhaka | M860: Non-PNP | N860: Within the Mahalla | O860: M | P860: B | Q860: বিভাগীয় শহর | R860: Dhaka | S860: 1342015 | T860: 1342.015 | U860: 1197212.5 | V860: 1486817.5 | W860: 1100252 | X860: 723334 | Y860: 1342015 | Z860: 13 | AA860: L2 Strong: SFT+Division+PNP+Pop+Income+Dhaka | AB860: SFT Band + Division + PNP Non PNP status + Population Density + Income Level + Dhaka/Out of Dhaka N | AC860: Within P25–P75 | AD860: 241763 | AE860: 0.21973421 | AF860: 0.027805341 | AJ860: 1052410 | AK860: 1631620 | AO860: 17685.957 | AP860: 56944.412 | AQ860: 0.16452802 | AR860: =K860&L860 -> DhakaDhaka | AS860: 0.004 | AT860: Square ⬜ shape | AU860: Ground floor | AV860: FR
A861: 927 | B861: D113 | C861: Joar Shahara New | D861: =CONCATENATE(J861,K861,L861,M861,,N861,O861,P861,Q861,AT861,AU861) -> More Then 10000 SFTDhakaDhakaPNPGated CommunityHAবিভাগীয় শহরSquare ⬜ shapeGround floor | E861: =CONCATENATE('Outlet Data'!K861,L861,'Outlet Data'!N861,M861) -> DhakaDhakaGated CommunityPNP | F861: =CONCATENATE(L861,Q861,M861) -> Dhakaবিভাগীয় শহরPNP | G861: =CONCATENATE(L861,M861) -> DhakaPNP | H861: 46128 | I861: 10200 | J861: =IF(I861="","",IF(I861<=1000,"Below 1000 SFT",IF(I861>10000,"More Then 10000 SFT",(INT((I861-1001)/500)*500+1001)&" - "&(INT((I861-1001)/500)*500+1500)&" SFT"))) -> More Then 10000 SFT | K861: Dhaka | L861: Dhaka | M861: PNP | N861: Gated Community | O861: H | P861: A | Q861: বিভাগীয় শহর | R861: Dhaka | S861: 5850206.8 | T861: 573.54968 | U861: 0 | V861: 9979370.8 | W861: 31078402 | X861: 22227387 | Y861: 47171802 | Z861: 11 | AA861: L4 Balanced: SFT+PNP+Pop+Income+Dhaka | AB861: SFT Band + PNP Non PNP status + Population Density + Income Level + Dhaka/Out of Dhaka N | AC861: Below P25 | AD861: -25228195 | AE861: -0.81175973 | AF861: -0.00092858959 | AH861: 0 | AI861: 0 | AJ861: 8258328 | AK861: 15142499 | AM861: -217161.33 | AN861: -453410.3 | AO861: 79541.863 | AP861: 569300 | AQ861: 0.055031149 | AR861: =K861&L861 -> DhakaDhaka | AS861: 0.004 | AT861: Square ⬜ shape | AU861: Ground floor | AV861: OWN
A862: 975 | B862: F931 | C862: Beparipara CTG | D862: =CONCATENATE(J862,K862,L862,M862,,N862,O862,P862,Q862,AT862,AU862) -> 2501 - 3000 SFTChattogramChattogramNon-PNPHigh Street W Residential BlockHAবিভাগীয় শহরOthersGround floor | E862: =CONCATENATE('Outlet Data'!K862,L862,'Outlet Data'!N862,M862) -> ChattogramChattogramHigh Street W Residential BlockNon-PNP | F862: =CONCATENATE(L862,Q862,M862) -> Chattogramবিভাগীয় শহরNon-PNP | G862: =CONCATENATE(L862,M862) -> ChattogramNon-PNP | H862: 46132 | I862: 2665 | J862: =IF(I862="","",IF(I862<=1000,"Below 1000 SFT",IF(I862>10000,"More Then 10000 SFT",(INT((I862-1001)/500)*500+1001)&" - "&(INT((I862-1001)/500)*500+1500)&" SFT"))) -> 2501 - 3000 SFT | K862: Chattogram | L862: Chattogram | M862: Non-PNP | N862: High Street W Residential Block | O862: H | P862: A | Q862: বিভাগীয় শহর | R862: Non Dhaka | S862: 2782461.5 | T862: 1044.0756 | U862: 2288021.2 | V862: 3276901.8 | W862: 2544594.2 | X862: 1771797 | Y862: 3631620.4 | Z862: 41 | AA862: L6 Practical: SFT+PNP+Dhaka | AB862: SFT Band + PNP Non PNP status + Dhaka/Out of Dhaka N | AC862: Within P25–P75 | AD862: 237867.3 | AE862: 0.093479463 | AF862: 0.06939337 | AJ862: 1793581 | AK862: 3771342 | AO862: 100421.81 | AP862: 285746.95 | AQ862: 0.17790147 | AR862: =K862&L862 -> ChattogramChattogram | AS862: 0.004 | AT862: Others | AU862: Ground floor | AV862: FR
A863: 977 | B863: F933 | C863: Targach Gazipur | D863: =CONCATENATE(J863,K863,L863,M863,,N863,O863,P863,Q863,AT863,AU863) -> 1001 - 1500 SFTDhakaGazipurNon-PNPWithin the MahallaMCজেলা শহরI shapeGround floor | E863: =CONCATENATE('Outlet Data'!K863,L863,'Outlet Data'!N863,M863) -> DhakaGazipurWithin the MahallaNon-PNP | F863: =CONCATENATE(L863,Q863,M863) -> Gazipurজেলা শহরNon-PNP | G863: =CONCATENATE(L863,M863) -> GazipurNon-PNP | H863: 46136 | I863: 1163 | J863: =IF(I863="","",IF(I863<=1000,"Below 1000 SFT",IF(I863>10000,"More Then 10000 SFT",(INT((I863-1001)/500)*500+1001)&" - "&(INT((I863-1001)/500)*500+1500)&" SFT"))) -> 1001 - 1500 SFT | K863: Dhaka | L863: Gazipur | M863: Non-PNP | N863: Within the Mahalla | O863: M | P863: C | Q863: জেলা শহর | R863: Dhaka | S863: 870117.5 | T863: 748.16638 | U863: 605472.25 | V863: 1134762.8 | W863: 1435127.3 | X863: 920723.95 | Y863: 2028621.2 | Z863: 50 | AA863: L2 Strong: SFT+Division+PNP+Pop+Income+Dhaka | AB863: SFT Band + Division + PNP Non PNP status + Population Density + Income Level + Dhaka/Out of Dhaka N | AC863: Below P25 | AD863: -565009.8 | AE863: -0.39370013 | AF863: 0.026956181 | AJ863: 340827 | AK863: 1399408 | AO863: 12665.321 | AP863: 34244.768 | AQ863: 0.17111206 | AR863: =K863&L863 -> DhakaGazipur | AS863: 0.004 | AT863: I shape | AU863: Ground floor | AV863: FR
A864: 985 | B864: F941 | C864: Mahajan Para Khagrachari | D864: =CONCATENATE(J864,K864,L864,M864,,N864,O864,P864,Q864,AT864,AU864) -> 1501 - 2000 SFTChattogramKhagrachhariNon-PNPHigh Street W Residential BlockHAজেলা শহরSquare ⬜ shapeSlightly upper than Ground floor | E864: =CONCATENATE('Outlet Data'!K864,L864,'Outlet Data'!N864,M864) -> ChattogramKhagrachhariHigh Street W Residential BlockNon-PNP | F864: =CONCATENATE(L864,Q864,M864) -> Khagrachhariজেলা শহরNon-PNP | G864: =CONCATENATE(L864,M864) -> KhagrachhariNon-PNP | H864: 46138 | I864: 1667 | J864: =IF(I864="","",IF(I864<=1000,"Below 1000 SFT",IF(I864>10000,"More Then 10000 SFT",(INT((I864-1001)/500)*500+1001)&" - "&(INT((I864-1001)/500)*500+1500)&" SFT"))) -> 1501 - 2000 SFT | K864: Chattogram | L864: Khagrachhari | M864: Non-PNP | N864: High Street W Residential Block | O864: H | P864: A | Q864: জেলা শহর | R864: Non Dhaka | S864: 473972.5 | T864: 284.32663 | U864: 303269.75 | V864: 644675.25 | W864: 1208115.2 | X864: 814254.4 | Y864: 2529809.5 | Z864: 7 | AA864: L4 Balanced: SFT+PNP+Pop+Income+Dhaka | AB864: SFT Band + PNP Non PNP status + Population Density + Income Level + Dhaka/Out of Dhaka N | AC864: Below P25 | AD864: -734142.7 | AE864: -0.60767607 | AF864: -0.045000855 | AJ864: 132567 | AK864: 815378 | AO864: -245.42993 | AP864: -42412.905 | AQ864: 0.19811611 | AR864: =K864&L864 -> ChattogramKhagrachhari | AS864: 0.004 | AT864: Square ⬜ shape | AU864: Slightly upper than Ground floor | AV864: FR
A865: 983 | B865: F939 | C865: Tapra Bus Stand Manikganj | D865: =CONCATENATE(J865,K865,L865,M865,,N865,O865,P865,Q865,AT865,AU865) -> 1001 - 1500 SFTDhakaManikganjNon-PNPHigh Street W Residential BlockMCঅন্যান্যSquare ⬜ shapeSlightly upper than Ground floor | E865: =CONCATENATE('Outlet Data'!K865,L865,'Outlet Data'!N865,M865) -> DhakaManikganjHigh Street W Residential BlockNon-PNP | F865: =CONCATENATE(L865,Q865,M865) -> Manikganjঅন্যান্যNon-PNP | G865: =CONCATENATE(L865,M865) -> ManikganjNon-PNP | H865: 46138 | I865: 1104 | J865: =IF(I865="","",IF(I865<=1000,"Below 1000 SFT",IF(I865>10000,"More Then 10000 SFT",(INT((I865-1001)/500)*500+1001)&" - "&(INT((I865-1001)/500)*500+1500)&" SFT"))) -> 1001 - 1500 SFT | K865: Dhaka | L865: Manikganj | M865: Non-PNP | N865: High Street W Residential Block | O865: M | P865: C | Q865: অন্যান্য | R865: Dhaka | S865: 406698.5 | T865: 368.38632 | U865: 250535.25 | V865: 562861.75 | W865: 1435127.3 | X865: 920723.95 | Y865: 2028621.2 | Z865: 50 | AA865: L2 Strong: SFT+Division+PNP+Pop+Income+Dhaka | AB865: SFT Band + Division + PNP Non PNP status + Population Density + Income Level + Dhaka/Out of Dhaka N | AC865: Below P25 | AD865: -1028428.8 | AE865: -0.71661155 | AF865: -0.034191301 | AJ865: 94372 | AK865: 719025 | AO865: -32655.902 | AP865: 4844.8008 | AQ865: 0.19285103 | AR865: =K865&L865 -> DhakaManikganj | AS865: 0.004 | AT865: Square ⬜ shape | AU865: Slightly upper than Ground floor | AV865: FR
A866: 972 | B866: F926 | C866: Victoria College Road Cumilla | D866: =CONCATENATE(J866,K866,L866,M866,,N866,O866,P866,Q866,AT866,AU866) -> Below 1000 SFTChattogramCumillaNon-PNPHigh Street W Residential BlockMBজেলা শহরSquare ⬜ shapeGround floor | E866: =CONCATENATE('Outlet Data'!K866,L866,'Outlet Data'!N866,M866) -> ChattogramCumillaHigh Street W Residential BlockNon-PNP | F866: =CONCATENATE(L866,Q866,M866) -> Cumillaজেলা শহরNon-PNP | G866: =CONCATENATE(L866,M866) -> CumillaNon-PNP | H866: 46139 | I866: 979 | J866: =IF(I866="","",IF(I866<=1000,"Below 1000 SFT",IF(I866>10000,"More Then 10000 SFT",(INT((I866-1001)/500)*500+1001)&" - "&(INT((I866-1001)/500)*500+1500)&" SFT"))) -> Below 1000 SFT | K866: Chattogram | L866: Cumilla | M866: Non-PNP | N866: High Street W Residential Block | O866: M | P866: B | Q866: জেলা শহর | R866: Non Dhaka | S866: 450464.5 | T866: 460.12717 | U866: 267405.75 | V866: 633523.25 | W866: 1039476.4 | X866: 672568 | Y866: 1386312.2 | Z866: 5 | AA866: L2 Strong: SFT+Division+PNP+Pop+Income+Dhaka | AB866: SFT Band + Division + PNP Non PNP status + Population Density + Income Level + Dhaka/Out of Dhaka N | AC866: Below P25 | AD866: -589011.9 | AE866: -0.56664288 | AF866: -0.0065140624 | AJ866: 84347 | AK866: 816582 | AO866: -4571.836 | AP866: -1296.8717 | AQ866: 0.18610293 | AR866: =K866&L866 -> ChattogramCumilla | AS866: 0.004 | AT866: Square ⬜ shape | AU866: Ground floor | AV866: FR
A867: 981 | B867: F937 | C867: Koborstan Amin Model Town Housing | D867: =CONCATENATE(J867,K867,L867,M867,,N867,O867,P867,Q867,AT867,AU867) -> 1001 - 1500 SFTDhakaDhakaNon-PNPWithin the MahallaMBজেলা শহরL shapeGround floor | E867: =CONCATENATE('Outlet Data'!K867,L867,'Outlet Data'!N867,M867) -> DhakaDhakaWithin the MahallaNon-PNP | F867: =CONCATENATE(L867,Q867,M867) -> Dhakaজেলা শহরNon-PNP | G867: =CONCATENATE(L867,M867) -> DhakaNon-PNP | H867: 46140 | I867: 1300 | J867: =IF(I867="","",IF(I867<=1000,"Below 1000 SFT",IF(I867>10000,"More Then 10000 SFT",(INT((I867-1001)/500)*500+1001)&" - "&(INT((I867-1001)/500)*500+1500)&" SFT"))) -> 1001 - 1500 SFT | K867: Dhaka | L867: Dhaka | M867: Non-PNP | N867: Within the Mahalla | O867: M | P867: B | Q867: জেলা শহর | R867: Dhaka | S867: 828435.5 | T867: 637.25808 | U867: 489791.75 | V867: 1167079.2 | W867: 1445730 | X867: 953500.6 | Y867: 1792550.9 | Z867: 55 | AA867: L2 Strong: SFT+Division+PNP+Pop+Income+Dhaka | AB867: SFT Band + Division + PNP Non PNP status + Population Density + Income Level + Dhaka/Out of Dhaka N | AC867: Below P25 | AD867: -617294.5 | AE867: -0.42697772 | AF867: 0.045120511 | AJ867: 151148 | AK867: 1505723 | AO867: 15359.785 | AP867: 59399.082 | AQ867: 0.18136614 | AR867: =K867&L867 -> DhakaDhaka | AS867: 0.004 | AT867: L shape | AU867: Ground floor | AV867: FR
A868: 892 | B868: F829 | C868: Sangita Mor, Narsingdi | D868: =CONCATENATE(J868,K868,L868,M868,,N868,O868,P868,Q868,AT868,AU868) -> 2501 - 3000 SFTDhakaNarsingdiNon-PNPHigh Street W Residential BlockLCজেলা শহরSquare ⬜ shapeGround floor | E868: =CONCATENATE('Outlet Data'!K868,L868,'Outlet Data'!N868,M868) -> DhakaNarsingdiHigh Street W Residential BlockNon-PNP | F868: =CONCATENATE(L868,Q868,M868) -> Narsingdiজেলা শহরNon-PNP | G868: =CONCATENATE(L868,M868) -> NarsingdiNon-PNP | H868: 46141 | I868: 3000 | J868: =IF(I868="","",IF(I868<=1000,"Below 1000 SFT",IF(I868>10000,"More Then 10000 SFT",(INT((I868-1001)/500)*500+1001)&" - "&(INT((I868-1001)/500)*500+1500)&" SFT"))) -> 2501 - 3000 SFT | K868: Dhaka | L868: Narsingdi | M868: Non-PNP | N868: High Street W Residential Block | O868: L | P868: C | Q868: জেলা শহর | R868: Dhaka | S868: 243485.6 | T868: 81.161867 | U868: 0 | V868: 48073 | W868: 658654.3 | X868: 409501.5 | Y868: 877803.35 | Z868: 6 | AA868: L5 Balanced: SFT+PNP+Pop+Income | AB868: SFT Band + PNP Non PNP status + Population Density + Income Level | AC868: Below P25 | AD868: -415168.7 | AE868: -0.63032869 | AF868: -0.22970524 | AG868: 0 | AH868: 0 | AI868: 0 | AJ868: 48073 | AK868: 1169355 | AL868: -17467.75 | AM868: -46564.52 | AN868: -91428.58 | AO868: -69814.572 | AP868: -54374.173 | AQ868: 0.068006655 | AR868: =K868&L868 -> DhakaNarsingdi | AS868: 0.004 | AT868: Square ⬜ shape | AU868: Ground floor | AV868: FR
A869: 978 | B869: F934 | C869: Bilashpur, Jpydebpur | D869: =CONCATENATE(J869,K869,L869,M869,,N869,O869,P869,Q869,AT869,AU869) -> 1001 - 1500 SFTDhakaGazipurNon-PNPWithin the MahallaMBজেলা শহরL shapeSlightly upper than Ground floor | E869: =CONCATENATE('Outlet Data'!K869,L869,'Outlet Data'!N869,M869) -> DhakaGazipurWithin the MahallaNon-PNP | F869: =CONCATENATE(L869,Q869,M869) -> Gazipurজেলা শহরNon-PNP | G869: =CONCATENATE(L869,M869) -> GazipurNon-PNP | H869: 46141 | I869: 1258 | J869: =IF(I869="","",IF(I869<=1000,"Below 1000 SFT",IF(I869>10000,"More Then 10000 SFT",(INT((I869-1001)/500)*500+1001)&" - "&(INT((I869-1001)/500)*500+1500)&" SFT"))) -> 1001 - 1500 SFT | K869: Dhaka | L869: Gazipur | M869: Non-PNP | N869: Within the Mahalla | O869: M | P869: B | Q869: জেলা শহর | R869: Dhaka | S869: 631622.5 | T869: 502.08466 | U869: 346395.75 | V869: 916849.25 | W869: 1445730 | X869: 953500.6 | Y869: 1792550.9 | Z869: 55 | AA869: L2 Strong: SFT+Division+PNP+Pop+Income+Dhaka | AB869: SFT Band + Division + PNP Non PNP status + Population Density + Income Level + Dhaka/Out of Dhaka N | AC869: Below P25 | AD869: -814107.5 | AE869: -0.56311172 | AF869: -0.015017914 | AJ869: 61169 | AK869: 1202076 | AO869: -19005.221 | AP869: 33.916293 | AQ869: 0.19225235 | AR869: =K869&L869 -> DhakaGazipur | AS869: 0.004 | AT869: L shape | AU869: Slightly upper than Ground floor | AV869: FR
A870: 993 | B870: F951 | C870: Waruk Bazar | D870: =CONCATENATE(J870,K870,L870,M870,,N870,O870,P870,Q870,AT870,AU870) -> Below 1000 SFTChattogramChandpurNon-PNPCommercial HubHBঅন্যান্যSquare ⬜ shapeGround floor | E870: =CONCATENATE('Outlet Data'!K870,L870,'Outlet Data'!N870,M870) -> ChattogramChandpurCommercial HubNon-PNP | F870: =CONCATENATE(L870,Q870,M870) -> Chandpurঅন্যান্যNon-PNP | G870: =CONCATENATE(L870,M870) -> ChandpurNon-PNP | H870: 46141 | I870: 972 | J870: =IF(I870="","",IF(I870<=1000,"Below 1000 SFT",IF(I870>10000,"More Then 10000 SFT",(INT((I870-1001)/500)*500+1001)&" - "&(INT((I870-1001)/500)*500+1500)&" SFT"))) -> Below 1000 SFT | K870: Chattogram | L870: Chandpur | M870: Non-PNP | N870: Commercial Hub | O870: H | P870: B | Q870: অন্যান্য | R870: Non Dhaka | S870: 677115 | T870: 696.62037 | U870: 348979.5 | V870: 1005250.5 | W870: 496784 | X870: 494034.8 | Y870: 677115 | Z870: 5 | AA870: L4 Balanced: SFT+PNP+Pop+Income+Dhaka | AB870: SFT Band + PNP Non PNP status + Population Density + Income Level + Dhaka/Out of Dhaka N | AC870: Within P25–P75 | AD870: 180331 | AE870: 0.3629968 | AF870: 0.011993569 | AJ870: 20844 | AK870: 1333386 | AO870: -2217.1783 | AP870: 18459.229 | AQ870: 0.19039512 | AR870: =K870&L870 -> ChattogramChandpur | AS870: 0.004 | AT870: Square ⬜ shape | AU870: Ground floor | AV870: FR
A871: 992 | B871: F950 | C871: Amla Bazar Kushtia | D871: =CONCATENATE(J871,K871,L871,M871,,N871,O871,P871,Q871,AT871,AU871) -> Below 1000 SFTKhulnaKushtiaNon-PNPHigh StreetMBঅন্যান্যSquare ⬜ shapeGround floor | E871: =CONCATENATE('Outlet Data'!K871,L871,'Outlet Data'!N871,M871) -> KhulnaKushtiaHigh StreetNon-PNP | F871: =CONCATENATE(L871,Q871,M871) -> Kushtiaঅন্যান্যNon-PNP | G871: =CONCATENATE(L871,M871) -> KushtiaNon-PNP | H871: 46142 | I871: 950 | J871: =IF(I871="","",IF(I871<=1000,"Below 1000 SFT",IF(I871>10000,"More Then 10000 SFT",(INT((I871-1001)/500)*500+1001)&" - "&(INT((I871-1001)/500)*500+1500)&" SFT"))) -> Below 1000 SFT | K871: Khulna | L871: Kushtia | M871: Non-PNP | N871: High Street | O871: M | P871: B | Q871: অন্যান্য | R871: Non Dhaka | S871: 523004 | T871: 550.53053 | U871: 264005 | V871: 782003 | W871: 974283.3 | X871: 538513.7 | Y871: 1231812.8 | Z871: 18 | AA871: L4 Balanced: SFT+PNP+Pop+Income+Dhaka | AB871: SFT Band + PNP Non PNP status + Population Density + Income Level + Dhaka/Out of Dhaka N | AC871: Below P25 | AD871: -451279.3 | AE871: -0.46319105 | AF871: -0.025166961 | AJ871: 5006 | AK871: 1041002 | AO871: -4146.4577 | AP871: -22178.385 | AQ871: 0.22346178 | AR871: =K871&L871 -> KhulnaKushtia | AS871: 0.004 | AT871: Square ⬜ shape | AU871: Ground floor | AV871: FR
A872: 1005 | B872: F971 | C872: Tajmahal Road, Block C | D872: =CONCATENATE(J872,K872,L872,M872,,N872,O872,P872,Q872,AT872,AU872) -> Below 1000 SFTDhakaDhakaNon-PNPHigh Street W Residential BlockHBবিভাগীয় শহরSquare ⬜ shapeGround floor | E872: =CONCATENATE('Outlet Data'!K872,L872,'Outlet Data'!N872,M872) -> DhakaDhakaHigh Street W Residential BlockNon-PNP | F872: =CONCATENATE(L872,Q872,M872) -> Dhakaবিভাগীয় শহরNon-PNP | G872: =CONCATENATE(L872,M872) -> DhakaNon-PNP | H872: 46142 | I872: 900 | J872: =IF(I872="","",IF(I872<=1000,"Below 1000 SFT",IF(I872>10000,"More Then 10000 SFT",(INT((I872-1001)/500)*500+1001)&" - "&(INT((I872-1001)/500)*500+1500)&" SFT"))) -> Below 1000 SFT | K872: Dhaka | L872: Dhaka | M872: Non-PNP | N872: High Street W Residential Block | O872: H | P872: B | Q872: বিভাগীয় শহর | R872: Dhaka | S872: 402266 | T872: 446.96222 | U872: 203843.5 | V872: 600688.5 | W872: 1346407.6 | X872: 627753 | Y872: 2031422.6 | Z872: 5 | AA872: L2 Strong: SFT+Division+PNP+Pop+Income+Dhaka | AB872: SFT Band + Division + PNP Non PNP status + Population Density + Income Level + Dhaka/Out of Dhaka N | AC872: Below P25 | AD872: -944141.6 | AE872: -0.70123015 | AF872: -0.019821043 | AJ872: 5421 | AK872: 799111 | AO872: 256.35962 | AP872: -16203.023 | AQ872: 0.16167856 | AR872: =K872&L872 -> DhakaDhaka | AS872: 0.004 | AT872: Square ⬜ shape | AU872: Ground floor | AV872: FR
A873: 1001 | B873: F966 | C873: HK Tower, Road 5, Chad Udyan | D873: =CONCATENATE(J873,K873,L873,M873,,N873,O873,P873,Q873,AT873,AU873) -> 1001 - 1500 SFTDhakaDhakaNon-PNPWithin the MahallaMCবিভাগীয় শহরSquare ⬜ shapeSlightly upper than Ground floor | E873: =CONCATENATE('Outlet Data'!K873,L873,'Outlet Data'!N873,M873) -> DhakaDhakaWithin the MahallaNon-PNP | F873: =CONCATENATE(L873,Q873,M873) -> Dhakaবিভাগীয় শহরNon-PNP | G873: =CONCATENATE(L873,M873) -> DhakaNon-PNP | H873: 46142 | I873: 1185 | J873: =IF(I873="","",IF(I873<=1000,"Below 1000 SFT",IF(I873>10000,"More Then 10000 SFT",(INT((I873-1001)/500)*500+1001)&" - "&(INT((I873-1001)/500)*500+1500)&" SFT"))) -> 1001 - 1500 SFT | K873: Dhaka | L873: Dhaka | M873: Non-PNP | N873: Within the Mahalla | O873: M | P873: C | Q873: বিভাগীয় শহর | R873: Dhaka | S873: 355054.5 | T873: 299.62405 | U873: 178981.75 | V873: 531127.25 | W873: 1796385.8 | X873: 1234693.5 | Y873: 2351918.3 | Z873: 14 | AA873: L1 Exact: All Criteria | AB873: SFT Band + Division + PNP Non PNP status + Location Type + Population Density + Income Level + Location Type (D,T,D) + E-Com + Dhaka/Out of Dhaka N | AC873: Below P25 | AD873: -1441331.3 | AE873: -0.80235064 | AF873: -0.036076399 | AJ873: 2909 | AK873: 707200 | AO873: -142.85024 | AP873: -25475.325 | AQ873: 0.037401135 | AR873: =K873&L873 -> DhakaDhaka | AS873: 0.004 | AT873: Square ⬜ shape | AU873: Slightly upper than Ground floor | AV873: FR
A874: 1002 | B874: F967 | C874: F967 - Chandipool, Dakshin Surma, Sylhet | D874: =CONCATENATE(J874,K874,L874,M874,,N874,O874,P874,Q874,AT874,AU874) -> 1501 - 2000 SFTSylhetSylhetNon-PNPHigh Street W Residential BlockMBজেলা শহরOthersGround floor | E874: =CONCATENATE('Outlet Data'!K874,L874,'Outlet Data'!N874,M874) -> SylhetSylhetHigh Street W Residential BlockNon-PNP | F874: =CONCATENATE(L874,Q874,M874) -> Sylhetজেলা শহরNon-PNP | G874: =CONCATENATE(L874,M874) -> SylhetNon-PNP | H874: 46142 | I874: 1800 | J874: =IF(I874="","",IF(I874<=1000,"Below 1000 SFT",IF(I874>10000,"More Then 10000 SFT",(INT((I874-1001)/500)*500+1001)&" - "&(INT((I874-1001)/500)*500+1500)&" SFT"))) -> 1501 - 2000 SFT | K874: Sylhet | L874: Sylhet | M874: Non-PNP | N874: High Street W Residential Block | O874: M | P874: B | Q874: জেলা শহর | R874: Non Dhaka | S874: 404122.5 | T874: 224.5125 | U874: 202464.25 | V874: 605780.75 | W874: 1446177.2 | X874: 1203978.4 | Y874: 1659596.8 | Z874: 9 | AA874: L2 Strong: SFT+Division+PNP+Pop+Income+Dhaka | AB874: SFT Band + Division + PNP Non PNP status + Population Density + Income Level + Dhaka/Out of Dhaka N | AC874: Below P25 | AD874: -1042054.7 | AE874: -0.7205581 | AF874: -0.025767311 | AJ874: 806 | AK874: 807439 | AO874: -9186.8056 | AP874: -11639.494 | AQ874: 0.046342735 | AR874: =K874&L874 -> SylhetSylhet | AS874: 0.004 | AT874: Others | AU874: Ground floor | AV874: FR
A875: 991 | B875: F949 | C875: Chowrongi Mor, Magura | D875: =CONCATENATE(J875,K875,L875,M875,,N875,O875,P875,Q875,AT875,AU875) -> 1001 - 1500 SFTKhulnaMaguraNon-PNPHigh Street W Residential BlockMBজেলা শহরSquare ⬜ shapeGround floor | E875: =CONCATENATE('Outlet Data'!K875,L875,'Outlet Data'!N875,M875) -> KhulnaMaguraHigh Street W Residential BlockNon-PNP | F875: =CONCATENATE(L875,Q875,M875) -> Maguraজেলা শহরNon-PNP | G875: =CONCATENATE(L875,M875) -> MaguraNon-PNP | H875: 46142 | I875: 1160 | J875: =IF(I875="","",IF(I875<=1000,"Below 1000 SFT",IF(I875>10000,"More Then 10000 SFT",(INT((I875-1001)/500)*500+1001)&" - "&(INT((I875-1001)/500)*500+1500)&" SFT"))) -> 1001 - 1500 SFT | K875: Khulna | L875: Magura | M875: Non-PNP | N875: High Street W Residential Block | O875: M | P875: B | Q875: জেলা শহর | R875: Non Dhaka | S875: 626182 | T875: 539.81207 | U875: 348993.5 | V875: 903370.5 | W875: 774190.53 | X875: 651933.81 | Y875: 1290955.3 | Z875: 6 | AA875: L2 Strong: SFT+Division+PNP+Pop+Income+Dhaka | AB875: SFT Band + Division + PNP Non PNP status + Population Density + Income Level + Dhaka/Out of Dhaka N | AC875: Below P25 | AD875: -148008.53 | AE875: -0.19117842 | AF875: -0.022604102 | AJ875: 71805 | AK875: 1180559 | AO875: 1327.4722 | AP875: -29636.036 | AQ875: 0.16174468 | AR875: =K875&L875 -> KhulnaMagura | AS875: 0.004 | AT875: Square ⬜ shape | AU875: Ground floor | AV875: FR
A876: 982 | B876: F938 | C876: Moksepur Gopalgonj | D876: =CONCATENATE(J876,K876,L876,M876,,N876,O876,P876,Q876,AT876,AU876) -> 1501 - 2000 SFTDhakaGopalganjNon-PNPCommercial HubMBথানা সদরI shapeGround floor | E876: =CONCATENATE('Outlet Data'!K876,L876,'Outlet Data'!N876,M876) -> DhakaGopalganjCommercial HubNon-PNP | F876: =CONCATENATE(L876,Q876,M876) -> Gopalganjথানা সদরNon-PNP | G876: =CONCATENATE(L876,M876) -> GopalganjNon-PNP | H876: 46142 | I876: 1750 | J876: =IF(I876="","",IF(I876<=1000,"Below 1000 SFT",IF(I876>10000,"More Then 10000 SFT",(INT((I876-1001)/500)*500+1001)&" - "&(INT((I876-1001)/500)*500+1500)&" SFT"))) -> 1501 - 2000 SFT | K876: Dhaka | L876: Gopalganj | M876: Non-PNP | N876: Commercial Hub | O876: M | P876: B | Q876: থানা সদর | R876: Dhaka | S876: 949848.5 | T876: 542.77057 | U876: 475581.25 | V876: 1424115.8 | W876: 2241169.2 | X876: 1161639.8 | Y876: 2544561.8 | Z876: 9 | AA876: L1 Exact: All Criteria | AB876: SFT Band + Division + PNP Non PNP status + Location Type + Population Density + Income Level + Location Type (D,T,D) + E-Com + Dhaka/Out of Dhaka N | AC876: Below P25 | AD876: -1291320.7 | AE876: -0.57618171 | AF876: 0.047979272 | AJ876: 1314 | AK876: 1898383 | AO876: -3952.6015 | AP876: 95098.68 | AQ876: 0.17502853 | AR876: =K876&L876 -> DhakaGopalganj | AS876: 0.004 | AT876: I shape | AU876: Ground floor | AV876: FR
A877: 996 | B877: F957 | C877: Dumni Bazar,kilkhet | D877: =CONCATENATE(J877,K877,L877,M877,,N877,O877,P877,Q877,AT877,AU877) -> 1001 - 1500 SFTDhakaDhakaNon-PNPCommercial HubMBবিভাগীয় শহরSquare ⬜ shapeGround floor | E877: =CONCATENATE('Outlet Data'!K877,L877,'Outlet Data'!N877,M877) -> DhakaDhakaCommercial HubNon-PNP | F877: =CONCATENATE(L877,Q877,M877) -> Dhakaবিভাগীয় শহরNon-PNP | G877: =CONCATENATE(L877,M877) -> DhakaNon-PNP | H877: 46142 | I877: 1500 | J877: =IF(I877="","",IF(I877<=1000,"Below 1000 SFT",IF(I877>10000,"More Then 10000 SFT",(INT((I877-1001)/500)*500+1001)&" - "&(INT((I877-1001)/500)*500+1500)&" SFT"))) -> 1001 - 1500 SFT | K877: Dhaka | L877: Dhaka | M877: Non-PNP | N877: Commercial Hub | O877: M | P877: B | Q877: বিভাগীয় শহর | R877: Dhaka | S877: 1134671 | T877: 756.44733 | U877: 567695.5 | V877: 1701646.5 | W877: 1445730 | X877: 953500.6 | Y877: 1792550.9 | Z877: 55 | AA877: L2 Strong: SFT+Division+PNP+Pop+Income+Dhaka | AB877: SFT Band + Division + PNP Non PNP status + Population Density + Income Level + Dhaka/Out of Dhaka N | AC877: Within P25–P75 | AD877: -311059 | AE877: -0.21515705 | AF877: 0.048024448 | AJ877: 720 | AK877: 2268622 | AO877: 124.48344 | AP877: 108859.41 | AQ877: 0.26779167 | AR877: =K877&L877 -> DhakaDhaka | AS877: 0.004 | AT877: Square ⬜ shape | AU877: Ground floor | AV877: FR
A878: 976 | B878: F932 | C878: Fayla Bazar | D878: =CONCATENATE(J878,K878,L878,M878,,N878,O878,P878,Q878,AT878,AU878) -> 1501 - 2000 SFTKhulnaBagerhatNon-PNPCommercial HubMBঅন্যান্যL shapeGround floor | E878: =CONCATENATE('Outlet Data'!K878,L878,'Outlet Data'!N878,M878) -> KhulnaBagerhatCommercial HubNon-PNP | F878: =CONCATENATE(L878,Q878,M878) -> Bagerhatঅন্যান্যNon-PNP | G878: =CONCATENATE(L878,M878) -> BagerhatNon-PNP | H878: 46142 | I878: 1700 | J878: =IF(I878="","",IF(I878<=1000,"Below 1000 SFT",IF(I878>10000,"More Then 10000 SFT",(INT((I878-1001)/500)*500+1001)&" - "&(INT((I878-1001)/500)*500+1500)&" SFT"))) -> 1501 - 2000 SFT | K878: Khulna | L878: Bagerhat | M878: Non-PNP | N878: Commercial Hub | O878: M | P878: B | Q878: অন্যান্য | R878: Non Dhaka | S878: 596058 | T878: 350.62235 | U878: 443084 | V878: 749032 | W878: 1784220.4 | X878: 1167808 | Y878: 2364199 | Z878: 13 | AA878: L2 Strong: SFT+Division+PNP+Pop+Income+Dhaka | AB878: SFT Band + Division + PNP Non PNP status + Population Density + Income Level + Dhaka/Out of Dhaka N | AC878: Below P25 | AD878: -1188162.4 | AE878: -0.66592804 | AF878: -0.016885141 | AJ878: 290110 | AK878: 902006 | AO878: -65271.313 | AP878: 45142.265 | AQ878: 0.18156692 | AR878: =K878&L878 -> KhulnaBagerhat | AS878: 0.004 | AT878: L shape | AU878: Ground floor | AV878: FR
A879: 999 | B879: F963 | C879: Gangra Bazar, Chauddagram, Cumilla | D879: =CONCATENATE(J879,K879,L879,M879,,N879,O879,P879,Q879,AT879,AU879) -> 1001 - 1500 SFTChattogramCumillaNon-PNPHigh Street W Residential BlockLCঅন্যান্যSquare ⬜ shapeGround floor | E879: =CONCATENATE('Outlet Data'!K879,L879,'Outlet Data'!N879,M879) -> ChattogramCumillaHigh Street W Residential BlockNon-PNP | F879: =CONCATENATE(L879,Q879,M879) -> Cumillaঅন্যান্যNon-PNP | G879: =CONCATENATE(L879,M879) -> CumillaNon-PNP | H879: 46142 | I879: 1481 | J879: =IF(I879="","",IF(I879<=1000,"Below 1000 SFT",IF(I879>10000,"More Then 10000 SFT",(INT((I879-1001)/500)*500+1001)&" - "&(INT((I879-1001)/500)*500+1500)&" SFT"))) -> 1001 - 1500 SFT | K879: Chattogram | L879: Cumilla | M879: Non-PNP | N879: High Street W Residential Block | O879: L | P879: C | Q879: অন্যান্য | R879: Non Dhaka | S879: 648874 | T879: 438.13234 | U879: 329526.5 | V879: 968221.5 | W879: 1267205 | X879: 882086.6 | Y879: 1558045 | Z879: 13 | AA879: L2 Strong: SFT+Division+PNP+Pop+Income+Dhaka | AB879: SFT Band + Division + PNP Non PNP status + Population Density + Income Level + Dhaka/Out of Dhaka N | AC879: Below P25 | AD879: -618331 | AE879: -0.48794867 | AF879: 0.024366651 | AJ879: 10179 | AK879: 1287569 | AO879: -5122.9133 | AP879: 36744.686 | AQ879: 0.18239044 | AR879: =K879&L879 -> ChattogramCumilla | AS879: 0.004 | AT879: Square ⬜ shape | AU879: Ground floor | AV879: FR
A880: 257 | B880: F513 | C880: Gorai Bazar Tangail | D880: =CONCATENATE(J880,K880,L880,M880,,N880,O880,P880,Q880,AT880,AU880) -> 2001 - 2500 SFTDhakaTangailNon-PNPIndustrialMBঅন্যান্যI shapeGround floor | E880: =CONCATENATE('Outlet Data'!K880,L880,'Outlet Data'!N880,M880) -> DhakaTangailIndustrialNon-PNP | F880: =CONCATENATE(L880,Q880,M880) -> Tangailঅন্যান্যNon-PNP | G880: =CONCATENATE(L880,M880) -> TangailNon-PNP | H880: 45588 | I880: 2275 | J880: =IF(I880="","",IF(I880<=1000,"Below 1000 SFT",IF(I880>10000,"More Then 10000 SFT",(INT((I880-1001)/500)*500+1001)&" - "&(INT((I880-1001)/500)*500+1500)&" SFT"))) -> 2001 - 2500 SFT | K880: Dhaka | L880: Tangail | M880: Non-PNP | N880: Industrial | O880: M | P880: B | Q880: অন্যান্য | R880: Dhaka | S880: 2334438.2 | T880: 1026.1267 | U880: 2274625 | V880: 2464295 | W880: 2241169.2 | X880: 1560783.8 | Y880: 3069073.6 | Z880: 59 | AA880: L2 Strong: SFT+Division+PNP+Pop+Income+Dhaka | AB880: SFT Band + Division + PNP Non PNP status + Population Density + Income Level + Dhaka/Out of Dhaka N | AC880: Within P25–P75 | AD880: 93269 | AE880: 0.041616224 | AF880: 0.056902917 | AG880: 2417223 | AH880: 2274625 | AI880: 2665605 | AJ880: 1850443 | AK880: 2464295 | AL880: 138593.7 | AM880: 128062.44 | AN880: 164123.53 | AO880: 83183.187 | AP880: 150218.86 | AQ880: 0.15848671 | AR880: =K880&L880 -> DhakaTangail | AS880: 0.004 | AT880: I shape | AU880: Ground floor | AV880: FR
